Workbook

Sheet Income Statement
A1: Company: Alphabet Inc. (GOOGL)
A2: Statement: Consolidated Statements of Income
A3: Units: USD in Millions
A4: Source: SEC 10-K filings, as filed (acc. 0001652044-26-000018 / 0001652044-24-000022 / 0001652044-22-000019 / 0001652044-20-000008 / 0001652044-18-000007; each year from the newest filing covering it)
A5: DEMO WORKBOOK: financial data as filed with the SEC (real); model inputs ILLUSTRATIVE ONLY — not analysis, not advice.
A6: Line Item | B6: 42735 | C6: 43100 | D6: 43465 | E6: 43830 | F6: 44196 | G6: 44561 | H6: 44926 | I6: 45291 | J6: 45657 | K6: 46022
A7: Revenues | B7: 90272 | C7: 110855 | D7: 136819 | E7: 161857 | F7: 182527 | G7: 257637 | H7: 282836 | I7: 307394 | J7: 350018 | K7: 402836
A8: Cost of revenues | B8: -35138 | C8: -45583 | D8: -59549 | E8: -71896 | F8: -84732 | G8: -110939 | H8: -126203 | I8: -133332 | J8: -146306 | K8: -162535
A9: Gross profit | B9: =B7+B8 | C9: =C7+C8 | D9: =D7+D8 | E9: =E7+E8 | F9: =F7+F8 | G9: =G7+G8 | H9: =H7+H8 | I9: =I7+I8 | ... K9: =K7+K8
A10: Research and development | B10: -13948 | C10: -16625 | D10: -21419 | E10: -26018 | F10: -27573 | G10: -31562 | H10: -39500 | I10: -45427 | J10: -49326 | K10: -61087
A11: Sales and marketing | B11: -10485 | C11: -12893 | D11: -16333 | E11: -18464 | F11: -17946 | G11: -22912 | H11: -26567 | I11: -27917 | J11: -27808 | K11: -28693
A12: General and administrative | B12: -6985 | C12: -6840 | D12: -6923 | E12: -9551 | F12: -11052 | G12: -13510 | H12: -15724 | I12: -16425 | J12: -14188 | K12: -21482
A13: European Commission fines | B13: 0 | C13: -2736 | D13: -5071 | E13: -1697 | F13: 0
A14: Total costs and expenses | B14: -66556 | C14: -84677 | D14: -109295 | E14: -127626 | F14: -141303 | G14: -178923 | H14: -207994 | I14: -223101 | J14: -237628 | K14: -273797
A15: Income from operations | B15: 23716 | C15: 26178 | D15: 27524 | E15: 34231 | F15: 41224 | G15: 78714 | H15: 74842 | I15: 84293 | J15: 112390 | K15: 129039
A16: Other income (expense), net | B16: 434 | C16: 1015 | D16: 7389 | E16: 5394 | F16: 6858 | G16: 12020 | H16: -3514 | I16: 1424 | J16: 7425 | K16: 29787
A17: Income before income taxes | B17: 24150 | C17: 27193 | D17: 34913 | E17: 39625 | F17: 48082 | G17: 90734 | H17: 71328 | I17: 85717 | J17: 119815 | K17: 158826
A18: Provision for income taxes | B18: -4672 | C18: -14531 | D18: -4177 | E18: -5282 | F18: -7813 | G18: -14701 | H18: -11356 | I18: -11922 | J18: -19697 | K18: -26656
A19: Net income | B19: 19478 | C19: 12662 | D19: 30736 | E19: 34343 | F19: 40269 | G19: 76033 | H19: 59972 | I19: 73795 | J19: 100118 | K19: 132170
A21: Basic earnings per share | B21: 28.32 | C21: 18.27 | D21: 44.22 | E21: 49.59 | F21: 2.96 | G21: 5.69 | H21: 4.59 | I21: 5.84 | J21: 8.13 | K21: 10.91
A22: Diluted earnings per share | B22: 27.85 | C22: 18 | D22: 43.7 | E22: 49.16 | F22: 2.93 | G22: 5.61 | H22: 4.56 | I22: 5.8 | J22: 8.04 | K22: 10.81
A23: Basic shares outstanding (M, wtd avg) | H23: 13063 | I23: 12630 | J23: 12319 | K23: 12116
A24: Diluted shares outstanding (M, wtd avg) | H24: 13159 | I24: 12722 | J24: 12447 | K24: 12230
A26: Note: EPS and weighted-average shares as filed (newest filing wins): FY2016-FY2019 pre 20-for-1 split (Jul 2022); FY2020 onward split-adjusted. Pre-2022 share counts were class-dimensioned in XBRL and are omitted.
A28: QUARTERLY (AS-FILED 10-Q; Q4 DERIVED)
A29: As-filed 10-Q discrete quarters (annual sign conventions: expenses negative). Q4 derived: IS/CF = annual FY column − Σ(Q1–Q3); BS = fiscal year-end (10-K). EPS/share rows non-additive (no Q4).
B31: Q1 2024 | C31: Q2 2024 | D31: Q3 2024 | E31: Q4 2024 | F31: Q1 2025 | G31: Q2 2025 | H31: Q3 2025 | I31: Q4 2025 | J31: Q1 2026
A32: Line Item | B32: 45382 | C32: 45473 | D32: 45565 | E32: 45657 | F32: 45747 | G32: 45838 | H32: 45930 | I32: 46022 | J32: 46112
A34: Revenues | B34: 80539 | C34: 84742 | D34: 88268 | E34: 96469 | F34: 90234 | G34: 96428 | H34: 102346 | I34: 113828 | J34: 109896
A35: Cost of revenues | B35: -33712 | C35: -35507 | D35: -36474 | E35: -40613 | F35: -36361 | G35: -39039 | H35: -41369 | I35: -45766 | J35: -41271
A36: Gross profit | B36: =B34+B35 | C36: =C34+C35 | D36: =D34+D35 | E36: =E34+E35 | F36: =F34+F35 | G36: =G34+G35 | H36: =H34+H35 | I36: =I34+I35 | J36: =J34+J35
A37: Research and development | B37: -11903 | C37: -11860 | D37: -12447 | E37: -13116 | F37: -13556 | G37: -13808 | H37: -15151 | I37: -18572 | J37: -17032
A38: Sales and marketing | B38: -6426 | C38: -6792 | D38: -7227 | E38: -7363 | F38: -6172 | G38: -7101 | H38: -7205 | I38: -8215 | J38: -7606
A39: General and administrative | B39: -3026 | C39: -3158 | D39: -3599 | E39: -4405 | F39: -3539 | G39: -5209 | H39: -7393 | I39: -5341 | J39: -4291
A40: European Commission fines
A41: Total costs and expenses | B41: -55067 | C41: -57317 | D41: -59747 | E41: -65497 | F41: -59628 | G41: -65157 | H41: -71118 | I41: -77894 | J41: -70200
A42: Income from operations | B42: 25472 | C42: 27425 | D42: 28521 | E42: 30972 | F42: 30606 | G42: 31271 | H42: 31228 | I42: 35934 | J42: 39696
A43: Other income (expense), net | B43: 2843 | C43: 126 | D43: 3185 | E43: 1271 | F43: 11183 | G43: 2662 | H43: 12759 | I43: 3183 | J43: 37716
A44: Income before income taxes | B44: 28315 | C44: 27551 | D44: 31706 | E44: 32243 | F44: 41789 | G44: 33933 | H44: 43987 | I44: 39117 | J44: 77412
A45: Provision for income taxes | B45: -4653 | C45: -3932 | D45: -5405 | E45: -5707 | F45: -7249 | G45: -5737 | H45: -9008 | I45: -4662 | J45: -14834
A46: Net income | B46: 23662 | C46: 23619 | D46: 26301 | E46: 26536 | F46: 34540 | G46: 28196 | H46: 34979 | I46: 34455 | J46: 62578
A48: Basic earnings per share | B48: 1.91 | C48: 1.91 | D48: 2.14 | F48: 2.84 | G48: 2.33 | H48: 2.89 | J48: 5.17
A49: Diluted earnings per share | B49: 1.89 | C49: 1.89 | D49: 2.12 | F49: 2.81 | G49: 2.31 | H49: 2.87 | J49: 5.11
A50: Basic shares outstanding (M, wtd avg) | B50: 12415 | C50: 12343 | D50: 12290 | F50: 12183 | G50: 12122 | H50: 12086 | J50: 12099
A51: Diluted shares outstanding (M, wtd avg) | B51: 12527 | C51: 12495 | D51: 12419 | F51: 12291 | G51: 12198 | H51: 12203 | J51: 12238
A53: Source 10-Qs: Q1 2024 0001652044-24-000053; Q2 2024 0001652044-24-000079; Q3 2024 0001652044-24-000118; Q1 2025 0001652044-25-000043; Q2 2025 0001652044-25-000062; Q3 2025 0001652044-25-000091; Q1 2026 0001652044-26-000048
A55: CORE EARNINGS BRIDGE (NON-RECURRING ITEMS STRIPPED)
A56: Items identified from public filings (source + evidence quote + confidence in the notes column). Toggle 'x' = strip from core. Amounts are PRETAX effects at as-filed sign (charge negative). Tax on adjustments defaults to the year's effective rate (blue row - editable). Core NOPAT uses the model's definition (NI + after-tax net interest).
A58: ANNUAL
A59: Line Item | B59: ='Income Statement'!B6 | C59: ='Income Statement'!C6 | D59: ='Income Statement'!D6 | E59: ='Income Statement'!E6 | F59: ='Income Statement'!F6 | G59: ='Income Statement'!G6 | H59: ='Income Statement'!H6 | I59: ='Income Statement'!I6 | ... K59: ='Income Statement'!K6 | L59: Include? (x) | M59: Source / evidence
A60: Reported pretax income | B60: ='Income Statement'!B17 | C60: ='Income Statement'!C17 | D60: ='Income Statement'!D17 | E60: ='Income Statement'!E17 | F60: ='Income Statement'!F17 | G60: ='Income Statement'!G17 | H60: ='Income Statement'!H17 | I60: ='Income Statement'!I17 | ... K60: ='Income Statement'!K17
A61: FY2016: Loss on marketable securities, net (pre-ASU 2016-01 presentation) [Other income (expense), net] | B61: -210 | L61: x | M61: [disclosed] 10-K 0001652044-17-000008, Note 5 OI&E components — OI&E note FY2016: 'Gain (loss) on marketable securities, net (210)'.
A62: FY2016: Loss on non-marketable investments, net (pre-ASU 2016-01 presentation) [Other income (expense), net] | B62: -65 | L62: x | M62: [disclosed] 10-K 0001652044-17-000008, Note 5 OI&E components — OI&E note FY2016: 'Gain (loss) on non-marketable investments, net (65)'.
A63: FY2016: No discrete non-recurring operating items identified [Revenues] | B63: 0 | M63: [disclosed] 10-K 0001652044-17-000008 (FY2016), MD&A + Notes review — No EC fines, restructuring, impairment, or separately disclosed legal settlements >$200M in the FY2016 10-K.
A64: FY2017: European Commission fine (Shopping, June 2017, EUR 2.4B) [European Commission fines] | C64: -2736 | L64: x | M64: [disclosed] 10-K 0001652044-18-000007, Consolidated Statements of Income + MD&A 'European Commission Fine' — FY2017 income statement carries separate line 'European Commission fine 2,736'; MD&A: fine of EUR 2.4 billion (
A65: FY2017: Loss on marketable securities, net (pre-ASU 2016-01 presentation) [Other income (expense), net] | C65: -80 | L65: x | M65: [disclosed] 10-K 0001652044-18-000007, OI&E note — OI&E note FY2017: 'Loss on marketable securities, net (80)'.
A66: FY2017: Loss on non-marketable investments, net (pre-ASU 2016-01 presentation) [Other income (expense), net] | C66: -114 | L66: x | M66: [disclosed] 10-K 0001652044-18-000007, OI&E note — OI&E note FY2017: 'Loss on non-marketable investments, net (114)'.
A67: FY2018: European Commission fine (Android, July 2018, EUR 4.3B) [European Commission fines] | D67: -5071 | L67: x | M67: [disclosed] 10-K 0001652044-19-000004, Consolidated Statements of Income + MD&A 'European Commission Fines' — FY2018 income statement line 'European Commission fines ... 2,736 / 5,071'; MD&A: EUR 4.3 billion ($5.1 billio
A68: FY2018: Gain on debt securities, net (incl. $1.3B one-time modification gain) [Other income (expense), net] | D68: 1190 | L68: x | M68: [disclosed] 10-K 0001652044-19-000004, OI&E note footnote 3 — 'During the year ended December 31, 2018, the terms of a non-marketable debt security were modified resulting in an unrealized $1.3 billion gain.'
A69: FY2018: Gain on equity securities, net (ASU 2016-01 first effective year) [Other income (expense), net] | D69: 5460 | L69: x | M69: [disclosed] 10-K 0001652044-19-000004, OI&E note — OI&E note: 'Gain (loss) on equity securities, net ... 5,460' for 2018.
A70: FY2018: Legal settlement gain in G&A (amount not disclosed) [General and administrative] | M70: [uncertain] 10-K 0001652044-20-000008 (FY2019), MD&A G&A discussion — FY2019 MD&A: G&A increase 'including a charge of $554 million from a legal settlement in 2019 and the effect of a legal settlement gain recorded in 20
A71: FY2018: Performance fees (tied to equity securities gains) [Other income (expense), net] | D71: -1203 | L71: x | M71: [disclosed] 10-K 0001652044-20-000008 (FY2019), OI&E note footnote 4 — 'Performance fees were reclassified for prior periods from general and administrative expenses to other income (expense), net to conform with current
A72: FY2019: European Commission fine (AdSense for Search, March 2019, EUR 1.5B) [European Commission fines] | E72: -1697 | L72: x | M72: [disclosed] 10-K 0001652044-20-000008, Consolidated Statements of Income + MD&A 'European Commission Fines' — FY2019 income statement line 'European Commission fines ... 5,071 / 1,697'; MD&A: EUR 1.5 billion ($1.7 billio
A73: FY2019: Gain on debt securities, net [Other income (expense), net] | E73: 149 | L73: x | M73: [disclosed] 10-K 0001652044-20-000008, OI&E note — OI&E note 2019: 'Gain (loss) on debt securities, net ... 149'.
A74: FY2019: Gain on equity securities, net [Other income (expense), net] | E74: 2649 | L74: x | M74: [disclosed] 10-K 0001652044-20-000008, OI&E note — OI&E note 2019: 'Gain (loss) on equity securities, net ... 2,649'.
A75: FY2019: Legal settlement charge in G&A [General and administrative] | E75: -554 | L75: x | M75: [disclosed] 10-K 0001652044-21-000010 (FY2020) and 0001652044-20-000008 (FY2019), MD&A G&A discussions — 'The increase was partially offset by a $554 million charge recognized in 2019 relating to a legal settlement.' (FY
A76: FY2019: Performance fees [Other income (expense), net] | E76: -326 | L76: x | M76: [disclosed] 10-K 0001652044-20-000008, OI&E note — OI&E note 2019: 'Performance fees ... (326)'.
A77: FY2020: Gain on debt securities, net [Other income (expense), net] | F77: 725 | L77: x | M77: [disclosed] 10-K 0001652044-21-000010, OI&E note — OI&E note 2020: 'Gain (loss) on debt securities, net ... 725'.
A78: FY2020: Gain on equity securities, net [Other income (expense), net] | F78: 5592 | L78: x | M78: [disclosed] 10-K 0001652044-21-000010, OI&E note — OI&E note 2020: 'Gain (loss) on equity securities, net ... 5,592'.
A79: FY2020: Losses on derivatives hedging marketable equity securities (in OI&E 'Other') [Other income (expense), net] | F79: -902 | L79: x | M79: [disclosed] 10-K 0001652044-21-000010, OI&E note footnote 4 — 'During the year ended December 31, 2020, we entered into derivatives that hedged the changes in fair value of certain marketable equity securities, which res
A80: FY2020: No discrete non-recurring operating items identified [Revenues] | F80: 0 | M80: [disclosed] 10-K 0001652044-21-000010, MD&A + Notes review — No EC fine charges (IS line 0), no restructuring, no separately disclosed legal settlement >$200M in FY2020.
A81: FY2020: Performance fees [Other income (expense), net] | F81: -609 | L81: x | M81: [disclosed] 10-K 0001652044-21-000010, OI&E note — OI&E note 2020: 'Performance fees ... (609)'.
A82: FY2021: Gain on equity securities, net [Other income (expense), net] | G82: 12380 | L82: x | M82: [disclosed] 10-K 0001652044-22-000019, OI&E note — OI&E note 2021: 'Gain (loss) on equity securities, net ... 12,380'.
A83: FY2021: Loss on debt securities, net [Other income (expense), net] | G83: -110 | L83: x | M83: [disclosed] 10-K 0001652044-22-000019, OI&E note — OI&E note 2021: 'Gain (loss) on debt securities, net ... (110)'.
A84: FY2021: Performance fees [Other income (expense), net] | G84: -1908 | L84: x | M84: [disclosed] 10-K 0001652044-22-000019, OI&E note — OI&E note 2021: 'Performance fees ... (1,908)'.
A85: FY2022: European Commission fine reduction (Android fine cut to EUR 4.1B by General Court) [General and administrative] | H85: 217 | L85: x | M85: [disclosed] 10-K 0001652044-23-000016 MD&A; placement per 10-Q 0001652044-22-000090 (Q3 2022) MD&A G&A discussion — 'In 2018 we recognized a charge of $5.1 billion for the fine, which we reduced by $217 million in 2022.'
A86: FY2022: Loss on debt securities, net [Other income (expense), net] | H86: -2064 | L86: x | M86: [disclosed] 10-K 0001652044-23-000016, OI&E note — OI&E note 2022: 'Gain (loss) on debt securities, net ... (2,064)'.
A87: FY2022: Loss on equity securities, net [Other income (expense), net] | H87: -3455 | L87: x | M87: [disclosed] 10-K 0001652044-23-000016, OI&E note — OI&E note 2022: 'Gain (loss) on equity securities, net ... (3,455)'.
A88: FY2022: Performance fees (credit) [Other income (expense), net] | H88: 798 | L88: x | M88: [disclosed] 10-K 0001652044-23-000016, OI&E note — OI&E note 2022: 'Performance fees ... 798'.
A89: FY2023: Accelerated rent and accelerated depreciation (office space optimization, in addition to exit charges) [Cost of revenues] | I89: -269 | M89: [disclosed] 10-K 0001652044-24-000022, MD&A Financial Results highlights — 'In addition to these exit charges, for the year ended December 31, 2023, we incurred $269 million in accelerated rent and accelerated depreciati
A90: FY2023: Employee severance and related charges - Cost of revenues portion [Cost of revenues] | I90: -479 | L90: x | M90: [disclosed] 10-K 0001652044-24-000022, Note 8 'Workforce Reduction and Other Initiatives' — Note 8 table 'Severance and office space exit charges are included within our consolidated statements of income as follows': Cos
A91: FY2023: Employee severance and related charges - G&A portion [General and administrative] | I91: -264 | L91: x | M91: [disclosed] 10-K 0001652044-24-000022, Note 8 — Note 8 table: General and administrative - Severance and Related $264.
A92: FY2023: Employee severance and related charges - R&D portion [Research and development] | I92: -848 | L92: x | M92: [disclosed] 10-K 0001652044-24-000022, Note 8 — Note 8 table: Research and development - Severance and Related $848.
A93: FY2023: Employee severance and related charges - S&M portion [Sales and marketing] | I93: -497 | L93: x | M93: [disclosed] 10-K 0001652044-24-000022, Note 8 — Note 8 table: Sales and marketing - Severance and Related $497.
A94: FY2023: Gain on equity securities, net [Other income (expense), net] | I94: 392 | L94: x | M94: [disclosed] 10-K 0001652044-24-000022, OI&E note — OI&E note 2023: 'Gain (loss) on equity securities, net ... 392'.
A95: FY2023: Google Play states/territories settlement charge [General and administrative] | I95: -700 | M95: [estimated] 10-K 0001652044-24-000022, Note 10 Legal Matters; amount per public settlement terms (Dec 2023), not quantified in filing — 'In September 2023, we reached a settlement in principle with 50 state Attorneys Gen
A96: FY2023: Loss on debt securities, net [Other income (expense), net] | I96: -1215 | L96: x | M96: [disclosed] 10-K 0001652044-24-000022, OI&E note — OI&E note 2023: 'Gain (loss) on debt securities, net ... (1,215)'.
A97: FY2023: Office space optimization exit charges - Cost of revenues portion [Cost of revenues] | I97: -481 | L97: x | M97: [disclosed] 10-K 0001652044-24-000022, Note 8 — Note 8 table: Cost of revenues - Office Space $481.
A98: FY2023: Office space optimization exit charges - G&A portion [General and administrative] | I98: -237 | L98: x | M98: [disclosed] 10-K 0001652044-24-000022, Note 8 — Note 8 table: General and administrative - Office Space $237.
A99: FY2023: Office space optimization exit charges - R&D portion [Research and development] | I99: -870 | L99: x | M99: [disclosed] 10-K 0001652044-24-000022, Note 8 — Note 8 table: Research and development - Office Space $870.
A100: FY2023: Office space optimization exit charges - S&M portion [Sales and marketing] | I100: -257 | L100: x | M100: [disclosed] 10-K 0001652044-24-000022, Note 8 — Note 8 table: Sales and marketing - Office Space $257.
A101: FY2023: Performance fees (credit) [Other income (expense), net] | I101: 257 | L101: x | M101: [disclosed] 10-K 0001652044-24-000022, OI&E note — OI&E note 2023: 'Performance fees ... 257'.
A102: FY2024: EC fines - no P&L effect in 2024 (context) [General and administrative] | J102: 0 | M102: [disclosed] 10-K 0001652044-25-000014, MD&A 'European Commission Fines' + Note 10 — 'In September 2024, the European Court of Justice rejected our appeal of the 2017 decision and upheld the EUR 2.4 billion fine. In the t
A103: FY2024: Employee severance and related charges [General and administrative] | J103: -1000 | L103: x | M103: [disclosed] 10-K 0001652044-25-000014, MD&A Financial Results highlights — 'Employee severance and related charges for the year ended December 31, 2024 were $1.0 billion, a decrease of $1.1 billion as compared to the yea
A104: FY2024: Gain on equity securities, net [Other income (expense), net] | J104: 3714 | L104: x | M104: [disclosed] 10-K 0001652044-25-000014, OI&E note — OI&E note 2024: 'Gain (loss) on equity securities, net ... 3,714'.
A105: FY2024: Loss on debt securities, net [Other income (expense), net] | J105: -1043 | L105: x | M105: [disclosed] 10-K 0001652044-25-000014, OI&E note — OI&E note 2024: 'Gain (loss) on debt securities, net ... (1,043)'.
A106: FY2024: Office space charges (incl. accelerated rent and accelerated depreciation) [General and administrative] | J106: -796 | L106: x | M106: [disclosed] 10-K 0001652044-25-000014, MD&A Financial Results highlights — 'Office space charges, including accelerated rent and accelerated depreciation, for the year ended December 31, 2024 were $796 million, a decreas
A107: FY2024: Performance fees (credit) [Other income (expense), net] | J107: 218 | L107: x | M107: [disclosed] 10-K 0001652044-25-000014, OI&E note — OI&E note 2024: 'Performance fees ... 218'.
A108: FY2025: European Commission fine (Advertising Technology, September 2025, ~EUR 3.0B) [General and administrative] | K108: -3500 | L108: x | M108: [disclosed] 10-K 0001652044-26-000018, MD&A G&A discussion + Note 10 — 'General and administrative expenses increased $7.3 billion from 2024 to 2025, primarily driven by an increase in expenses related to legal and other
A109: FY2025: Gain on debt securities, net [Other income (expense), net] | K109: 540 | L109: x | M109: [disclosed] 10-K 0001652044-26-000018, OI&E note — OI&E note 2025: 'Gain (loss) on debt securities, net ... 540'.
...

Sheet Balance Sheet
A1: Company: Alphabet Inc. (GOOGL)
A2: Statement: Consolidated Balance Sheets
A3: Units: USD in Millions
A4: Source: SEC 10-K filings, as filed (acc. 0001652044-26-000018 / 0001652044-24-000022 / 0001652044-22-000019 / 0001652044-20-000008 / 0001652044-18-000007; each year from the newest filing covering it)
A6: Line Item | B6: 42735 | C6: 43100 | D6: 43465 | E6: 43830 | F6: 44196 | G6: 44561 | H6: 44926 | I6: 45291 | J6: 45657 | K6: 46022
A7: CURRENT ASSETS
A8: Cash and cash equivalents | B8: 12918 | C8: 10715 | D8: 16701 | E8: 18498 | F8: 26465 | G8: 20945 | H8: 21879 | I8: 24048 | J8: 23466 | K8: 30708
A9: Marketable securities | B9: 73415 | C9: 91156 | D9: 92439 | E9: 101177 | F9: 110229 | G9: 118704 | H9: 91883 | I9: 86868 | J9: 72191 | K9: 96135
A10: Accounts receivable, net | B10: 14137 | C10: 18336 | D10: 20838 | E10: 25326 | F10: 30930 | G10: 39304 | H10: 40258 | I10: 47964 | J10: 52340 | K10: 62886
A11: Income taxes receivable, net | B11: 95 | C11: 369 | D11: 355 | E11: 2166 | F11: 454 | G11: 966
A12: Inventory | B12: 268 | C12: 749 | D12: 1107 | E12: 999 | F12: 728 | G12: 1170
A13: Other current assets | B13: 4575 | C13: 2983 | D13: 4236 | E13: 4412 | F13: 5490 | G13: 7054 | H13: 10775 | I13: 12650 | J13: 15714 | K13: 16309
A14: Total current assets | B14: =SUM(B8:B13) | C14: =SUM(C8:C13) | D14: =SUM(D8:D13) | E14: =SUM(E8:E13) | F14: =SUM(F8:F13) | G14: =SUM(G8:G13) | H14: =SUM(H8:H13) | I14: =SUM(I8:I13) | ... K14: =SUM(K8:K13)
A16: NON-CURRENT ASSETS
A17: Non-marketable securities | B17: 5878 | C17: 7813 | D17: 13859 | E17: 13078 | F17: 20703 | G17: 29549 | H17: 30492 | I17: 31008 | J17: 37982 | K17: 68687
A18: Deferred income taxes | B18: 383 | C18: 680 | D18: 737 | E18: 721 | F18: 1084 | G18: 1284 | H18: 5261 | I18: 12169 | J18: 17180 | K18: 9113
A19: Property and equipment, net | B19: 34234 | C19: 42383 | D19: 59719 | E19: 73646 | F19: 84749 | G19: 97599 | H19: 112668 | I19: 134345 | J19: 171036 | K19: 246597
A20: Operating lease assets | E20: 10941 | F20: 12211 | G20: 12959 | H20: 14381 | I20: 14091 | J20: 13588 | K20: 15221
A21: Goodwill | B21: 16468 | C21: 16747 | D21: 17888 | E21: 20624 | F21: 21175 | G21: 22956 | H21: 28960 | I21: 29198 | J21: 31885 | K21: 33380
A22: Intangible assets, net | B22: 3307 | C22: 2692 | D22: 2220 | E22: 1979 | F22: 1445 | G22: 1417
A23: Other non-current assets | B23: 1819 | C23: 2672 | D23: 2693 | E23: 2342 | F23: 3953 | G23: 5361 | H23: 8707 | I23: 10051 | J23: 14874 | K23: 16245
A24: Total assets | B24: =B14+SUM(B17:B23) | C24: =C14+SUM(C17:C23) | D24: =D14+SUM(D17:D23) | E24: =E14+SUM(E17:E23) | F24: =F14+SUM(F17:F23) | G24: =G14+SUM(G17:G23) | H24: =H14+SUM(H17:H23) | I24: =I14+SUM(I17:I23) | ... K24: =K14+SUM(K17:K23)
A26: CURRENT LIABILITIES
A27: Accounts payable | B27: 2041 | C27: 3137 | D27: 4378 | E27: 5561 | F27: 5589 | G27: 6037 | H27: 5128 | I27: 7493 | J27: 7987 | K27: 12200
A28: Accrued compensation and benefits | B28: 3976 | C28: 4581 | D28: 6839 | E28: 8495 | F28: 11086 | G28: 13889 | H28: 14028 | I28: 15140 | J28: 15069 | K28: 17546
A29: Accrued expenses and other current liabilities | B29: 6144 | C29: 10177 | D29: 16958 | E29: 23067 | F29: 28631 | G29: 31236 | H29: 37866 | I29: 46168 | J29: 51228 | K29: 55557
A30: Accrued revenue share | B30: 2942 | C30: 3975 | D30: 4592 | E30: 5916 | F30: 7500 | G30: 8996 | H30: 8370 | I30: 8876 | J30: 9802 | K30: 10864
A31: Deferred revenue | B31: 1099 | C31: 1432 | D31: 1784 | E31: 1908 | F31: 2543 | G31: 3288 | H31: 3908 | I31: 4137 | J31: 5036 | K31: 6578
A32: Income taxes payable, net | B32: 554 | C32: 881 | D32: 69 | E32: 274 | F32: 1485 | G32: 808
A33: Total current liabilities | B33: =SUM(B27:B32) | C33: =SUM(C27:C32) | D33: =SUM(D27:D32) | E33: =SUM(E27:E32) | F33: =SUM(F27:F32) | G33: =SUM(G27:G32) | H33: =SUM(H27:H32) | I33: =SUM(I27:I32) | ... K33: =SUM(K27:K32)
A35: NON-CURRENT LIABILITIES
A36: Long-term debt | B36: 3935 | C36: 3969 | D36: 4012 | E36: 4554 | F36: 13932 | G36: 14817 | H36: 14701 | I36: 13253 | J36: 10883 | K36: 46547
A37: Deferred revenue, non-current | B37: 202 | C37: 340 | D37: 396 | E37: 358 | F37: 481 | G37: 535 | H37: 599 | I37: 911
A38: Income taxes payable, non-current | B38: 4677 | C38: 12812 | D38: 11327 | E38: 9885 | F38: 8849 | G38: 9176 | H38: 9258 | I38: 8474 | J38: 8782 | K38: 9531
A39: Deferred income taxes, non-current | B39: 226 | C39: 430 | D39: 1264 | E39: 1701 | F39: 3561 | G39: 5257 | H39: 514 | I39: 485
A40: Operating lease liabilities, non-current | E40: 10214 | F40: 11146 | G40: 11389 | H40: 12501 | I40: 12460 | J40: 11691 | K40: 12744
A41: Other long-term liabilities | B41: 2665 | C41: 3059 | D41: 3545 | E41: 2534 | F41: 2269 | G41: 2205 | H41: 2247 | I41: 1616 | J41: 4694 | K41: 8449
A42: Total liabilities | B42: =B33+SUM(B36:B41) | C42: =C33+SUM(C36:C41) | D42: =D33+SUM(D36:D41) | E42: =E33+SUM(E36:E41) | F42: =F33+SUM(F36:F41) | G42: =G33+SUM(G36:G41) | H42: =H33+SUM(H36:H41) | I42: =I33+SUM(I36:I41) | ... K42: =K33+SUM(K36:K41)
A44: STOCKHOLDERS' EQUITY
A45: Class A/B/C stock and additional paid-in capital | B45: 36307 | C45: 40247 | D45: 45049 | E45: 50552 | F45: 58510 | G45: 61774 | H45: 68184 | I45: 76534 | J45: 84800 | K45: 93126
A46: Accumulated other comprehensive income (loss) | B46: -2402 | C46: -992 | D46: -2306 | E46: -1232 | F46: 633 | G46: -1623 | H46: -7603 | I46: -4402 | J46: -4800 | K46: -1916
A47: Retained earnings | B47: 105131 | C47: 113247 | D47: 134885 | E47: 152122 | F47: 163401 | G47: 191484 | H47: 195563 | I47: 211247 | J47: 245084 | K47: 324055
A48: Total stockholders' equity | B48: =SUM(B45:B47) | C48: =SUM(C45:C47) | D48: =SUM(D45:D47) | E48: =SUM(E45:E47) | F48: =SUM(F45:F47) | G48: =SUM(G45:G47) | H48: =SUM(H45:H47) | I48: =SUM(I45:I47) | ... K48: =SUM(K45:K47)
A50: Total liabilities and stockholders' equity | B50: =B42+B48 | C50: =C42+C48 | D50: =D42+D48 | E50: =E42+E48 | F50: =F42+F48 | G50: =G42+G48 | H50: =H42+H48 | I50: =I42+I48 | ... K50: =K42+K48
A52: QUARTERLY (AS-FILED 10-Q; Q4 DERIVED)
A53: As-filed 10-Q period-end balances; Q4 columns are the fiscal year-end balance sheet (10-K). Blank cells follow each filing's own presentation.
B55: Q1 2024 | C55: Q2 2024 | D55: Q3 2024 | E55: Q4 2024 | F55: Q1 2025 | G55: Q2 2025 | H55: Q3 2025 | I55: Q4 2025 | J55: Q1 2026
A56: Line Item | B56: 45382 | C56: 45473 | D56: 45565 | E56: 45657 | F56: 45747 | G56: 45838 | H56: 45930 | I56: 46022 | J56: 46112
A58: CURRENT ASSETS
A59: Cash and cash equivalents | B59: 24493 | C59: 27225 | D59: 19959 | E59: 23466 | F59: 23264 | G59: 21036 | H59: 23090 | I59: 30708 | J59: 38063
A60: Marketable securities | B60: 83597 | C60: 73500 | D60: 73271 | E60: 72191 | F60: 72064 | G60: 74112 | H60: 75406 | I60: 96135 | J60: 88777
A61: Accounts receivable, net | B61: 44552 | C61: 47087 | D61: 49104 | E61: 52340 | F61: 51000 | G61: 55048 | H61: 57148 | I61: 62886 | J61: 62999
A62: Income taxes receivable, net
A63: Inventory
A64: Other current assets | B64: 12829 | C64: 14183 | D64: 15207 | E64: 15714 | F64: 15724 | G64: 16020 | H64: 18303 | I64: 16309 | J64: 23914
A65: Total current assets | B65: =SUM(B59:B64) | C65: =SUM(C59:C64) | D65: =SUM(D59:D64) | E65: =SUM(E59:E64) | F65: =SUM(F59:F64) | G65: =SUM(G59:G64) | H65: =SUM(H59:H64) | I65: =SUM(I59:I64) | J65: =SUM(J59:J64)
A67: NON-CURRENT ASSETS
A68: Non-marketable securities | B68: 33994 | C68: 34172 | D68: 36177 | E68: 37982 | F68: 51029 | G68: 52574 | H68: 63800 | I68: 68687 | J68: 106946
A69: Deferred income taxes | B69: 11687 | C69: 14958 | D69: 15915 | E69: 17180 | F69: 18386 | G69: 19289 | H69: 10331 | I69: 9113 | J69: 1995
A70: Property and equipment, net | B70: 143182 | C70: 151155 | D70: 161270 | E70: 171036 | F70: 185062 | G70: 203231 | H70: 223787 | I70: 246597 | J70: 281020
A71: Operating lease assets | B71: 13768 | C71: 13606 | D71: 13561 | E71: 13588 | F71: 13722 | G71: 14255 | H71: 14524 | I71: 15221 | J71: 15509
A72: Goodwill | B72: 29183 | C72: 29185 | D72: 31935 | E72: 31885 | F72: 32173 | G72: 32335 | H72: 33269 | I72: 33380 | J72: 57774
A73: Intangible assets, net | J73: 9444
A74: Other non-current assets | B74: 10065 | C74: 9699 | D74: 13867 | E74: 14874 | F74: 12950 | G74: 14153 | H74: 16811 | I74: 16245 | J74: 17478
A75: Total assets | B75: =B65+SUM(B68:B74) | C75: =C65+SUM(C68:C74) | D75: =D65+SUM(D68:D74) | E75: =E65+SUM(E68:E74) | F75: =F65+SUM(F68:F74) | G75: =G65+SUM(G68:G74) | H75: =H65+SUM(H68:H74) | I75: =I65+SUM(I68:I74) | J75: =J65+SUM(J68:J74)
A77: CURRENT LIABILITIES
A78: Accounts payable | B78: 6198 | C78: 6092 | D78: 7049 | E78: 7987 | F78: 8497 | G78: 8347 | H78: 10546 | I78: 12200 | J78: 16852
A79: Accrued compensation and benefits | B79: 9703 | C79: 11373 | D79: 12908 | E79: 15069 | F79: 9984 | G79: 12168 | H79: 13944 | I79: 17546 | J79: 13947
A80: Accrued expenses and other current liabilities | B80: 48603 | C80: 47298 | D80: 46585 | E80: 51228 | F80: 58300 | G80: 52039 | H80: 59437 | I80: 55557 | J80: 63019
A81: Accrued revenue share | B81: 8520 | C81: 8899 | D81: 9365 | E81: 9802 | F81: 9965 | G81: 9787 | H81: 10081 | I81: 10864 | J81: 10208
A82: Deferred revenue | B82: 3973 | C82: 4251 | D82: 4896 | E82: 5036 | F82: 4908 | G82: 4969 | H82: 5542 | I82: 6578 | J82: 7162
A83: Income taxes payable, net
A84: Total current liabilities | B84: =SUM(B78:B83) | C84: =SUM(C78:C83) | D84: =SUM(D78:D83) | E84: =SUM(E78:E83) | F84: =SUM(F78:F83) | G84: =SUM(G78:G83) | H84: =SUM(H78:H83) | I84: =SUM(I78:I83) | J84: =SUM(J78:J83)
A86: NON-CURRENT LIABILITIES
A87: Long-term debt | B87: 13228 | C87: 13238 | D87: 12297 | E87: 10883 | F87: 10886 | G87: 23607 | H87: 21607 | I87: 46547 | J87: 77501
A88: Deferred revenue, non-current | B88: 921 | C88: 985 | D88: 1015
A89: Income taxes payable, non-current | B89: 9234 | C89: 7703 | D89: 8219 | E89: 8782 | F89: 9773 | G89: 10027 | H89: 10072 | I89: 9531 | J89: 12457
A90: Deferred income taxes, non-current | B90: 486 | C90: 717 | D90: 706
A91: Operating lease liabilities, non-current | B91: 11957 | C91: 11708 | D91: 11654 | E91: 11691 | F91: 11678 | G91: 11952 | H91: 12106 | I91: 12744 | J91: 12983
A92: Other long-term liabilities | B92: 1683 | C92: 1753 | D92: 1453 | E92: 4694 | F92: 6116 | G92: 6241 | H92: 6267 | I92: 8449 | J92: 11044
A93: Total liabilities | B93: =B84+SUM(B87:B92) | C93: =C84+SUM(C87:C92) | D93: =D84+SUM(D87:D92) | E93: =E84+SUM(E87:E92) | F93: =F84+SUM(F87:F92) | G93: =G84+SUM(G87:G92) | H93: =H84+SUM(H87:H92) | I93: =I84+SUM(I87:I92) | J93: =J84+SUM(J87:J92)
A95: STOCKHOLDERS' EQUITY
A96: Class A/B/C stock and additional paid-in capital | B96: 77913 | C96: 79732 | D96: 82030 | E96: 84800 | F96: 86725 | G96: 89283 | H96: 91695 | I96: 93126 | J96: 96902
A97: Accumulated other comprehensive income (loss) | B97: -4839 | C97: -5012 | D97: -3228 | E97: -4800 | F97: -4086 | G97: -2127 | H97: -2054 | I97: -1916 | J97: -2180
A98: Retained earnings | B98: 219770 | C98: 226033 | D98: 235317 | E98: 245084 | F98: 262628 | G98: 275760 | H98: 297226 | I98: 324055 | J98: 384024
A99: Total stockholders' equity | B99: =SUM(B96:B98) | C99: =SUM(C96:C98) | D99: =SUM(D96:D98) | E99: =SUM(E96:E98) | F99: =SUM(F96:F98) | G99: =SUM(G96:G98) | H99: =SUM(H96:H98) | I99: =SUM(I96:I98) | J99: =SUM(J96:J98)
A101: Total liabilities and stockholders' equity | B101: =B93+B99 | C101: =C93+C99 | D101: =D93+D99 | E101: =E93+E99 | F101: =F93+F99 | G101: =G93+G99 | H101: =H93+H99 | I101: =I93+I99 | J101: =J93+J99
A103: Source 10-Qs: Q1 2024 0001652044-24-000053; Q2 2024 0001652044-24-000079; Q3 2024 0001652044-24-000118; Q1 2025 0001652044-25-000043; Q2 2025 0001652044-25-000062; Q3 2025 0001652044-25-000091; Q1 2026 0001652044-26-000048

Sheet Cash Flow Statement
A1: Company: Alphabet Inc. (GOOGL)
A2: Statement: Consolidated Statements of Cash Flows
A3: Units: USD in Millions
A4: Source: SEC 10-K filings, as filed (acc. 0001652044-26-000018 / 0001652044-24-000022 / 0001652044-22-000019 / 0001652044-20-000008 / 0001652044-18-000007; each year from the newest filing covering it)
A6: Line Item | B6: 42735 | C6: 43100 | D6: 43465 | E6: 43830 | F6: 44196 | G6: 44561 | H6: 44926 | I6: 45291 | J6: 45657 | K6: 46022
A7: OPERATING ACTIVITIES
A8: Net income | B8: 19478 | C8: 12662 | D8: 30736 | E8: 34343 | F8: 40269 | G8: 76033 | H8: 59972 | I8: 73795 | J8: 100118 | K8: 132170
A9: Adjustments:
A10: Depreciation and impairment of property and equipment | B10: 5267 | C10: 6103 | D10: 8164 | E10: 10856 | F10: 12905
A11: Depreciation of property and equipment | G11: 10273 | H11: 13475 | I11: 11946 | J11: 15311 | K11: 21136
A12: Amortization and impairment of intangible assets | B12: 877 | C12: 812 | D12: 871 | E12: 925 | F12: 792
A13: Stock-based compensation expense | B13: 6703 | C13: 7679 | D13: 9353 | E13: 10794 | F13: 12991 | G13: 15376 | H13: 19362 | I13: 22460 | J13: 22785 | K13: 24953
A14: Deferred income taxes | B14: -38 | C14: 258 | D14: 778 | E14: 173 | F14: 1390 | G14: 1808 | H14: -8081 | I14: -7763 | J14: -5257 | K14: 8348
A15: Loss on marketable and non-marketable investments, net | B15: 275
A16: (Gain) loss on debt and equity securities, net | C16: 37 | D16: -6650 | E16: -2798 | F16: -6317 | G16: -12270 | H16: 5519 | I16: 823 | J16: -2671 | K16: -24620
A17: Other | B17: 174 | C17: 294 | D17: -189 | E17: -592 | F17: 1267 | G17: 1955 | H17: 3483 | I17: 4330 | J17: 3419 | K17: 2108
A18: Changes in assets and liabilities, net of effects of acquisitions:
A19: Accounts receivable, net | B19: -2578 | C19: -3768 | D19: -2169 | E19: -4340 | F19: -6524 | G19: -9095 | H19: -2317 | I19: -7833 | J19: -5891 | K19: -8779
A20: Income taxes, net | B20: 3125 | C20: 8211 | D20: -2251 | E20: -3128 | F20: 1209 | G20: -625 | H20: 584 | I20: 523 | J20: -2418 | K20: -3226
A21: Other assets | B21: 312 | C21: -2164 | D21: -1207 | E21: -621 | F21: -1330 | G21: -1846 | H21: -5046 | I21: -2143 | J21: -1397 | K21: -4542
A22: Accounts payable | B22: 110 | C22: 731 | D22: 1067 | E22: 428 | F22: 694 | G22: 283 | H22: 707 | I22: 664 | J22: 359 | K22: 907
A23: Accrued expenses and other liabilities | B23: 1515 | C23: 4891 | D23: 8614 | E23: 7170 | F23: 5504 | G23: 7304 | H23: 3915 | I23: 3937 | J23: -1161 | K23: 12939
A24: Accrued revenue share | B24: 593 | C24: 955 | D24: 483 | E24: 1273 | F24: 1639 | G24: 1682 | H24: -445 | I24: 482 | J24: 1059 | K24: 899
A25: Deferred revenue | B25: 223 | C25: 390 | D25: 371 | E25: 37 | F25: 635 | G25: 774 | H25: 367 | I25: 525 | J25: 1043 | K25: 2420
A26: Net cash provided by operating activities | B26: 36036 | C26: 37091 | D26: 47971 | E26: 54520 | F26: 65124 | G26: 91652 | H26: 91495 | I26: 101746 | J26: 125299 | K26: 164713
A28: INVESTING ACTIVITIES
A29: Purchases of property and equipment | B29: -10212 | C29: -13184 | D29: -25139 | E29: -23548 | F29: -22281 | G29: -24640 | H29: -31485 | I29: -32251 | J29: -52535 | K29: -91447
A30: Proceeds from disposals of property and equipment | B30: 240
A31: Purchases of marketable securities | B31: -84509 | C31: -92195 | D31: -50158 | E31: -100315 | F31: -136576 | G31: -135196 | H31: -78874 | I31: -77858 | J31: -86679 | K31: -103773
A32: Maturities and sales of marketable securities | B32: 66895 | C32: 73959 | D32: 48507 | E32: 97825 | F32: 132906 | G32: 128294 | H32: 97822 | I32: 86672 | J32: 103428 | K32: 83240
A33: Purchases of non-marketable securities | B33: -1109 | C33: -1745 | D33: -2073 | E33: -1932 | F33: -7175 | G33: -2838 | H33: -2531 | I33: -3027 | J33: -5034 | K33: -5716
A34: Maturities and sales of non-marketable securities | B34: 494 | C34: 533 | D34: 1752 | E34: 405 | F34: 1023 | G34: 934 | H34: 150 | I34: 947 | J34: 882 | K34: 1367
A35: Cash collateral related to securities lending | B35: -2428
A36: Investments in reverse repurchase agreements | B36: 450
A37: Acquisitions, net of cash acquired, and purchases of intangible and other assets | B37: -986 | C37: -287 | D37: -1491 | E37: -2515 | F37: -738 | G37: -2618 | H37: -6969 | I37: -495 | J37: -2931 | K37: -1592
A38: Proceeds from collection of notes receivable | B38: 0 | C38: 1419 | D38: 0
A39: Other investing activities | C39: 99 | D39: 98 | E39: 589 | F39: 68 | G39: 541 | H39: 1589 | I39: -1051 | J39: -2667 | K39: -2370
A40: Net cash used in investing activities | B40: -31165 | C40: -31401 | D40: -28504 | E40: -29491 | F40: -32773 | G40: -35523 | H40: -20298 | I40: -27063 | J40: -45536 | K40: -120291
A42: FINANCING ACTIVITIES
A43: Net payments related to stock-based award activities | B43: -3304 | C43: -4166 | D43: -4993 | E43: -4765 | F43: -5720 | G43: -10162 | H43: -9300 | I43: -9837 | J43: -12190 | K43: -14167
A44: Repurchases of stock | B44: -3693 | C44: -4846 | D44: -9075 | E44: -18396 | F44: -31149 | G44: -50274 | H44: -59296 | I44: -61504 | J44: -62222 | K44: -45709
A45: Dividend payments | B45: 0 | I45: 0 | J45: -7363 | K45: -10049
A46: Proceeds from issuance of debt, net of costs | B46: 8729 | C46: 4291 | D46: 6766 | E46: 317 | F46: 11761 | G46: 20199 | H46: 52872 | I46: 10790 | J46: 13589 | K46: 64564
A47: Repayments of debt | B47: -10064 | C47: -4377 | D47: -6827 | E47: -585 | F47: -2100 | G47: -21435 | H47: -54068 | I47: -11550 | J47: -12701 | K47: -32427
A48: Proceeds from sale of interest in consolidated entities, net | B48: 0 | C48: 800 | D48: 950 | E48: 220 | F48: 2800 | G48: 310 | H48: 35 | I48: 8 | J48: 1154 | K48: 400
A49: Net cash used in financing activities | B49: -8332 | C49: -8298 | D49: -13179 | E49: -23209 | F49: -24408 | G49: -61362 | H49: -69757 | I49: -72093 | J49: -79733 | K49: -37388
A51: Effect of exchange rate changes on cash and cash equivalents | B51: -170 | C51: 405 | D51: -302 | E51: -23 | F51: 24 | G51: -287 | H51: -506 | I51: -421 | J51: -612 | K51: 208
A52: Net increase (decrease) in cash and cash equivalents | B52: -3631 | C52: -2203 | D52: 5986 | E52: 1797 | F52: 7967 | G52: -5520 | H52: 934 | I52: 2169 | J52: -582 | K52: 7242
A53: Cash and cash equivalents at beginning of period | B53: 16549 | C53: 12918 | D53: 10715 | E53: 16701 | F53: 18498 | G53: 26465 | H53: 20945 | I53: 21879 | J53: 24048 | K53: 23466
A54: Cash and cash equivalents at end of period | B54: 12918 | C54: 10715 | D54: 16701 | E54: 18498 | F54: 26465 | G54: 20945 | H54: 21879 | I54: 24048 | J54: 23466 | K54: 30708
A56: SUPPLEMENTAL DISCLOSURES
A57: Cash paid for income taxes, net of refunds | B57: 1643 | C57: 6191 | D57: 5671 | E57: 8203 | F57: 4990 | G57: 13412 | H57: 18892
A58: Cash paid for interest, net of amounts capitalized | B58: 84
A59: Purchases of property and equipment included in accrued liabilities | I59: 7435 | J59: 10326 | K59: 15090
A61: QUARTERLY (AS-FILED 10-Q; Q4 DERIVED)
A62: 10-Q cash flows are filed cumulative (YTD); de-cumulated here (Qn = YTDn − YTDn−1; begin cash of Qn = end cash of Qn−1). Q4 derived: IS/CF = annual FY column − Σ(Q1–Q3); BS = fiscal year-end (10-K). EPS/share rows non-additive (no Q4).
B64: Q1 2024 | C64: Q2 2024 | D64: Q3 2024 | E64: Q4 2024 | F64: Q1 2025 | G64: Q2 2025 | H64: Q3 2025 | I64: Q4 2025 | J64: Q1 2026
A65: Line Item | B65: 45382 | C65: 45473 | D65: 45565 | E65: 45657 | F65: 45747 | G65: 45838 | H65: 45930 | I65: 46022 | J65: 46112
A67: OPERATING ACTIVITIES
A68: Net income | B68: 23662 | C68: 23619 | D68: 26301 | E68: 26536 | F68: 34540 | G68: 28196 | H68: 34979 | I68: 34455 | J68: 62578
A69: Adjustments:
A70: Depreciation and impairment of property and equipment
A71: Depreciation of property and equipment | B71: 3413 | C71: 3708 | D71: 3985 | E71: 4205 | F71: 4487 | G71: 4998 | H71: 5611 | I71: 6040 | J71: 6482
A72: Amortization and impairment of intangible assets
A73: Stock-based compensation expense | B73: 5264 | C73: 5865 | D73: 5846 | E73: 5810 | F73: 5516 | G73: 5998 | H73: 6368 | I73: 7071 | J73: 6751
A74: Deferred income taxes | B74: 419 | C74: -3157 | D74: -1071 | E74: -1448 | F74: -1152 | G74: -444 | H74: 8726 | I74: 1218 | J74: 6920
A75: Loss on marketable and non-marketable investments, net
A76: (Gain) loss on debt and equity securities, net | B76: -1781 | C76: 1024 | D76: -1981 | E76: 67 | F76: -9960 | G76: -1451 | H76: -10855 | I76: -2354 | J76: -36804
A77: Other | B77: 334 | C77: 851 | D77: 1407 | E77: 827 | F77: 481 | G77: 560 | H77: -198 | I77: 1265 | J77: 1265
A78: Changes in assets and liabilities, net of effects of acquisitions:
A79: Accounts receivable, net | B79: 3167 | C79: -3057 | D79: -1431 | E79: -4570 | F79: 1638 | G79: -2839 | H79: -2381 | I79: -5197 | J79: -363
A80: Income taxes, net | B80: 3011 | C80: -3900 | D80: -1908 | E80: 379 | F80: 7197 | G80: -9631 | H80: -858 | I80: 66 | J80: 8101
A81: Other assets | B81: -1000 | C81: -532 | D81: -802 | E81: 937 | F81: -1288 | G81: -1479 | H81: -1293 | I81: -482 | J81: -3403
A82: Accounts payable | B82: -2124 | C82: 1561 | D82: 521 | E82: 401 | F82: -880 | G82: 553 | H82: -444 | I82: 1678 | J82: -240
A83: Accrued expenses and other liabilities | B83: -5054 | C83: -122 | D83: -1190 | E83: 5205 | F83: -5045 | G83: 3485 | H83: 7759 | I83: 6740 | J83: -6002
A84: Accrued revenue share | B84: -322 | C84: 419 | D84: 381 | E84: 581 | F84: 116 | G84: -335 | H84: 319 | I84: 799
A85: Deferred revenue | B85: -141 | C85: 361 | D85: 640 | E85: 183 | F85: 500 | G85: 136 | H85: 681 | I85: 1103 | J85: 505
A86: Net cash provided by operating activities | B86: 28848 | C86: 26640 | D86: 30698 | E86: 39113 | F86: 36150 | G86: 27747 | H86: 48414 | I86: 52402 | J86: 45790
A88: INVESTING ACTIVITIES
A89: Purchases of property and equipment | B89: -12012 | C89: -13186 | D89: -13061 | E89: -14276 | F89: -17197 | G89: -22446 | H89: -23953 | I89: -27851 | J89: -35674
A90: Proceeds from disposals of property and equipment
A91: Purchases of marketable securities | B91: -20684 | C91: -22327 | D91: -22023 | E91: -21645 | F91: -18453 | G91: -21417 | H91: -20964 | I91: -42939 | J91: -31041
A92: Maturities and sales of marketable securities | B92: 24985 | C92: 33592 | D92: 23202 | E92: 21649 | F92: 20345 | G92: 20585 | H92: 20371 | I92: 21939 | J92: 38001
A93: Purchases of non-marketable securities | B93: -1206 | C93: -993 | D93: -1035 | E93: -1800 | F93: -958 | G93: -1354 | H93: -1000 | I93: -2404 | J93: -906
A94: Maturities and sales of non-marketable securities | B94: 313 | C94: 292 | D94: 127 | E94: 150 | F94: 259 | G94: 614 | H94: 323 | I94: 171 | J94: 848
A95: Cash collateral related to securities lending
A96: Investments in reverse repurchase agreements
A97: Acquisitions, net of cash acquired, and purchases of intangible and other assets | B97: -61 | C97: -26 | D97: -2753 | E97: -91 | F97: -340 | G97: -13 | H97: -1072 | I97: -167 | J97: -33621
A98: Proceeds from collection of notes receivable
A99: Other investing activities | B99: 101 | C99: -133 | D99: -2468 | E99: -167 | F99: 150 | G99: -513 | H99: -1482 | I99: -525 | J99: -996
A100: Net cash used in investing activities | B100: -8564 | C100: -2781 | D100: -18011 | E100: -16180 | F100: -16194 | G100: -24544 | H100: -27777 | I100: -51776 | J100: -63389
A102: FINANCING ACTIVITIES
A103: Net payments related to stock-based award activities | B103: -2929 | C103: -3209 | D103: -3003 | E103: -3049 | F103: -3110 | G103: -2621 | H103: -3270 | I103: -5166 | J103: -5483
A104: Repurchases of stock | B104: -15696 | C104: -15684 | D104: -15291 | E104: -15551 | F104: -15068 | G104: -13638 | H104: -11504 | I104: -5499 | J104: 0
A105: Dividend payments | C105: -2466 | D105: -2455 | E105: -2442 | F105: -2434 | G105: -2543 | H105: -2536 | I105: -2536 | J105: -2542
A106: Proceeds from issuance of debt, net of costs | B106: 1982 | C106: 2893 | D106: 3819 | E106: 4895 | F106: 4532 | G106: 26846 | H106: 6624 | I106: 26562 | J106: 31379
A107: Repayments of debt | B107: -3079 | C107: -2423 | D107: -3449 | E107: -3750 | F107: -4521 | G107: -13876 | H107: -7697 | I107: -6333 | J107: -1477
A108: Proceeds from sale of interest in consolidated entities, net | B108: 8 | C108: 0 | D108: 285 | E108: 861 | F108: 400 | G108: 0 | H108: 0 | I108: 0 | J108: 3200
A109: Net cash used in financing activities | B109: -19714 | C109: -20889 | D109: -20094 | E109: -19036 | F109: -20201 | G109: -5832 | H109: -18383 | I109: 7028 | J109: 25077
A111: Effect of exchange rate changes on cash and cash equivalents | B111: -125 | C111: -238 | D111: 141 | E111: -390 | F111: 43 | G111: 401 | H111: -200 | I111: -36 | J111: -123
...

Sheet Condensed Financials
A1: Alphabet Inc. (GOOGL) — Condensed Financials
A2: NOPAT, Operating/Financial Classification, NOA/Net Debt/Equity
A3: Aggregates driven by the interactive classification table (rows 49+); values linked to source tabs
A5: Line Item | B5: ='Income Statement'!B6 | C5: ='Income Statement'!C6 | D5: ='Income Statement'!D6 | E5: ='Income Statement'!E6 | F5: ='Income Statement'!F6 | G5: ='Income Statement'!G6 | H5: ='Income Statement'!H6 | I5: ='Income Statement'!I6 | ... K5: ='Income Statement'!K6
A7: A. CONDENSED INCOME STATEMENT
A8: Net Income | B8: ='Income Statement'!B19 | C8: ='Income Statement'!C19 | D8: ='Income Statement'!D19 | E8: ='Income Statement'!E19 | F8: ='Income Statement'!F19 | G8: ='Income Statement'!G19 | H8: ='Income Statement'!H19 | I8: ='Income Statement'!I19 | ... K8: ='Income Statement'!K19
A9: Other Income (Expense), Net | B9: ='Income Statement'!B16 | C9: ='Income Statement'!C16 | D9: ='Income Statement'!D16 | E9: ='Income Statement'!E16 | F9: ='Income Statement'!F16 | G9: ='Income Statement'!G16 | H9: ='Income Statement'!H16 | I9: ='Income Statement'!I16 | ... K9: ='Income Statement'!K16
A10: Interest Expense (estimated) | B10: 124 | C10: 109 | D10: 114 | E10: 100 | F10: 135 | G10: 346 | H10: 357 | I10: 308 | J10: 365 | K10: 1200
A11: Interest Income (estimated) | B11: 1220 | C11: 1312 | D11: 1878 | E11: 2427 | F11: 1865 | G11: 1499 | H11: 1268 | I11: 3865 | J11: 4963 | K11: 4801
A12: Net Interest Expense (Income) | B12: =B10-B11 | C12: =C10-C11 | D12: =D10-D11 | E12: =E10-E11 | F12: =F10-F11 | G12: =G10-G11 | H12: =H10-H11 | I12: =I10-I11 | ... K12: =K10-K11
A13: Pretax Income | B13: ='Income Statement'!B17 | C13: ='Income Statement'!C17 | D13: ='Income Statement'!D17 | E13: ='Income Statement'!E17 | F13: ='Income Statement'!F17 | G13: ='Income Statement'!G17 | H13: ='Income Statement'!H17 | I13: ='Income Statement'!I17 | ... K13: ='Income Statement'!K17
A14: Tax Expense | B14: =ABS('Income Statement'!B18) | C14: =ABS('Income Statement'!C18) | D14: =ABS('Income Statement'!D18) | E14: =ABS('Income Statement'!E18) | F14: =ABS('Income Statement'!F18) | G14: =ABS('Income Statement'!G18) | H14: =ABS('Income Statement'!H18) | I14: =ABS('Income Statement'!I18) | ... K14: =ABS('Income Statement'!K18)
A15: Effective Tax Rate | B15: =IFERROR(B14/B13,0) | C15: =IFERROR(C14/C13,0) | D15: =IFERROR(D14/D13,0) | E15: =IFERROR(E14/E13,0) | F15: =IFERROR(F14/F13,0) | G15: =IFERROR(G14/G13,0) | H15: =IFERROR(H14/H13,0) | I15: =IFERROR(I14/I13,0) | ... K15: =IFERROR(K14/K13,0)
A16: Net Interest After Tax | B16: =B12*(1-B15) | C16: =C12*(1-C15) | D16: =D12*(1-D15) | E16: =E12*(1-E15) | F16: =F12*(1-F15) | G16: =G12*(1-G15) | H16: =H12*(1-H15) | I16: =I12*(1-I15) | ... K16: =K12*(1-K15)
A17: NOPAT | B17: =B8+B16 | C17: =C8+C16 | D17: =D8+D16 | E17: =E8+E16 | F17: =F8+F16 | G17: =G8+G16 | H17: =H8+H16 | I17: =I8+I16 | ... K17: =K8+K16
A18: Interest rows: FY2016-FY2020 as disclosed (XBRL InterestExpense / InterestIncomeOther); FY2021-FY2025 estimated from filing disclosures.
A20: B. CONDENSED BALANCE SHEET
A21: All aggregates below are SUMIFs over the CLASSIFICATION TABLE (rows 51-78). Toggle any item’s classification in column L of the table; NOWC, NOA, Net Debt, DuPont ratios and model anchors recompute.
A25: Operating Working Capital Assets | B25: =SUMIF($L$51:$L$78,"Operating Working Capital Asset",B$51:B$78) | C25: =SUMIF($L$51:$L$78,"Operating Working Capital Asset",C$51:C$78) | D25: =SUMIF($L$51:$L$78,"Operating Working Capital Asset",D$51:D$78) | E25: =SUMIF($L$51:$L$78,"Operating Working Capital Asset",E$51:E$78) | F25: =SUMIF($L$51:$L$78,"Operating Working Capital Asset",F$51:F$78) | G25: =SUMIF($L$51:$L$78,"Operating Working Capital Asset",G$51:G$78) | H25: =SUMIF($L$51:$L$78,"Operating Working Capital Asset",H$51:H$78) | I25: =SUMIF($L$51:$L$78,"Operating Working Capital Asset",I$51:I$78) | ... K25: =SUMIF($L$51:$L$78,"Operating Working Capital Asset",K$51:K$78)
A26: Operating Working Capital Liabilities | B26: =SUMIF($L$51:$L$78,"Operating Working Capital Liability",B$51:B$78) | C26: =SUMIF($L$51:$L$78,"Operating Working Capital Liability",C$51:C$78) | D26: =SUMIF($L$51:$L$78,"Operating Working Capital Liability",D$51:D$78) | E26: =SUMIF($L$51:$L$78,"Operating Working Capital Liability",E$51:E$78) | F26: =SUMIF($L$51:$L$78,"Operating Working Capital Liability",F$51:F$78) | G26: =SUMIF($L$51:$L$78,"Operating Working Capital Liability",G$51:G$78) | H26: =SUMIF($L$51:$L$78,"Operating Working Capital Liability",H$51:H$78) | I26: =SUMIF($L$51:$L$78,"Operating Working Capital Liability",I$51:I$78) | ... K26: =SUMIF($L$51:$L$78,"Operating Working Capital Liability",K$51:K$78)
A27: NET OPERATING WORKING CAPITAL (NOWC) | B27: =B25-B26 | C27: =C25-C26 | D27: =D25-D26 | E27: =E25-E26 | F27: =F25-F26 | G27: =G25-G26 | H27: =H25-H26 | I27: =I25-I26 | ... K27: =K25-K26
A29: Operating Long-Term Assets | B29: =SUMIF($L$51:$L$78,"Operating Long-Term Asset",B$51:B$78) | C29: =SUMIF($L$51:$L$78,"Operating Long-Term Asset",C$51:C$78) | D29: =SUMIF($L$51:$L$78,"Operating Long-Term Asset",D$51:D$78) | E29: =SUMIF($L$51:$L$78,"Operating Long-Term Asset",E$51:E$78) | F29: =SUMIF($L$51:$L$78,"Operating Long-Term Asset",F$51:F$78) | G29: =SUMIF($L$51:$L$78,"Operating Long-Term Asset",G$51:G$78) | H29: =SUMIF($L$51:$L$78,"Operating Long-Term Asset",H$51:H$78) | I29: =SUMIF($L$51:$L$78,"Operating Long-Term Asset",I$51:I$78) | ... K29: =SUMIF($L$51:$L$78,"Operating Long-Term Asset",K$51:K$78)
A30: Operating Long-Term Liabilities | B30: =SUMIF($L$51:$L$78,"Operating Long-Term Liability",B$51:B$78) | C30: =SUMIF($L$51:$L$78,"Operating Long-Term Liability",C$51:C$78) | D30: =SUMIF($L$51:$L$78,"Operating Long-Term Liability",D$51:D$78) | E30: =SUMIF($L$51:$L$78,"Operating Long-Term Liability",E$51:E$78) | F30: =SUMIF($L$51:$L$78,"Operating Long-Term Liability",F$51:F$78) | G30: =SUMIF($L$51:$L$78,"Operating Long-Term Liability",G$51:G$78) | H30: =SUMIF($L$51:$L$78,"Operating Long-Term Liability",H$51:H$78) | I30: =SUMIF($L$51:$L$78,"Operating Long-Term Liability",I$51:I$78) | ... K30: =SUMIF($L$51:$L$78,"Operating Long-Term Liability",K$51:K$78)
A31: NET OPERATING LT ASSETS | B31: =B29-B30 | C31: =C29-C30 | D31: =D29-D30 | E31: =E29-E30 | F31: =F29-F30 | G31: =G29-G30 | H31: =H29-H30 | I31: =I29-I30 | ... K31: =K29-K30
A33: NET OPERATING ASSETS (NOA) | B33: =B27+B31 | C33: =C27+C31 | D33: =D27+D31 | E33: =E27+E31 | F33: =F27+F31 | G33: =G27+G31 | H33: =H27+H31 | I33: =I27+I31 | ... K33: =K27+K31
A35: Financial Assets | B35: =SUMIF($L$51:$L$78,"Financial Asset",B$51:B$78) | C35: =SUMIF($L$51:$L$78,"Financial Asset",C$51:C$78) | D35: =SUMIF($L$51:$L$78,"Financial Asset",D$51:D$78) | E35: =SUMIF($L$51:$L$78,"Financial Asset",E$51:E$78) | F35: =SUMIF($L$51:$L$78,"Financial Asset",F$51:F$78) | G35: =SUMIF($L$51:$L$78,"Financial Asset",G$51:G$78) | H35: =SUMIF($L$51:$L$78,"Financial Asset",H$51:H$78) | I35: =SUMIF($L$51:$L$78,"Financial Asset",I$51:I$78) | ... K35: =SUMIF($L$51:$L$78,"Financial Asset",K$51:K$78)
A36: Financial Liabilities | B36: =SUMIF($L$51:$L$78,"Financial Liability",B$51:B$78) | C36: =SUMIF($L$51:$L$78,"Financial Liability",C$51:C$78) | D36: =SUMIF($L$51:$L$78,"Financial Liability",D$51:D$78) | E36: =SUMIF($L$51:$L$78,"Financial Liability",E$51:E$78) | F36: =SUMIF($L$51:$L$78,"Financial Liability",F$51:F$78) | G36: =SUMIF($L$51:$L$78,"Financial Liability",G$51:G$78) | H36: =SUMIF($L$51:$L$78,"Financial Liability",H$51:H$78) | I36: =SUMIF($L$51:$L$78,"Financial Liability",I$51:I$78) | ... K36: =SUMIF($L$51:$L$78,"Financial Liability",K$51:K$78)
A37: NET DEBT (Fin Liab - Fin Assets) | B37: =B36-B35 | C37: =C36-C35 | D37: =D36-D35 | E37: =E36-E35 | F37: =F36-F35 | G37: =G36-G35 | H37: =H36-H35 | I37: =I36-I35 | ... K37: =K36-K35
A38: NOTE: Negative Net Debt = net cash position (Fin Assets > Fin Liab)
A40: EQUITY (NOA - Net Debt) | B40: =B33-B37 | C40: =C33-C37 | D40: =D33-D37 | E40: =E33-E37 | F40: =F33-F37 | G40: =G33-G37 | H40: =H33-H37 | I40: =I33-I37 | ... K40: =K33-K37
A41: Reported Equity | B41: ='Balance Sheet'!B48 | C41: ='Balance Sheet'!C48 | D41: ='Balance Sheet'!D48 | E41: ='Balance Sheet'!E48 | F41: ='Balance Sheet'!F48 | G41: ='Balance Sheet'!G48 | H41: ='Balance Sheet'!H48 | I41: ='Balance Sheet'!I48 | ... K41: ='Balance Sheet'!K48
A44: TOTAL CAPITAL (Net Debt + Equity) | B44: =B37+B40 | C44: =C37+C40 | D44: =D37+D40 | E44: =E37+E40 | F44: =F37+F40 | G44: =G37+G40 | H44: =H37+H40 | I44: =I37+I40 | ... K44: =K37+K40
A45: CHECK: implied equity = reported equity | B45: =IF(ABS(B40-B41)<1,"OK","CHECK") | C45: =IF(ABS(C40-C41)<1,"OK","CHECK") | D45: =IF(ABS(D40-D41)<1,"OK","CHECK") | E45: =IF(ABS(E40-E41)<1,"OK","CHECK") | F45: =IF(ABS(F40-F41)<1,"OK","CHECK") | G45: =IF(ABS(G40-G41)<1,"OK","CHECK") | H45: =IF(ABS(H40-H41)<1,"OK","CHECK") | I45: =IF(ABS(I40-I41)<1,"OK","CHECK") | ... K45: =IF(ABS(K40-K41)<1,"OK","CHECK")
A49: C. BALANCE SHEET CLASSIFICATION TABLE (interactive) | L49: ▼ TOGGLE HERE: click any cell below — a dropdown menu appears
A50: Line Item | B50: ='Balance Sheet'!B6 | C50: ='Balance Sheet'!C6 | D50: ='Balance Sheet'!D6 | E50: ='Balance Sheet'!E6 | F50: ='Balance Sheet'!F6 | G50: ='Balance Sheet'!G6 | H50: ='Balance Sheet'!H6 | I50: ='Balance Sheet'!I6 | ... K50: ='Balance Sheet'!K6 | L50: Classification (click → ▼) | M50: Notes
A51: Cash and cash equivalents | B51: ='Balance Sheet'!B8 | C51: ='Balance Sheet'!C8 | D51: ='Balance Sheet'!D8 | E51: ='Balance Sheet'!E8 | F51: ='Balance Sheet'!F8 | G51: ='Balance Sheet'!G8 | H51: ='Balance Sheet'!H8 | I51: ='Balance Sheet'!I8 | ... K51: ='Balance Sheet'!K8 | L51: Financial Asset
A52: Marketable securities | B52: ='Balance Sheet'!B9 | C52: ='Balance Sheet'!C9 | D52: ='Balance Sheet'!D9 | E52: ='Balance Sheet'!E9 | F52: ='Balance Sheet'!F9 | G52: ='Balance Sheet'!G9 | H52: ='Balance Sheet'!H9 | I52: ='Balance Sheet'!I9 | ... K52: ='Balance Sheet'!K9 | L52: Financial Asset
A53: Accounts receivable, net | B53: ='Balance Sheet'!B10 | C53: ='Balance Sheet'!C10 | D53: ='Balance Sheet'!D10 | E53: ='Balance Sheet'!E10 | F53: ='Balance Sheet'!F10 | G53: ='Balance Sheet'!G10 | H53: ='Balance Sheet'!H10 | I53: ='Balance Sheet'!I10 | ... K53: ='Balance Sheet'!K10 | L53: Operating Working Capital Asset
A54: Income taxes receivable, net | B54: ='Balance Sheet'!B11 | C54: ='Balance Sheet'!C11 | D54: ='Balance Sheet'!D11 | E54: ='Balance Sheet'!E11 | F54: ='Balance Sheet'!F11 | G54: ='Balance Sheet'!G11 | H54: ='Balance Sheet'!H11 | I54: ='Balance Sheet'!I11 | ... K54: ='Balance Sheet'!K11 | L54: Operating Working Capital Asset
A55: Inventory | B55: ='Balance Sheet'!B12 | C55: ='Balance Sheet'!C12 | D55: ='Balance Sheet'!D12 | E55: ='Balance Sheet'!E12 | F55: ='Balance Sheet'!F12 | G55: ='Balance Sheet'!G12 | H55: ='Balance Sheet'!H12 | I55: ='Balance Sheet'!I12 | ... K55: ='Balance Sheet'!K12 | L55: Operating Working Capital Asset
A56: Other current assets | B56: ='Balance Sheet'!B13 | C56: ='Balance Sheet'!C13 | D56: ='Balance Sheet'!D13 | E56: ='Balance Sheet'!E13 | F56: ='Balance Sheet'!F13 | G56: ='Balance Sheet'!G13 | H56: ='Balance Sheet'!H13 | I56: ='Balance Sheet'!I13 | ... K56: ='Balance Sheet'!K13 | L56: Operating Working Capital Asset
A57: Non-marketable securities | B57: ='Balance Sheet'!B17 | C57: ='Balance Sheet'!C17 | D57: ='Balance Sheet'!D17 | E57: ='Balance Sheet'!E17 | F57: ='Balance Sheet'!F17 | G57: ='Balance Sheet'!G17 | H57: ='Balance Sheet'!H17 | I57: ='Balance Sheet'!I17 | ... K57: ='Balance Sheet'!K17 | L57: Operating Long-Term Asset | M57: Convention: non-marketable/strategic stakes -> Operating LT Asset
A58: Deferred income taxes | B58: ='Balance Sheet'!B18 | C58: ='Balance Sheet'!C18 | D58: ='Balance Sheet'!D18 | E58: ='Balance Sheet'!E18 | F58: ='Balance Sheet'!F18 | G58: ='Balance Sheet'!G18 | H58: ='Balance Sheet'!H18 | I58: ='Balance Sheet'!I18 | ... K58: ='Balance Sheet'!K18 | L58: Operating Long-Term Asset | M58: ⚠ judgment: operating vs exclude
A59: Property and equipment, net | B59: ='Balance Sheet'!B19 | C59: ='Balance Sheet'!C19 | D59: ='Balance Sheet'!D19 | E59: ='Balance Sheet'!E19 | F59: ='Balance Sheet'!F19 | G59: ='Balance Sheet'!G19 | H59: ='Balance Sheet'!H19 | I59: ='Balance Sheet'!I19 | ... K59: ='Balance Sheet'!K19 | L59: Operating Long-Term Asset
A60: Operating lease assets | B60: ='Balance Sheet'!B20 | C60: ='Balance Sheet'!C20 | D60: ='Balance Sheet'!D20 | E60: ='Balance Sheet'!E20 | F60: ='Balance Sheet'!F20 | G60: ='Balance Sheet'!G20 | H60: ='Balance Sheet'!H20 | I60: ='Balance Sheet'!I20 | ... K60: ='Balance Sheet'!K20 | L60: Operating Long-Term Asset | M60: ⚠ judgment: operating vs financial
A61: Goodwill | B61: ='Balance Sheet'!B21 | C61: ='Balance Sheet'!C21 | D61: ='Balance Sheet'!D21 | E61: ='Balance Sheet'!E21 | F61: ='Balance Sheet'!F21 | G61: ='Balance Sheet'!G21 | H61: ='Balance Sheet'!H21 | I61: ='Balance Sheet'!I21 | ... K61: ='Balance Sheet'!K21 | L61: Operating Long-Term Asset
A62: Intangible assets, net | B62: ='Balance Sheet'!B22 | C62: ='Balance Sheet'!C22 | D62: ='Balance Sheet'!D22 | E62: ='Balance Sheet'!E22 | F62: ='Balance Sheet'!F22 | G62: ='Balance Sheet'!G22 | H62: ='Balance Sheet'!H22 | I62: ='Balance Sheet'!I22 | ... K62: ='Balance Sheet'!K22 | L62: Operating Long-Term Asset
A63: Other non-current assets | B63: ='Balance Sheet'!B23 | C63: ='Balance Sheet'!C23 | D63: ='Balance Sheet'!D23 | E63: ='Balance Sheet'!E23 | F63: ='Balance Sheet'!F23 | G63: ='Balance Sheet'!G23 | H63: ='Balance Sheet'!H23 | I63: ='Balance Sheet'!I23 | ... K63: ='Balance Sheet'!K23 | L63: Operating Long-Term Asset
A64: Accounts payable | B64: ='Balance Sheet'!B27 | C64: ='Balance Sheet'!C27 | D64: ='Balance Sheet'!D27 | E64: ='Balance Sheet'!E27 | F64: ='Balance Sheet'!F27 | G64: ='Balance Sheet'!G27 | H64: ='Balance Sheet'!H27 | I64: ='Balance Sheet'!I27 | ... K64: ='Balance Sheet'!K27 | L64: Operating Working Capital Liability
A65: Accrued compensation and benefits | B65: ='Balance Sheet'!B28 | C65: ='Balance Sheet'!C28 | D65: ='Balance Sheet'!D28 | E65: ='Balance Sheet'!E28 | F65: ='Balance Sheet'!F28 | G65: ='Balance Sheet'!G28 | H65: ='Balance Sheet'!H28 | I65: ='Balance Sheet'!I28 | ... K65: ='Balance Sheet'!K28 | L65: Financial Liability | M65: Convention: accrued compensation -> Financial Liability
A66: Accrued expenses and other current liabilities | B66: ='Balance Sheet'!B29 | C66: ='Balance Sheet'!C29 | D66: ='Balance Sheet'!D29 | E66: ='Balance Sheet'!E29 | F66: ='Balance Sheet'!F29 | G66: ='Balance Sheet'!G29 | H66: ='Balance Sheet'!H29 | I66: ='Balance Sheet'!I29 | ... K66: ='Balance Sheet'!K29 | L66: Operating Working Capital Liability
A67: Accrued revenue share | B67: ='Balance Sheet'!B30 | C67: ='Balance Sheet'!C30 | D67: ='Balance Sheet'!D30 | E67: ='Balance Sheet'!E30 | F67: ='Balance Sheet'!F30 | G67: ='Balance Sheet'!G30 | H67: ='Balance Sheet'!H30 | I67: ='Balance Sheet'!I30 | ... K67: ='Balance Sheet'!K30 | L67: Operating Working Capital Liability
A68: Deferred revenue | B68: ='Balance Sheet'!B31 | C68: ='Balance Sheet'!C31 | D68: ='Balance Sheet'!D31 | E68: ='Balance Sheet'!E31 | F68: ='Balance Sheet'!F31 | G68: ='Balance Sheet'!G31 | H68: ='Balance Sheet'!H31 | I68: ='Balance Sheet'!I31 | ... K68: ='Balance Sheet'!K31 | L68: Operating Working Capital Liability
A69: Income taxes payable, net | B69: ='Balance Sheet'!B32 | C69: ='Balance Sheet'!C32 | D69: ='Balance Sheet'!D32 | E69: ='Balance Sheet'!E32 | F69: ='Balance Sheet'!F32 | G69: ='Balance Sheet'!G32 | H69: ='Balance Sheet'!H32 | I69: ='Balance Sheet'!I32 | ... K69: ='Balance Sheet'!K32 | L69: Operating Working Capital Liability
A70: Long-term debt | B70: ='Balance Sheet'!B36 | C70: ='Balance Sheet'!C36 | D70: ='Balance Sheet'!D36 | E70: ='Balance Sheet'!E36 | F70: ='Balance Sheet'!F36 | G70: ='Balance Sheet'!G36 | H70: ='Balance Sheet'!H36 | I70: ='Balance Sheet'!I36 | ... K70: ='Balance Sheet'!K36 | L70: Financial Liability
A71: Deferred revenue, non-current | B71: ='Balance Sheet'!B37 | C71: ='Balance Sheet'!C37 | D71: ='Balance Sheet'!D37 | E71: ='Balance Sheet'!E37 | F71: ='Balance Sheet'!F37 | G71: ='Balance Sheet'!G37 | H71: ='Balance Sheet'!H37 | I71: ='Balance Sheet'!I37 | ... K71: ='Balance Sheet'!K37 | L71: Operating Long-Term Liability
A72: Income taxes payable, non-current | B72: ='Balance Sheet'!B38 | C72: ='Balance Sheet'!C38 | D72: ='Balance Sheet'!D38 | E72: ='Balance Sheet'!E38 | F72: ='Balance Sheet'!F38 | G72: ='Balance Sheet'!G38 | H72: ='Balance Sheet'!H38 | I72: ='Balance Sheet'!I38 | ... K72: ='Balance Sheet'!K38 | L72: Operating Long-Term Liability | M72: ⚠ judgment: operating vs financial
A73: Deferred income taxes, non-current | B73: ='Balance Sheet'!B39 | C73: ='Balance Sheet'!C39 | D73: ='Balance Sheet'!D39 | E73: ='Balance Sheet'!E39 | F73: ='Balance Sheet'!F39 | G73: ='Balance Sheet'!G39 | H73: ='Balance Sheet'!H39 | I73: ='Balance Sheet'!I39 | ... K73: ='Balance Sheet'!K39 | L73: Operating Long-Term Liability | M73: ⚠ judgment: operating vs exclude
A74: Operating lease liabilities, non-current | B74: ='Balance Sheet'!B40 | C74: ='Balance Sheet'!C40 | D74: ='Balance Sheet'!D40 | E74: ='Balance Sheet'!E40 | F74: ='Balance Sheet'!F40 | G74: ='Balance Sheet'!G40 | H74: ='Balance Sheet'!H40 | I74: ='Balance Sheet'!I40 | ... K74: ='Balance Sheet'!K40 | L74: Financial Liability | M74: Convention: lease liabilities financial; lease ASSETS stay operating
A75: Other long-term liabilities | B75: ='Balance Sheet'!B41 | C75: ='Balance Sheet'!C41 | D75: ='Balance Sheet'!D41 | E75: ='Balance Sheet'!E41 | F75: ='Balance Sheet'!F41 | G75: ='Balance Sheet'!G41 | H75: ='Balance Sheet'!H41 | I75: ='Balance Sheet'!I41 | ... K75: ='Balance Sheet'!K41 | L75: Operating Long-Term Liability
A76: Class A/B/C stock and additional paid-in capital | B76: ='Balance Sheet'!B45 | C76: ='Balance Sheet'!C45 | D76: ='Balance Sheet'!D45 | E76: ='Balance Sheet'!E45 | F76: ='Balance Sheet'!F45 | G76: ='Balance Sheet'!G45 | H76: ='Balance Sheet'!H45 | I76: ='Balance Sheet'!I45 | ... K76: ='Balance Sheet'!K45 | L76: Equity
A77: Accumulated other comprehensive income (loss) | B77: ='Balance Sheet'!B46 | C77: ='Balance Sheet'!C46 | D77: ='Balance Sheet'!D46 | E77: ='Balance Sheet'!E46 | F77: ='Balance Sheet'!F46 | G77: ='Balance Sheet'!G46 | H77: ='Balance Sheet'!H46 | I77: ='Balance Sheet'!I46 | ... K77: ='Balance Sheet'!K46 | L77: Equity
A78: Retained earnings | B78: ='Balance Sheet'!B47 | C78: ='Balance Sheet'!C47 | D78: ='Balance Sheet'!D47 | E78: ='Balance Sheet'!E47 | F78: ='Balance Sheet'!F47 | G78: ='Balance Sheet'!G47 | H78: ='Balance Sheet'!H47 | I78: ='Balance Sheet'!I47 | ... K78: ='Balance Sheet'!K47 | L78: Equity
A80: D. QUARTERLY CONDENSED (NOPAT + AGGREGATES)
A81: Same classification as Section C: the Section E class cells reference the annual table — toggle Section C and these quarterly aggregates recompute. Flows are one quarter, not annualized.
B83: Q1 2024 | C83: Q2 2024 | D83: Q3 2024 | E83: Q4 2024 | F83: Q1 2025 | G83: Q2 2025 | H83: Q3 2025 | I83: Q4 2025 | J83: Q1 2026
A84: Line Item | B84: ='Income Statement'!B32 | C84: ='Income Statement'!C32 | D84: ='Income Statement'!D32 | E84: ='Income Statement'!E32 | F84: ='Income Statement'!F32 | G84: ='Income Statement'!G32 | H84: ='Income Statement'!H32 | I84: ='Income Statement'!I32 | J84: ='Income Statement'!J32
A85: Net Income | B85: ='Income Statement'!B46 | C85: ='Income Statement'!C46 | D85: ='Income Statement'!D46 | E85: ='Income Statement'!E46 | F85: ='Income Statement'!F46 | G85: ='Income Statement'!G46 | H85: ='Income Statement'!H46 | I85: ='Income Statement'!I46 | J85: ='Income Statement'!J46
A86: Other Income (Expense), Net | B86: ='Income Statement'!B43 | C86: ='Income Statement'!C43 | D86: ='Income Statement'!D43 | E86: ='Income Statement'!E43 | F86: ='Income Statement'!F43 | G86: ='Income Statement'!G43 | H86: ='Income Statement'!H43 | I86: ='Income Statement'!I43 | J86: ='Income Statement'!J43
A87: Interest Expense (XBRL-disclosed) | B87: 94 | C87: 67 | D87: 54 | E87: 53 | F87: 34 | G87: 261 | H87: 143 | I87: 298 | J87: 533
A88: Interest Income (XBRL-disclosed) | B88: 1061 | C88: 1090 | D88: 1243 | E88: 1088 | F88: 1001 | G88: 1050 | H88: 1076 | I88: 1210 | J88: 1381
A89: Net Interest Expense (Income) | B89: =B87-B88 | C89: =C87-C88 | D89: =D87-D88 | E89: =E87-E88 | F89: =F87-F88 | G89: =G87-G88 | H89: =H87-H88 | I89: =I87-I88 | J89: =J87-J88
A90: Pretax Income | B90: ='Income Statement'!B44 | C90: ='Income Statement'!C44 | D90: ='Income Statement'!D44 | E90: ='Income Statement'!E44 | F90: ='Income Statement'!F44 | G90: ='Income Statement'!G44 | H90: ='Income Statement'!H44 | I90: ='Income Statement'!I44 | J90: ='Income Statement'!J44
A91: Tax Expense | B91: =ABS('Income Statement'!B45) | C91: =ABS('Income Statement'!C45) | D91: =ABS('Income Statement'!D45) | E91: =ABS('Income Statement'!E45) | F91: =ABS('Income Statement'!F45) | G91: =ABS('Income Statement'!G45) | H91: =ABS('Income Statement'!H45) | I91: =ABS('Income Statement'!I45) | J91: =ABS('Income Statement'!J45)
A92: Effective Tax Rate | B92: =IFERROR(B91/B90,0) | C92: =IFERROR(C91/C90,0) | D92: =IFERROR(D91/D90,0) | E92: =IFERROR(E91/E90,0) | F92: =IFERROR(F91/F90,0) | G92: =IFERROR(G91/G90,0) | H92: =IFERROR(H91/H90,0) | I92: =IFERROR(I91/I90,0) | J92: =IFERROR(J91/J90,0) | M92: Quarterly ETRs are noisy (discrete items); the NIAT shield uses the quarter's own rate
A93: Net Interest After Tax | B93: =B89*(1-B92) | C93: =C89*(1-C92) | D93: =D89*(1-D92) | E93: =E89*(1-E92) | F93: =F89*(1-F92) | G93: =G89*(1-G92) | H93: =H89*(1-H92) | I93: =I89*(1-I92) | J93: =J89*(1-J92)
A94: NOPAT | B94: =B85+B93 | C94: =C85+C93 | D94: =D85+D93 | E94: =E85+E93 | F94: =F85+F93 | G94: =G85+G93 | H94: =H85+H93 | I94: =I85+I93 | J94: =J85+J93
A95: Quarterly interest rows are XBRL-DISCLOSED facts (us-gaap_InterestExpenseNonoperating / us-gaap_InterestIncomeOther; Q4 = FY fact - SUM Q1-Q3) and diverge from the annual rows 10-11 estimates (FY2024 XBRL 268/4,482 vs est. 365/4,963; FY2025 736/4,337 vs est. 1,200/4,801) - different bases, both shown.
A97: Operating Working Capital Assets | B97: =SUMIF($L$115:$L$142,"Operating Working Capital Asset",B$115:B$142) | C97: =SUMIF($L$115:$L$142,"Operating Working Capital Asset",C$115:C$142) | D97: =SUMIF($L$115:$L$142,"Operating Working Capital Asset",D$115:D$142) | E97: =SUMIF($L$115:$L$142,"Operating Working Capital Asset",E$115:E$142) | F97: =SUMIF($L$115:$L$142,"Operating Working Capital Asset",F$115:F$142) | G97: =SUMIF($L$115:$L$142,"Operating Working Capital Asset",G$115:G$142) | H97: =SUMIF($L$115:$L$142,"Operating Working Capital Asset",H$115:H$142) | I97: =SUMIF($L$115:$L$142,"Operating Working Capital Asset",I$115:I$142) | J97: =SUMIF($L$115:$L$142,"Operating Working Capital Asset",J$115:J$142)
A98: Operating Working Capital Liabilities | B98: =SUMIF($L$115:$L$142,"Operating Working Capital Liability",B$115:B$142) | C98: =SUMIF($L$115:$L$142,"Operating Working Capital Liability",C$115:C$142) | D98: =SUMIF($L$115:$L$142,"Operating Working Capital Liability",D$115:D$142) | E98: =SUMIF($L$115:$L$142,"Operating Working Capital Liability",E$115:E$142) | F98: =SUMIF($L$115:$L$142,"Operating Working Capital Liability",F$115:F$142) | G98: =SUMIF($L$115:$L$142,"Operating Working Capital Liability",G$115:G$142) | H98: =SUMIF($L$115:$L$142,"Operating Working Capital Liability",H$115:H$142) | I98: =SUMIF($L$115:$L$142,"Operating Working Capital Liability",I$115:I$142) | J98: =SUMIF($L$115:$L$142,"Operating Working Capital Liability",J$115:J$142)
A99: NET OPERATING WORKING CAPITAL (NOWC) | B99: =B97-B98 | C99: =C97-C98 | D99: =D97-D98 | E99: =E97-E98 | F99: =F97-F98 | G99: =G97-G98 | H99: =H97-H98 | I99: =I97-I98 | J99: =J97-J98
A100: Operating Long-Term Assets | B100: =SUMIF($L$115:$L$142,"Operating Long-Term Asset",B$115:B$142) | C100: =SUMIF($L$115:$L$142,"Operating Long-Term Asset",C$115:C$142) | D100: =SUMIF($L$115:$L$142,"Operating Long-Term Asset",D$115:D$142) | E100: =SUMIF($L$115:$L$142,"Operating Long-Term Asset",E$115:E$142) | F100: =SUMIF($L$115:$L$142,"Operating Long-Term Asset",F$115:F$142) | G100: =SUMIF($L$115:$L$142,"Operating Long-Term Asset",G$115:G$142) | H100: =SUMIF($L$115:$L$142,"Operating Long-Term Asset",H$115:H$142) | I100: =SUMIF($L$115:$L$142,"Operating Long-Term Asset",I$115:I$142) | J100: =SUMIF($L$115:$L$142,"Operating Long-Term Asset",J$115:J$142)
A101: Operating Long-Term Liabilities | B101: =SUMIF($L$115:$L$142,"Operating Long-Term Liability",B$115:B$142) | C101: =SUMIF($L$115:$L$142,"Operating Long-Term Liability",C$115:C$142) | D101: =SUMIF($L$115:$L$142,"Operating Long-Term Liability",D$115:D$142) | E101: =SUMIF($L$115:$L$142,"Operating Long-Term Liability",E$115:E$142) | F101: =SUMIF($L$115:$L$142,"Operating Long-Term Liability",F$115:F$142) | G101: =SUMIF($L$115:$L$142,"Operating Long-Term Liability",G$115:G$142) | H101: =SUMIF($L$115:$L$142,"Operating Long-Term Liability",H$115:H$142) | I101: =SUMIF($L$115:$L$142,"Operating Long-Term Liability",I$115:I$142) | J101: =SUMIF($L$115:$L$142,"Operating Long-Term Liability",J$115:J$142)
A102: NET OPERATING LT ASSETS | B102: =B100-B101 | C102: =C100-C101 | D102: =D100-D101 | E102: =E100-E101 | F102: =F100-F101 | G102: =G100-G101 | H102: =H100-H101 | I102: =I100-I101 | J102: =J100-J101
A103: NET OPERATING ASSETS (NOA) | B103: =B99+B102 | C103: =C99+C102 | D103: =D99+D102 | E103: =E99+E102 | F103: =F99+F102 | G103: =G99+G102 | H103: =H99+H102 | I103: =I99+I102 | J103: =J99+J102
A104: Financial Assets | B104: =SUMIF($L$115:$L$142,"Financial Asset",B$115:B$142) | C104: =SUMIF($L$115:$L$142,"Financial Asset",C$115:C$142) | D104: =SUMIF($L$115:$L$142,"Financial Asset",D$115:D$142) | E104: =SUMIF($L$115:$L$142,"Financial Asset",E$115:E$142) | F104: =SUMIF($L$115:$L$142,"Financial Asset",F$115:F$142) | G104: =SUMIF($L$115:$L$142,"Financial Asset",G$115:G$142) | H104: =SUMIF($L$115:$L$142,"Financial Asset",H$115:H$142) | I104: =SUMIF($L$115:$L$142,"Financial Asset",I$115:I$142) | J104: =SUMIF($L$115:$L$142,"Financial Asset",J$115:J$142)
A105: Financial Liabilities | B105: =SUMIF($L$115:$L$142,"Financial Liability",B$115:B$142) | C105: =SUMIF($L$115:$L$142,"Financial Liability",C$115:C$142) | D105: =SUMIF($L$115:$L$142,"Financial Liability",D$115:D$142) | E105: =SUMIF($L$115:$L$142,"Financial Liability",E$115:E$142) | F105: =SUMIF($L$115:$L$142,"Financial Liability",F$115:F$142) | G105: =SUMIF($L$115:$L$142,"Financial Liability",G$115:G$142) | H105: =SUMIF($L$115:$L$142,"Financial Liability",H$115:H$142) | I105: =SUMIF($L$115:$L$142,"Financial Liability",I$115:I$142) | J105: =SUMIF($L$115:$L$142,"Financial Liability",J$115:J$142)
A106: NET DEBT (Fin Liab - Fin Assets) | B106: =B105-B104 | C106: =C105-C104 | D106: =D105-D104 | E106: =E105-E104 | F106: =F105-F104 | G106: =G105-G104 | H106: =H105-H104 | I106: =I105-I104 | J106: =J105-J104
A107: EQUITY (NOA - Net Debt) | B107: =B103-B106 | C107: =C103-C106 | D107: =D103-D106 | E107: =E103-E106 | F107: =F103-F106 | G107: =G103-G106 | H107: =H103-H106 | I107: =I103-I106 | J107: =J103-J106
A108: Reported Equity | B108: ='Balance Sheet'!B99 | C108: ='Balance Sheet'!C99 | D108: ='Balance Sheet'!D99 | E108: ='Balance Sheet'!E99 | F108: ='Balance Sheet'!F99 | G108: ='Balance Sheet'!G99 | H108: ='Balance Sheet'!H99 | I108: ='Balance Sheet'!I99 | J108: ='Balance Sheet'!J99
A109: TOTAL CAPITAL (Net Debt + Equity) | B109: =B106+B107 | C109: =C106+C107 | D109: =D106+D107 | E109: =E106+E107 | F109: =F106+F107 | G109: =G106+G107 | H109: =H106+H107 | I109: =I106+I107 | J109: =J106+J107
A110: CHECK: implied equity = reported equity | B110: =IF(ABS(B107-B108)<1,"OK","CHECK") | C110: =IF(ABS(C107-C108)<1,"OK","CHECK") | D110: =IF(ABS(D107-D108)<1,"OK","CHECK") | E110: =IF(ABS(E107-E108)<1,"OK","CHECK") | F110: =IF(ABS(F107-F108)<1,"OK","CHECK") | G110: =IF(ABS(G107-G108)<1,"OK","CHECK") | H110: =IF(ABS(H107-H108)<1,"OK","CHECK") | I110: =IF(ABS(I107-I108)<1,"OK","CHECK") | J110: =IF(ABS(J107-J108)<1,"OK","CHECK")
A112: E. QUARTERLY BS CLASSIFICATION (class cells reference Section C — toggle there)
B113: Q1 2024 | C113: Q2 2024 | D113: Q3 2024 | E113: Q4 2024 | F113: Q1 2025 | G113: Q2 2025 | H113: Q3 2025 | I113: Q4 2025 | J113: Q1 2026
A114: Line Item | B114: 45382 | C114: 45473 | D114: 45565 | E114: 45657 | F114: 45747 | G114: 45838 | H114: 45930 | I114: 46022 | J114: 46112 | L114: Class (=Section C)
A115: Cash and cash equivalents | B115: ='Balance Sheet'!B59 | C115: ='Balance Sheet'!C59 | D115: ='Balance Sheet'!D59 | E115: ='Balance Sheet'!E59 | F115: ='Balance Sheet'!F59 | G115: ='Balance Sheet'!G59 | H115: ='Balance Sheet'!H59 | I115: ='Balance Sheet'!I59 | J115: ='Balance Sheet'!J59 | L115: =$L$51
A116: Marketable securities | B116: ='Balance Sheet'!B60 | C116: ='Balance Sheet'!C60 | D116: ='Balance Sheet'!D60 | E116: ='Balance Sheet'!E60 | F116: ='Balance Sheet'!F60 | G116: ='Balance Sheet'!G60 | H116: ='Balance Sheet'!H60 | I116: ='Balance Sheet'!I60 | J116: ='Balance Sheet'!J60 | L116: =$L$52
A117: Accounts receivable, net | B117: ='Balance Sheet'!B61 | C117: ='Balance Sheet'!C61 | D117: ='Balance Sheet'!D61 | E117: ='Balance Sheet'!E61 | F117: ='Balance Sheet'!F61 | G117: ='Balance Sheet'!G61 | H117: ='Balance Sheet'!H61 | I117: ='Balance Sheet'!I61 | J117: ='Balance Sheet'!J61 | L117: =$L$53
A118: Income taxes receivable, net | B118: ='Balance Sheet'!B62 | C118: ='Balance Sheet'!C62 | D118: ='Balance Sheet'!D62 | E118: ='Balance Sheet'!E62 | F118: ='Balance Sheet'!F62 | G118: ='Balance Sheet'!G62 | H118: ='Balance Sheet'!H62 | I118: ='Balance Sheet'!I62 | J118: ='Balance Sheet'!J62 | L118: =$L$54
A119: Inventory | B119: ='Balance Sheet'!B63 | C119: ='Balance Sheet'!C63 | D119: ='Balance Sheet'!D63 | E119: ='Balance Sheet'!E63 | F119: ='Balance Sheet'!F63 | G119: ='Balance Sheet'!G63 | H119: ='Balance Sheet'!H63 | I119: ='Balance Sheet'!I63 | J119: ='Balance Sheet'!J63 | L119: =$L$55
...

Sheet ALT DuPont
A1: Alphabet Inc. (GOOGL) — Alternative DuPont Decomposition
A2: ROE = RNOA + FLEV × Spread
A3: All values linked to Condensed Financials
A5: Metric | B5: ='Income Statement'!B6 | C5: ='Income Statement'!C6 | D5: ='Income Statement'!D6 | E5: ='Income Statement'!E6 | F5: ='Income Statement'!F6 | G5: ='Income Statement'!G6 | H5: ='Income Statement'!H6 | I5: ='Income Statement'!I6 | ... K5: ='Income Statement'!K6
A7: Revenue | B7: ='Income Statement'!B7 | C7: ='Income Statement'!C7 | D7: ='Income Statement'!D7 | E7: ='Income Statement'!E7 | F7: ='Income Statement'!F7 | G7: ='Income Statement'!G7 | H7: ='Income Statement'!H7 | I7: ='Income Statement'!I7 | ... K7: ='Income Statement'!K7
A8: NOPAT | B8: ='Condensed Financials'!B17 | C8: ='Condensed Financials'!C17 | D8: ='Condensed Financials'!D17 | E8: ='Condensed Financials'!E17 | F8: ='Condensed Financials'!F17 | G8: ='Condensed Financials'!G17 | H8: ='Condensed Financials'!H17 | I8: ='Condensed Financials'!I17 | ... K8: ='Condensed Financials'!K17
A9: Net Income | B9: ='Condensed Financials'!B8 | C9: ='Condensed Financials'!C8 | D9: ='Condensed Financials'!D8 | E9: ='Condensed Financials'!E8 | F9: ='Condensed Financials'!F8 | G9: ='Condensed Financials'!G8 | H9: ='Condensed Financials'!H8 | I9: ='Condensed Financials'!I8 | ... K9: ='Condensed Financials'!K8
A10: Net Interest After Tax | B10: ='Condensed Financials'!B16 | C10: ='Condensed Financials'!C16 | D10: ='Condensed Financials'!D16 | E10: ='Condensed Financials'!E16 | F10: ='Condensed Financials'!F16 | G10: ='Condensed Financials'!G16 | H10: ='Condensed Financials'!H16 | I10: ='Condensed Financials'!I16 | ... K10: ='Condensed Financials'!K16
A12: NOA (Beginning) | B12: n/a | C12: ='Condensed Financials'!B33 | D12: ='Condensed Financials'!C33 | E12: ='Condensed Financials'!D33 | F12: ='Condensed Financials'!E33 | G12: ='Condensed Financials'!F33 | H12: ='Condensed Financials'!G33 | I12: ='Condensed Financials'!H33 | J12: ='Condensed Financials'!I33 | K12: ='Condensed Financials'!J33
A13: Net Debt (Beginning) | B13: n/a | C13: ='Condensed Financials'!B37 | D13: ='Condensed Financials'!C37 | E13: ='Condensed Financials'!D37 | F13: ='Condensed Financials'!E37 | G13: ='Condensed Financials'!F37 | H13: ='Condensed Financials'!G37 | I13: ='Condensed Financials'!H37 | J13: ='Condensed Financials'!I37 | K13: ='Condensed Financials'!J37
A14: Equity (Beginning) | B14: n/a | C14: ='Condensed Financials'!B40 | D14: ='Condensed Financials'!C40 | E14: ='Condensed Financials'!D40 | F14: ='Condensed Financials'!E40 | G14: ='Condensed Financials'!F40 | H14: ='Condensed Financials'!G40 | I14: ='Condensed Financials'!H40 | J14: ='Condensed Financials'!I40 | K14: ='Condensed Financials'!J40
A16: Sales Growth | B16: n/a | C16: =C7/B7-1 | D16: =D7/C7-1 | E16: =E7/D7-1 | F16: =F7/E7-1 | G16: =G7/F7-1 | H16: =H7/G7-1 | I16: =I7/H7-1 | J16: =J7/I7-1 | K16: =K7/J7-1
A17: NOPAT Margin | B17: =IFERROR(B8/B7,0) | C17: =IFERROR(C8/C7,0) | D17: =IFERROR(D8/D7,0) | E17: =IFERROR(E8/E7,0) | F17: =IFERROR(F8/F7,0) | G17: =IFERROR(G8/G7,0) | H17: =IFERROR(H8/H7,0) | I17: =IFERROR(I8/I7,0) | ... K17: =IFERROR(K8/K7,0)
A18: Avg NOA | B18: n/a | C18: =('Condensed Financials'!C33+'Condensed Financials'!B33)/2 | D18: =('Condensed Financials'!D33+'Condensed Financials'!C33)/2 | E18: =('Condensed Financials'!E33+'Condensed Financials'!D33)/2 | F18: =('Condensed Financials'!F33+'Condensed Financials'!E33)/2 | G18: =('Condensed Financials'!G33+'Condensed Financials'!F33)/2 | H18: =('Condensed Financials'!H33+'Condensed Financials'!G33)/2 | I18: =('Condensed Financials'!I33+'Condensed Financials'!H33)/2 | J18: =('Condensed Financials'!J33+'Condensed Financials'!I33)/2 | K18: =('Condensed Financials'!K33+'Condensed Financials'!J33)/2
A19: Asset Turnover (Revenue / Avg NOA) | B19: n/a | C19: =IFERROR(C7/C18,0) | D19: =IFERROR(D7/D18,0) | E19: =IFERROR(E7/E18,0) | F19: =IFERROR(F7/F18,0) | G19: =IFERROR(G7/G18,0) | H19: =IFERROR(H7/H18,0) | I19: =IFERROR(I7/I18,0) | J19: =IFERROR(J7/J18,0) | K19: =IFERROR(K7/K18,0)
A20: RNOA (NOPAT Margin × Turnover) | B20: n/a | C20: =C17*C19 | D20: =D17*D19 | E20: =E17*E19 | F20: =F17*F19 | G20: =G17*G19 | H20: =H17*H19 | I20: =I17*I19 | J20: =J17*J19 | K20: =K17*K19
A22: Avg Net Debt | B22: n/a | C22: =('Condensed Financials'!C37+'Condensed Financials'!B37)/2 | D22: =('Condensed Financials'!D37+'Condensed Financials'!C37)/2 | E22: =('Condensed Financials'!E37+'Condensed Financials'!D37)/2 | F22: =('Condensed Financials'!F37+'Condensed Financials'!E37)/2 | G22: =('Condensed Financials'!G37+'Condensed Financials'!F37)/2 | H22: =('Condensed Financials'!H37+'Condensed Financials'!G37)/2 | I22: =('Condensed Financials'!I37+'Condensed Financials'!H37)/2 | J22: =('Condensed Financials'!J37+'Condensed Financials'!I37)/2 | K22: =('Condensed Financials'!K37+'Condensed Financials'!J37)/2
A23: After-tax Cost of Debt | B23: n/a | C23: =IFERROR(C10/C22,0) | D23: =IFERROR(D10/D22,0) | E23: =IFERROR(E10/E22,0) | F23: =IFERROR(F10/F22,0) | G23: =IFERROR(G10/G22,0) | H23: =IFERROR(H10/H22,0) | I23: =IFERROR(I10/I22,0) | J23: =IFERROR(J10/J22,0) | K23: =IFERROR(K10/K22,0)
A24: Spread (RNOA - Cost of Debt) | B24: n/a | C24: =C20-C23 | D24: =D20-D23 | E24: =E20-E23 | F24: =F20-F23 | G24: =G20-G23 | H24: =H20-H23 | I24: =I20-I23 | J24: =J20-J23 | K24: =K20-K23
A25: Avg Equity | B25: n/a | C25: =('Condensed Financials'!C40+'Condensed Financials'!B40)/2 | D25: =('Condensed Financials'!D40+'Condensed Financials'!C40)/2 | E25: =('Condensed Financials'!E40+'Condensed Financials'!D40)/2 | F25: =('Condensed Financials'!F40+'Condensed Financials'!E40)/2 | G25: =('Condensed Financials'!G40+'Condensed Financials'!F40)/2 | H25: =('Condensed Financials'!H40+'Condensed Financials'!G40)/2 | I25: =('Condensed Financials'!I40+'Condensed Financials'!H40)/2 | J25: =('Condensed Financials'!J40+'Condensed Financials'!I40)/2 | K25: =('Condensed Financials'!K40+'Condensed Financials'!J40)/2
A26: Net Financial Leverage (Avg ND / Avg Eq) | B26: n/a | C26: =IFERROR(C22/C25,0) | D26: =IFERROR(D22/D25,0) | E26: =IFERROR(E22/E25,0) | F26: =IFERROR(F22/F25,0) | G26: =IFERROR(G22/G25,0) | H26: =IFERROR(H22/H25,0) | I26: =IFERROR(I22/I25,0) | J26: =IFERROR(J22/J25,0) | K26: =IFERROR(K22/K25,0)
A27: Financial Leverage Gain (Spread × FLEV) | B27: n/a | C27: =C24*C26 | D27: =D24*D26 | E27: =E24*E26 | F27: =F24*F26 | G27: =G24*G26 | H27: =H24*H26 | I27: =I24*I26 | J27: =J24*J26 | K27: =K24*K26
A29: ROE (Decomposed) = RNOA + Fin Lev Gain | B29: n/a | C29: =C20+C27 | D29: =D20+D27 | E29: =E20+E27 | F29: =F20+F27 | G29: =G20+G27 | H29: =H20+H27 | I29: =I20+I27 | J29: =J20+J27 | K29: =K20+K27
A30: Actual ROE (NI / Avg Equity) | B30: n/a | C30: =IFERROR(C9/C25,0) | D30: =IFERROR(D9/D25,0) | E30: =IFERROR(E9/E25,0) | F30: =IFERROR(F9/F25,0) | G30: =IFERROR(G9/G25,0) | H30: =IFERROR(H9/H25,0) | I30: =IFERROR(I9/I25,0) | J30: =IFERROR(J9/J25,0) | K30: =IFERROR(K9/K25,0)
A31: CHECK: |Decomp - Actual| < 0.1% | B31: n/a | C31: =IF(ABS(C29-C30)<0.001,"OK","CHECK") | D31: =IF(ABS(D29-D30)<0.001,"OK","CHECK") | E31: =IF(ABS(E29-E30)<0.001,"OK","CHECK") | F31: =IF(ABS(F29-F30)<0.001,"OK","CHECK") | G31: =IF(ABS(G29-G30)<0.001,"OK","CHECK") | H31: =IF(ABS(H29-H30)<0.001,"OK","CHECK") | I31: =IF(ABS(I29-I30)<0.001,"OK","CHECK") | J31: =IF(ABS(J29-J30)<0.001,"OK","CHECK") | K31: =IF(ABS(K29-K30)<0.001,"OK","CHECK")
A33: QUARTERLY DUPONT (FLOWS ANNUALIZED ×4)
A34: Quarterly NOPAT/NIAT/NI are annualized (×4) against average positions; Sales Growth is QoQ (not seasonally adjusted). The first quarter column's averages use the FY2023 annual Condensed column (I) as the prior period.
B36: Q1 2024 | C36: Q2 2024 | D36: Q3 2024 | E36: Q4 2024 | F36: Q1 2025 | G36: Q2 2025 | H36: Q3 2025 | I36: Q4 2025 | J36: Q1 2026
A37: Line Item | B37: ='Income Statement'!B32 | C37: ='Income Statement'!C32 | D37: ='Income Statement'!D32 | E37: ='Income Statement'!E32 | F37: ='Income Statement'!F32 | G37: ='Income Statement'!G32 | H37: ='Income Statement'!H32 | I37: ='Income Statement'!I32 | J37: ='Income Statement'!J32
A38: Sales Growth (QoQ) | B38: n/a | C38: ='Income Statement'!C34/'Income Statement'!B34-1 | D38: ='Income Statement'!D34/'Income Statement'!C34-1 | E38: ='Income Statement'!E34/'Income Statement'!D34-1 | F38: ='Income Statement'!F34/'Income Statement'!E34-1 | G38: ='Income Statement'!G34/'Income Statement'!F34-1 | H38: ='Income Statement'!H34/'Income Statement'!G34-1 | I38: ='Income Statement'!I34/'Income Statement'!H34-1 | J38: ='Income Statement'!J34/'Income Statement'!I34-1
A39: NOPAT Margin (quarter) | B39: ='Condensed Financials'!B94/'Income Statement'!B34 | C39: ='Condensed Financials'!C94/'Income Statement'!C34 | D39: ='Condensed Financials'!D94/'Income Statement'!D34 | E39: ='Condensed Financials'!E94/'Income Statement'!E34 | F39: ='Condensed Financials'!F94/'Income Statement'!F34 | G39: ='Condensed Financials'!G94/'Income Statement'!G34 | H39: ='Condensed Financials'!H94/'Income Statement'!H34 | I39: ='Condensed Financials'!I94/'Income Statement'!I34 | J39: ='Condensed Financials'!J94/'Income Statement'!J34
A40: Avg NOA | B40: =('Condensed Financials'!B103+'Condensed Financials'!I33)/2 | C40: =('Condensed Financials'!C103+'Condensed Financials'!B103)/2 | D40: =('Condensed Financials'!D103+'Condensed Financials'!C103)/2 | E40: =('Condensed Financials'!E103+'Condensed Financials'!D103)/2 | F40: =('Condensed Financials'!F103+'Condensed Financials'!E103)/2 | G40: =('Condensed Financials'!G103+'Condensed Financials'!F103)/2 | H40: =('Condensed Financials'!H103+'Condensed Financials'!G103)/2 | I40: =('Condensed Financials'!I103+'Condensed Financials'!H103)/2 | J40: =('Condensed Financials'!J103+'Condensed Financials'!I103)/2
A41: Asset Turnover (annualized) | B41: ='Income Statement'!B34*4/B40 | C41: ='Income Statement'!C34*4/C40 | D41: ='Income Statement'!D34*4/D40 | E41: ='Income Statement'!E34*4/E40 | F41: ='Income Statement'!F34*4/F40 | G41: ='Income Statement'!G34*4/G40 | H41: ='Income Statement'!H34*4/H40 | I41: ='Income Statement'!I34*4/I40 | J41: ='Income Statement'!J34*4/J40
A42: RNOA (annualized) | B42: =B39*B41 | C42: =C39*C41 | D42: =D39*D41 | E42: =E39*E41 | F42: =F39*F41 | G42: =G39*G41 | H42: =H39*H41 | I42: =I39*I41 | J42: =J39*J41
A43: Avg Net Debt | B43: =('Condensed Financials'!B106+'Condensed Financials'!I37)/2 | C43: =('Condensed Financials'!C106+'Condensed Financials'!B106)/2 | D43: =('Condensed Financials'!D106+'Condensed Financials'!C106)/2 | E43: =('Condensed Financials'!E106+'Condensed Financials'!D106)/2 | F43: =('Condensed Financials'!F106+'Condensed Financials'!E106)/2 | G43: =('Condensed Financials'!G106+'Condensed Financials'!F106)/2 | H43: =('Condensed Financials'!H106+'Condensed Financials'!G106)/2 | I43: =('Condensed Financials'!I106+'Condensed Financials'!H106)/2 | J43: =('Condensed Financials'!J106+'Condensed Financials'!I106)/2
A44: After-tax Cost of Debt (annualized) | B44: =IFERROR('Condensed Financials'!B93*4/B43,0) | C44: =IFERROR('Condensed Financials'!C93*4/C43,0) | D44: =IFERROR('Condensed Financials'!D93*4/D43,0) | E44: =IFERROR('Condensed Financials'!E93*4/E43,0) | F44: =IFERROR('Condensed Financials'!F93*4/F43,0) | G44: =IFERROR('Condensed Financials'!G93*4/G43,0) | H44: =IFERROR('Condensed Financials'!H93*4/H43,0) | I44: =IFERROR('Condensed Financials'!I93*4/I43,0) | J44: =IFERROR('Condensed Financials'!J93*4/J43,0)
A45: Spread (RNOA - Cost of Debt) | B45: =B42-B44 | C45: =C42-C44 | D45: =D42-D44 | E45: =E42-E44 | F45: =F42-F44 | G45: =G42-G44 | H45: =H42-H44 | I45: =I42-I44 | J45: =J42-J44
A46: Avg Equity | B46: =('Condensed Financials'!B107+'Condensed Financials'!I40)/2 | C46: =('Condensed Financials'!C107+'Condensed Financials'!B107)/2 | D46: =('Condensed Financials'!D107+'Condensed Financials'!C107)/2 | E46: =('Condensed Financials'!E107+'Condensed Financials'!D107)/2 | F46: =('Condensed Financials'!F107+'Condensed Financials'!E107)/2 | G46: =('Condensed Financials'!G107+'Condensed Financials'!F107)/2 | H46: =('Condensed Financials'!H107+'Condensed Financials'!G107)/2 | I46: =('Condensed Financials'!I107+'Condensed Financials'!H107)/2 | J46: =('Condensed Financials'!J107+'Condensed Financials'!I107)/2
A47: Net Financial Leverage (Avg ND / Avg Eq) | B47: =IFERROR(B43/B46,0) | C47: =IFERROR(C43/C46,0) | D47: =IFERROR(D43/D46,0) | E47: =IFERROR(E43/E46,0) | F47: =IFERROR(F43/F46,0) | G47: =IFERROR(G43/G46,0) | H47: =IFERROR(H43/H46,0) | I47: =IFERROR(I43/I46,0) | J47: =IFERROR(J43/J46,0)
A48: Financial Leverage Gain (Spread × FLEV) | B48: =B45*B47 | C48: =C45*C47 | D48: =D45*D47 | E48: =E45*E47 | F48: =F45*F47 | G48: =G45*G47 | H48: =H45*H47 | I48: =I45*I47 | J48: =J45*J47
A49: ROE (Decomposed, annualized) | B49: =B42+B48 | C49: =C42+C48 | D49: =D42+D48 | E49: =E42+E48 | F49: =F42+F48 | G49: =G42+G48 | H49: =H42+H48 | I49: =I42+I48 | J49: =J42+J48
A50: Actual ROE (NI ×4 / Avg Equity) | B50: =IFERROR('Condensed Financials'!B85*4/B46,0) | C50: =IFERROR('Condensed Financials'!C85*4/C46,0) | D50: =IFERROR('Condensed Financials'!D85*4/D46,0) | E50: =IFERROR('Condensed Financials'!E85*4/E46,0) | F50: =IFERROR('Condensed Financials'!F85*4/F46,0) | G50: =IFERROR('Condensed Financials'!G85*4/G46,0) | H50: =IFERROR('Condensed Financials'!H85*4/H46,0) | I50: =IFERROR('Condensed Financials'!I85*4/I46,0) | J50: =IFERROR('Condensed Financials'!J85*4/J46,0)
A51: CHECK: |Decomp - Actual| < 0.1% | B51: =IF(ABS(B49-B50)<0.001,"OK","CHECK") | C51: =IF(ABS(C49-C50)<0.001,"OK","CHECK") | D51: =IF(ABS(D49-D50)<0.001,"OK","CHECK") | E51: =IF(ABS(E49-E50)<0.001,"OK","CHECK") | F51: =IF(ABS(F49-F50)<0.001,"OK","CHECK") | G51: =IF(ABS(G49-G50)<0.001,"OK","CHECK") | H51: =IF(ABS(H49-H50)<0.001,"OK","CHECK") | I51: =IF(ABS(I49-I50)<0.001,"OK","CHECK") | J51: =IF(ABS(J49-J50)<0.001,"OK","CHECK")

Sheet Earnings Quality
A1: Alphabet Inc. (GOOGL) — Earnings Quality
A2: SCREENS, NOT VERDICTS: thresholds are calibrated on cross-sections; for a mega-cap a flag is a tripwire that demands explanation, not an accusation.
A3: Accruals / M-Score / F-Score are live formulas over the source tabs; Benford rows are script-computed from each filing's FULL XBRL fact set (build_quality.py).
A5: ANNUAL
A6: Line Item | B6: ='Income Statement'!B6 | C6: ='Income Statement'!C6 | D6: ='Income Statement'!D6 | E6: ='Income Statement'!E6 | F6: ='Income Statement'!F6 | G6: ='Income Statement'!G6 | H6: ='Income Statement'!H6 | I6: ='Income Statement'!I6 | ... K6: ='Income Statement'!K6
A8: A. ACCRUALS & CASH CONVERSION
A9: NOA (Condensed) | B9: ='Condensed Financials'!B33 | C9: ='Condensed Financials'!C33 | D9: ='Condensed Financials'!D33 | E9: ='Condensed Financials'!E33 | F9: ='Condensed Financials'!F33 | G9: ='Condensed Financials'!G33 | H9: ='Condensed Financials'!H33 | I9: ='Condensed Financials'!I33 | ... K9: ='Condensed Financials'!K33
A10: BS accruals = dNOA | B10: n/a | C10: =C9-B9 | D10: =D9-C9 | E10: =E9-D9 | F10: =F9-E9 | G10: =G9-F9 | H10: =H9-G9 | I10: =I9-H9 | J10: =J9-I9 | K10: =K9-J9
A11: Avg NOA | B11: n/a | C11: =(C9+B9)/2 | D11: =(D9+C9)/2 | E11: =(E9+D9)/2 | F11: =(F9+E9)/2 | G11: =(G9+F9)/2 | H11: =(H9+G9)/2 | I11: =(I9+H9)/2 | J11: =(J9+I9)/2 | K11: =(K9+J9)/2
A12: Scaled BS accruals (dNOA/avg NOA) | B12: n/a | C12: =C10/C11 | D12: =D10/D11 | E12: =E10/E11 | F12: =F10/F11 | G12: =G10/G11 | H12: =H10/H11 | I12: =I10/I11 | J12: =J10/J11 | K12: =K10/K11 | L12: High positive accruals with weak cash conversion = the classic earnings-quality red flag (Sloan 1996). GOOGL's NI carries large NON-cash unrealized securities gains (see Core Earnings Bridge) - they inflate income accruals mechanically
A13: Net income | B13: ='Income Statement'!B19 | C13: ='Income Statement'!C19 | D13: ='Income Statement'!D19 | E13: ='Income Statement'!E19 | F13: ='Income Statement'!F19 | G13: ='Income Statement'!G19 | H13: ='Income Statement'!H19 | I13: ='Income Statement'!I19 | ... K13: ='Income Statement'!K19
A14: CFO | B14: ='Cash Flow Statement'!B26 | C14: ='Cash Flow Statement'!C26 | D14: ='Cash Flow Statement'!D26 | E14: ='Cash Flow Statement'!E26 | F14: ='Cash Flow Statement'!F26 | G14: ='Cash Flow Statement'!G26 | H14: ='Cash Flow Statement'!H26 | I14: ='Cash Flow Statement'!I26 | ... K14: ='Cash Flow Statement'!K26
A15: Income accruals = NI - CFO | B15: =B13-B14 | C15: =C13-C14 | D15: =D13-D14 | E15: =E13-E14 | F15: =F13-F14 | G15: =G13-G14 | H15: =H13-H14 | I15: =I13-I14 | ... K15: =K13-K14
A16: Scaled income accruals ((NI-CFO)/avg NOA) | B16: n/a | C16: =C15/C11 | D16: =D15/D11 | E16: =E15/E11 | F16: =F15/F11 | G16: =G15/G11 | H16: =H15/H11 | I16: =I15/I11 | J16: =J15/J11 | K16: =K15/K11
A17: Cash conversion (CFO/NI) | B17: =IFERROR('Cash Flow Statement'!B26/'Income Statement'!B19,"n/m") | C17: =IFERROR('Cash Flow Statement'!C26/'Income Statement'!C19,"n/m") | D17: =IFERROR('Cash Flow Statement'!D26/'Income Statement'!D19,"n/m") | E17: =IFERROR('Cash Flow Statement'!E26/'Income Statement'!E19,"n/m") | F17: =IFERROR('Cash Flow Statement'!F26/'Income Statement'!F19,"n/m") | G17: =IFERROR('Cash Flow Statement'!G26/'Income Statement'!G19,"n/m") | H17: =IFERROR('Cash Flow Statement'!H26/'Income Statement'!H19,"n/m") | I17: =IFERROR('Cash Flow Statement'!I26/'Income Statement'!I19,"n/m") | ... K17: =IFERROR('Cash Flow Statement'!K26/'Income Statement'!K19,"n/m")
A19: B. BENEISH M-SCORE (8-variable, YoY)
A20: DSRI (receivables/sales index) | B20: n/a | C20: =IFERROR(('Balance Sheet'!C10/'Income Statement'!C7)/('Balance Sheet'!B10/'Income Statement'!B7),"n/m") | D20: =IFERROR(('Balance Sheet'!D10/'Income Statement'!D7)/('Balance Sheet'!C10/'Income Statement'!C7),"n/m") | E20: =IFERROR(('Balance Sheet'!E10/'Income Statement'!E7)/('Balance Sheet'!D10/'Income Statement'!D7),"n/m") | F20: =IFERROR(('Balance Sheet'!F10/'Income Statement'!F7)/('Balance Sheet'!E10/'Income Statement'!E7),"n/m") | G20: =IFERROR(('Balance Sheet'!G10/'Income Statement'!G7)/('Balance Sheet'!F10/'Income Statement'!F7),"n/m") | H20: =IFERROR(('Balance Sheet'!H10/'Income Statement'!H7)/('Balance Sheet'!G10/'Income Statement'!G7),"n/m") | I20: =IFERROR(('Balance Sheet'!I10/'Income Statement'!I7)/('Balance Sheet'!H10/'Income Statement'!H7),"n/m") | J20: =IFERROR(('Balance Sheet'!J10/'Income Statement'!J7)/('Balance Sheet'!I10/'Income Statement'!I7),"n/m") | K20: =IFERROR(('Balance Sheet'!K10/'Income Statement'!K7)/('Balance Sheet'!J10/'Income Statement'!J7),"n/m")
A21: GMI (gross margin index) | B21: n/a | C21: =IFERROR(('Income Statement'!B9/'Income Statement'!B7)/('Income Statement'!C9/'Income Statement'!C7),"n/m") | D21: =IFERROR(('Income Statement'!C9/'Income Statement'!C7)/('Income Statement'!D9/'Income Statement'!D7),"n/m") | E21: =IFERROR(('Income Statement'!D9/'Income Statement'!D7)/('Income Statement'!E9/'Income Statement'!E7),"n/m") | F21: =IFERROR(('Income Statement'!E9/'Income Statement'!E7)/('Income Statement'!F9/'Income Statement'!F7),"n/m") | G21: =IFERROR(('Income Statement'!F9/'Income Statement'!F7)/('Income Statement'!G9/'Income Statement'!G7),"n/m") | H21: =IFERROR(('Income Statement'!G9/'Income Statement'!G7)/('Income Statement'!H9/'Income Statement'!H7),"n/m") | I21: =IFERROR(('Income Statement'!H9/'Income Statement'!H7)/('Income Statement'!I9/'Income Statement'!I7),"n/m") | J21: =IFERROR(('Income Statement'!I9/'Income Statement'!I7)/('Income Statement'!J9/'Income Statement'!J7),"n/m") | K21: =IFERROR(('Income Statement'!J9/'Income Statement'!J7)/('Income Statement'!K9/'Income Statement'!K7),"n/m")
A22: AQI (asset quality index) | B22: n/a | C22: =IFERROR((1-('Balance Sheet'!C14+'Balance Sheet'!C19)/'Balance Sheet'!C24)/(1-('Balance Sheet'!B14+'Balance Sheet'!B19)/'Balance Sheet'!B24),"n/m") | D22: =IFERROR((1-('Balance Sheet'!D14+'Balance Sheet'!D19)/'Balance Sheet'!D24)/(1-('Balance Sheet'!C14+'Balance Sheet'!C19)/'Balance Sheet'!C24),"n/m") | E22: =IFERROR((1-('Balance Sheet'!E14+'Balance Sheet'!E19)/'Balance Sheet'!E24)/(1-('Balance Sheet'!D14+'Balance Sheet'!D19)/'Balance Sheet'!D24),"n/m") | F22: =IFERROR((1-('Balance Sheet'!F14+'Balance Sheet'!F19)/'Balance Sheet'!F24)/(1-('Balance Sheet'!E14+'Balance Sheet'!E19)/'Balance Sheet'!E24),"n/m") | G22: =IFERROR((1-('Balance Sheet'!G14+'Balance Sheet'!G19)/'Balance Sheet'!G24)/(1-('Balance Sheet'!F14+'Balance Sheet'!F19)/'Balance Sheet'!F24),"n/m") | H22: =IFERROR((1-('Balance Sheet'!H14+'Balance Sheet'!H19)/'Balance Sheet'!H24)/(1-('Balance Sheet'!G14+'Balance Sheet'!G19)/'Balance Sheet'!G24),"n/m") | I22: =IFERROR((1-('Balance Sheet'!I14+'Balance Sheet'!I19)/'Balance Sheet'!I24)/(1-('Balance Sheet'!H14+'Balance Sheet'!H19)/'Balance Sheet'!H24),"n/m") | J22: =IFERROR((1-('Balance Sheet'!J14+'Balance Sheet'!J19)/'Balance Sheet'!J24)/(1-('Balance Sheet'!I14+'Balance Sheet'!I19)/'Balance Sheet'!I24),"n/m") | K22: =IFERROR((1-('Balance Sheet'!K14+'Balance Sheet'!K19)/'Balance Sheet'!K24)/(1-('Balance Sheet'!J14+'Balance Sheet'!J19)/'Balance Sheet'!J24),"n/m")
A23: SGI (sales growth index) | B23: n/a | C23: ='Income Statement'!C7/'Income Statement'!B7 | D23: ='Income Statement'!D7/'Income Statement'!C7 | E23: ='Income Statement'!E7/'Income Statement'!D7 | F23: ='Income Statement'!F7/'Income Statement'!E7 | G23: ='Income Statement'!G7/'Income Statement'!F7 | H23: ='Income Statement'!H7/'Income Statement'!G7 | I23: ='Income Statement'!I7/'Income Statement'!H7 | J23: ='Income Statement'!J7/'Income Statement'!I7 | K23: ='Income Statement'!K7/'Income Statement'!J7
A24: DEPI (depreciation rate index) | B24: n/a | C24: =IFERROR(((N('Cash Flow Statement'!B10)+N('Cash Flow Statement'!B11)+N('Cash Flow Statement'!B12))/((N('Cash Flow Statement'!B10)+N('Cash Flow Statement'!B11)+N('Cash Flow Statement'!B12))+'Balance Sheet'!B19))/((N('Cash Flow Statement'!C10)+N('Cash Flow Statement'!C11)+N('Cash Flow Statement'!C12))/((N('Cash Flow Statement'!C10)+N('Cash Flow Statement'!C11)+N('Cash Flow Statement'!C12))+'Balance Sheet'!C19)),"n/m") | D24: =IFERROR(((N('Cash Flow Statement'!C10)+N('Cash Flow Statement'!C11)+N('Cash Flow Statement'!C12))/((N('Cash Flow Statement'!C10)+N('Cash Flow Statement'!C11)+N('Cash Flow Statement'!C12))+'Balance Sheet'!C19))/((N('Cash Flow Statement'!D10)+N('Cash Flow Statement'!D11)+N('Cash Flow Statement'!D12))/((N('Cash Flow Statement'!D10)+N('Cash Flow Statement'!D11)+N('Cash Flow Statement'!D12))+'Balance Sheet'!D19)),"n/m") | E24: =IFERROR(((N('Cash Flow Statement'!D10)+N('Cash Flow Statement'!D11)+N('Cash Flow Statement'!D12))/((N('Cash Flow Statement'!D10)+N('Cash Flow Statement'!D11)+N('Cash Flow Statement'!D12))+'Balance Sheet'!D19))/((N('Cash Flow Statement'!E10)+N('Cash Flow Statement'!E11)+N('Cash Flow Statement'!E12))/((N('Cash Flow Statement'!E10)+N('Cash Flow Statement'!E11)+N('Cash Flow Statement'!E12))+'Balance Sheet'!E19)),"n/m") | F24: =IFERROR(((N('Cash Flow Statement'!E10)+N('Cash Flow Statement'!E11)+N('Cash Flow Statement'!E12))/((N('Cash Flow Statement'!E10)+N('Cash Flow Statement'!E11)+N('Cash Flow Statement'!E12))+'Balance Sheet'!E19))/((N('Cash Flow Statement'!F10)+N('Cash Flow Statement'!F11)+N('Cash Flow Statement'!F12))/((N('Cash Flow Statement'!F10)+N('Cash Flow Statement'!F11)+N('Cash Flow Statement'!F12))+'Balance Sheet'!F19)),"n/m") | G24: =IFERROR(((N('Cash Flow Statement'!F10)+N('Cash Flow Statement'!F11)+N('Cash Flow Statement'!F12))/((N('Cash Flow Statement'!F10)+N('Cash Flow Statement'!F11)+N('Cash Flow Statement'!F12))+'Balance Sheet'!F19))/((N('Cash Flow Statement'!G10)+N('Cash Flow Statement'!G11)+N('Cash Flow Statement'!G12))/((N('Cash Flow Statement'!G10)+N('Cash Flow Statement'!G11)+N('Cash Flow Statement'!G12))+'Balance Sheet'!G19)),"n/m") | H24: =IFERROR(((N('Cash Flow Statement'!G10)+N('Cash Flow Statement'!G11)+N('Cash Flow Statement'!G12))/((N('Cash Flow Statement'!G10)+N('Cash Flow Statement'!G11)+N('Cash Flow Statement'!G12))+'Balance Sheet'!G19))/((N('Cash Flow Statement'!H10)+N('Cash Flow Statement'!H11)+N('Cash Flow Statement'!H12))/((N('Cash Flow Statement'!H10)+N('Cash Flow Statement'!H11)+N('Cash Flow Statement'!H12))+'Balance Sheet'!H19)),"n/m") | I24: =IFERROR(((N('Cash Flow Statement'!H10)+N('Cash Flow Statement'!H11)+N('Cash Flow Statement'!H12))/((N('Cash Flow Statement'!H10)+N('Cash Flow Statement'!H11)+N('Cash Flow Statement'!H12))+'Balance Sheet'!H19))/((N('Cash Flow Statement'!I10)+N('Cash Flow Statement'!I11)+N('Cash Flow Statement'!I12))/((N('Cash Flow Statement'!I10)+N('Cash Flow Statement'!I11)+N('Cash Flow Statement'!I12))+'Balance Sheet'!I19)),"n/m") | J24: =IFERROR(((N('Cash Flow Statement'!I10)+N('Cash Flow Statement'!I11)+N('Cash Flow Statement'!I12))/((N('Cash Flow Statement'!I10)+N('Cash Flow Statement'!I11)+N('Cash Flow Statement'!I12))+'Balance Sheet'!I19))/((N('Cash Flow Statement'!J10)+N('Cash Flow Statement'!J11)+N('Cash Flow Statement'!J12))/((N('Cash Flow Statement'!J10)+N('Cash Flow Statement'!J11)+N('Cash Flow Statement'!J12))+'Balance Sheet'!J19)),"n/m") | K24: =IFERROR(((N('Cash Flow Statement'!J10)+N('Cash Flow Statement'!J11)+N('Cash Flow Statement'!J12))/((N('Cash Flow Statement'!J10)+N('Cash Flow Statement'!J11)+N('Cash Flow Statement'!J12))+'Balance Sheet'!J19))/((N('Cash Flow Statement'!K10)+N('Cash Flow Statement'!K11)+N('Cash Flow Statement'!K12))/((N('Cash Flow Statement'!K10)+N('Cash Flow Statement'!K11)+N('Cash Flow Statement'!K12))+'Balance Sheet'!K19)),"n/m") | L24: DEPI sums the CF D&A lines present each year (2016-2020: dep+impairment of P&E plus amortization+impairment of intangibles; 2021+: depreciation of P&E only - as-filed granularity change); AQI uses 1-(CA+PPE)/TA (securities not separable)
A25: SGAI (SG&A index; S&M+G&A) | B25: n/a | C25: =IFERROR(((ABS('Income Statement'!C11)+ABS('Income Statement'!C12))/'Income Statement'!C7)/((ABS('Income Statement'!B11)+ABS('Income Statement'!B12))/'Income Statement'!B7),"n/m") | D25: =IFERROR(((ABS('Income Statement'!D11)+ABS('Income Statement'!D12))/'Income Statement'!D7)/((ABS('Income Statement'!C11)+ABS('Income Statement'!C12))/'Income Statement'!C7),"n/m") | E25: =IFERROR(((ABS('Income Statement'!E11)+ABS('Income Statement'!E12))/'Income Statement'!E7)/((ABS('Income Statement'!D11)+ABS('Income Statement'!D12))/'Income Statement'!D7),"n/m") | F25: =IFERROR(((ABS('Income Statement'!F11)+ABS('Income Statement'!F12))/'Income Statement'!F7)/((ABS('Income Statement'!E11)+ABS('Income Statement'!E12))/'Income Statement'!E7),"n/m") | G25: =IFERROR(((ABS('Income Statement'!G11)+ABS('Income Statement'!G12))/'Income Statement'!G7)/((ABS('Income Statement'!F11)+ABS('Income Statement'!F12))/'Income Statement'!F7),"n/m") | H25: =IFERROR(((ABS('Income Statement'!H11)+ABS('Income Statement'!H12))/'Income Statement'!H7)/((ABS('Income Statement'!G11)+ABS('Income Statement'!G12))/'Income Statement'!G7),"n/m") | I25: =IFERROR(((ABS('Income Statement'!I11)+ABS('Income Statement'!I12))/'Income Statement'!I7)/((ABS('Income Statement'!H11)+ABS('Income Statement'!H12))/'Income Statement'!H7),"n/m") | J25: =IFERROR(((ABS('Income Statement'!J11)+ABS('Income Statement'!J12))/'Income Statement'!J7)/((ABS('Income Statement'!I11)+ABS('Income Statement'!I12))/'Income Statement'!I7),"n/m") | K25: =IFERROR(((ABS('Income Statement'!K11)+ABS('Income Statement'!K12))/'Income Statement'!K7)/((ABS('Income Statement'!J11)+ABS('Income Statement'!J12))/'Income Statement'!J7),"n/m")
A26: LVGI (leverage index) | B26: n/a | C26: =IFERROR((('Balance Sheet'!C33+'Balance Sheet'!C36)/'Balance Sheet'!C24)/(('Balance Sheet'!B33+'Balance Sheet'!B36)/'Balance Sheet'!B24),"n/m") | D26: =IFERROR((('Balance Sheet'!D33+'Balance Sheet'!D36)/'Balance Sheet'!D24)/(('Balance Sheet'!C33+'Balance Sheet'!C36)/'Balance Sheet'!C24),"n/m") | E26: =IFERROR((('Balance Sheet'!E33+'Balance Sheet'!E36)/'Balance Sheet'!E24)/(('Balance Sheet'!D33+'Balance Sheet'!D36)/'Balance Sheet'!D24),"n/m") | F26: =IFERROR((('Balance Sheet'!F33+'Balance Sheet'!F36)/'Balance Sheet'!F24)/(('Balance Sheet'!E33+'Balance Sheet'!E36)/'Balance Sheet'!E24),"n/m") | G26: =IFERROR((('Balance Sheet'!G33+'Balance Sheet'!G36)/'Balance Sheet'!G24)/(('Balance Sheet'!F33+'Balance Sheet'!F36)/'Balance Sheet'!F24),"n/m") | H26: =IFERROR((('Balance Sheet'!H33+'Balance Sheet'!H36)/'Balance Sheet'!H24)/(('Balance Sheet'!G33+'Balance Sheet'!G36)/'Balance Sheet'!G24),"n/m") | I26: =IFERROR((('Balance Sheet'!I33+'Balance Sheet'!I36)/'Balance Sheet'!I24)/(('Balance Sheet'!H33+'Balance Sheet'!H36)/'Balance Sheet'!H24),"n/m") | J26: =IFERROR((('Balance Sheet'!J33+'Balance Sheet'!J36)/'Balance Sheet'!J24)/(('Balance Sheet'!I33+'Balance Sheet'!I36)/'Balance Sheet'!I24),"n/m") | K26: =IFERROR((('Balance Sheet'!K33+'Balance Sheet'!K36)/'Balance Sheet'!K24)/(('Balance Sheet'!J33+'Balance Sheet'!J36)/'Balance Sheet'!J24),"n/m")
A27: TATA ((NI-CFO)/TA) | B27: n/a | C27: =(C13-C14)/'Balance Sheet'!C24 | D27: =(D13-D14)/'Balance Sheet'!D24 | E27: =(E13-E14)/'Balance Sheet'!E24 | F27: =(F13-F14)/'Balance Sheet'!F24 | G27: =(G13-G14)/'Balance Sheet'!G24 | H27: =(H13-H14)/'Balance Sheet'!H24 | I27: =(I13-I14)/'Balance Sheet'!I24 | J27: =(J13-J14)/'Balance Sheet'!J24 | K27: =(K13-K14)/'Balance Sheet'!K24
A28: M-SCORE | B28: n/a | C28: =IFERROR(-4.84+0.92*C20+0.528*C21+0.404*C22+0.892*C23+0.115*C24-0.172*C25+4.679*C27-0.327*C26,"n/m") | D28: =IFERROR(-4.84+0.92*D20+0.528*D21+0.404*D22+0.892*D23+0.115*D24-0.172*D25+4.679*D27-0.327*D26,"n/m") | E28: =IFERROR(-4.84+0.92*E20+0.528*E21+0.404*E22+0.892*E23+0.115*E24-0.172*E25+4.679*E27-0.327*E26,"n/m") | F28: =IFERROR(-4.84+0.92*F20+0.528*F21+0.404*F22+0.892*F23+0.115*F24-0.172*F25+4.679*F27-0.327*F26,"n/m") | G28: =IFERROR(-4.84+0.92*G20+0.528*G21+0.404*G22+0.892*G23+0.115*G24-0.172*G25+4.679*G27-0.327*G26,"n/m") | H28: =IFERROR(-4.84+0.92*H20+0.528*H21+0.404*H22+0.892*H23+0.115*H24-0.172*H25+4.679*H27-0.327*H26,"n/m") | I28: =IFERROR(-4.84+0.92*I20+0.528*I21+0.404*I22+0.892*I23+0.115*I24-0.172*I25+4.679*I27-0.327*I26,"n/m") | J28: =IFERROR(-4.84+0.92*J20+0.528*J21+0.404*J22+0.892*J23+0.115*J24-0.172*J25+4.679*J27-0.327*J26,"n/m") | K28: =IFERROR(-4.84+0.92*K20+0.528*K21+0.404*K22+0.892*K23+0.115*K24-0.172*K25+4.679*K27-0.327*K26,"n/m")
A29: Verdict (> -1.78 flag; > -2.22 grey) | B29: n/a | C29: =IF(NOT(ISNUMBER(C28)),"n/m",IF(C28>-1.78,"FLAG",IF(C28>-2.22,"grey","ok"))) | D29: =IF(NOT(ISNUMBER(D28)),"n/m",IF(D28>-1.78,"FLAG",IF(D28>-2.22,"grey","ok"))) | E29: =IF(NOT(ISNUMBER(E28)),"n/m",IF(E28>-1.78,"FLAG",IF(E28>-2.22,"grey","ok"))) | F29: =IF(NOT(ISNUMBER(F28)),"n/m",IF(F28>-1.78,"FLAG",IF(F28>-2.22,"grey","ok"))) | G29: =IF(NOT(ISNUMBER(G28)),"n/m",IF(G28>-1.78,"FLAG",IF(G28>-2.22,"grey","ok"))) | H29: =IF(NOT(ISNUMBER(H28)),"n/m",IF(H28>-1.78,"FLAG",IF(H28>-2.22,"grey","ok"))) | I29: =IF(NOT(ISNUMBER(I28)),"n/m",IF(I28>-1.78,"FLAG",IF(I28>-2.22,"grey","ok"))) | J29: =IF(NOT(ISNUMBER(J28)),"n/m",IF(J28>-1.78,"FLAG",IF(J28>-2.22,"grey","ok"))) | K29: =IF(NOT(ISNUMBER(K28)),"n/m",IF(K28>-1.78,"FLAG",IF(K28>-2.22,"grey","ok"))) | L29: Beneish was fit on profitable-firm manipulators; the 2021/2023 server-life extensions move DEPI by construction (estimate changes, see disclosure-only memo in the Core Earnings Bridge)
A31: C. PIOTROSKI F-SCORE (9 signals)
A32: 1. ROA > 0 | B32: n/a | C32: =IF(('Income Statement'!C19/(('Balance Sheet'!C24+'Balance Sheet'!B24)/2))>0,1,0) | D32: =IF(('Income Statement'!D19/(('Balance Sheet'!D24+'Balance Sheet'!C24)/2))>0,1,0) | E32: =IF(('Income Statement'!E19/(('Balance Sheet'!E24+'Balance Sheet'!D24)/2))>0,1,0) | F32: =IF(('Income Statement'!F19/(('Balance Sheet'!F24+'Balance Sheet'!E24)/2))>0,1,0) | G32: =IF(('Income Statement'!G19/(('Balance Sheet'!G24+'Balance Sheet'!F24)/2))>0,1,0) | H32: =IF(('Income Statement'!H19/(('Balance Sheet'!H24+'Balance Sheet'!G24)/2))>0,1,0) | I32: =IF(('Income Statement'!I19/(('Balance Sheet'!I24+'Balance Sheet'!H24)/2))>0,1,0) | J32: =IF(('Income Statement'!J19/(('Balance Sheet'!J24+'Balance Sheet'!I24)/2))>0,1,0) | K32: =IF(('Income Statement'!K19/(('Balance Sheet'!K24+'Balance Sheet'!J24)/2))>0,1,0)
A33: 2. CFO > 0 | B33: n/a | C33: =IF('Cash Flow Statement'!C26>0,1,0) | D33: =IF('Cash Flow Statement'!D26>0,1,0) | E33: =IF('Cash Flow Statement'!E26>0,1,0) | F33: =IF('Cash Flow Statement'!F26>0,1,0) | G33: =IF('Cash Flow Statement'!G26>0,1,0) | H33: =IF('Cash Flow Statement'!H26>0,1,0) | I33: =IF('Cash Flow Statement'!I26>0,1,0) | J33: =IF('Cash Flow Statement'!J26>0,1,0) | K33: =IF('Cash Flow Statement'!K26>0,1,0)
A34: 3. dROA > 0 | B34: n/a | C34: n/a | D34: =IF(('Income Statement'!D19/(('Balance Sheet'!D24+'Balance Sheet'!C24)/2))>('Income Statement'!C19/(('Balance Sheet'!C24+'Balance Sheet'!B24)/2)),1,0) | E34: =IF(('Income Statement'!E19/(('Balance Sheet'!E24+'Balance Sheet'!D24)/2))>('Income Statement'!D19/(('Balance Sheet'!D24+'Balance Sheet'!C24)/2)),1,0) | F34: =IF(('Income Statement'!F19/(('Balance Sheet'!F24+'Balance Sheet'!E24)/2))>('Income Statement'!E19/(('Balance Sheet'!E24+'Balance Sheet'!D24)/2)),1,0) | G34: =IF(('Income Statement'!G19/(('Balance Sheet'!G24+'Balance Sheet'!F24)/2))>('Income Statement'!F19/(('Balance Sheet'!F24+'Balance Sheet'!E24)/2)),1,0) | H34: =IF(('Income Statement'!H19/(('Balance Sheet'!H24+'Balance Sheet'!G24)/2))>('Income Statement'!G19/(('Balance Sheet'!G24+'Balance Sheet'!F24)/2)),1,0) | I34: =IF(('Income Statement'!I19/(('Balance Sheet'!I24+'Balance Sheet'!H24)/2))>('Income Statement'!H19/(('Balance Sheet'!H24+'Balance Sheet'!G24)/2)),1,0) | J34: =IF(('Income Statement'!J19/(('Balance Sheet'!J24+'Balance Sheet'!I24)/2))>('Income Statement'!I19/(('Balance Sheet'!I24+'Balance Sheet'!H24)/2)),1,0) | K34: =IF(('Income Statement'!K19/(('Balance Sheet'!K24+'Balance Sheet'!J24)/2))>('Income Statement'!J19/(('Balance Sheet'!J24+'Balance Sheet'!I24)/2)),1,0)
A35: 4. CFO > NI (accruals) | B35: n/a | C35: =IF('Cash Flow Statement'!C26>'Income Statement'!C19,1,0) | D35: =IF('Cash Flow Statement'!D26>'Income Statement'!D19,1,0) | E35: =IF('Cash Flow Statement'!E26>'Income Statement'!E19,1,0) | F35: =IF('Cash Flow Statement'!F26>'Income Statement'!F19,1,0) | G35: =IF('Cash Flow Statement'!G26>'Income Statement'!G19,1,0) | H35: =IF('Cash Flow Statement'!H26>'Income Statement'!H19,1,0) | I35: =IF('Cash Flow Statement'!I26>'Income Statement'!I19,1,0) | J35: =IF('Cash Flow Statement'!J26>'Income Statement'!J19,1,0) | K35: =IF('Cash Flow Statement'!K26>'Income Statement'!K19,1,0)
A36: 5. dLeverage < 0 (LTD/TA) | B36: n/a | C36: =IF(('Balance Sheet'!C36/'Balance Sheet'!C24)<('Balance Sheet'!B36/'Balance Sheet'!B24),1,0) | D36: =IF(('Balance Sheet'!D36/'Balance Sheet'!D24)<('Balance Sheet'!C36/'Balance Sheet'!C24),1,0) | E36: =IF(('Balance Sheet'!E36/'Balance Sheet'!E24)<('Balance Sheet'!D36/'Balance Sheet'!D24),1,0) | F36: =IF(('Balance Sheet'!F36/'Balance Sheet'!F24)<('Balance Sheet'!E36/'Balance Sheet'!E24),1,0) | G36: =IF(('Balance Sheet'!G36/'Balance Sheet'!G24)<('Balance Sheet'!F36/'Balance Sheet'!F24),1,0) | H36: =IF(('Balance Sheet'!H36/'Balance Sheet'!H24)<('Balance Sheet'!G36/'Balance Sheet'!G24),1,0) | I36: =IF(('Balance Sheet'!I36/'Balance Sheet'!I24)<('Balance Sheet'!H36/'Balance Sheet'!H24),1,0) | J36: =IF(('Balance Sheet'!J36/'Balance Sheet'!J24)<('Balance Sheet'!I36/'Balance Sheet'!I24),1,0) | K36: =IF(('Balance Sheet'!K36/'Balance Sheet'!K24)<('Balance Sheet'!J36/'Balance Sheet'!J24),1,0)
A37: 6. dCurrent ratio > 0 | B37: n/a | C37: =IF(('Balance Sheet'!C14/'Balance Sheet'!C33)>('Balance Sheet'!B14/'Balance Sheet'!B33),1,0) | D37: =IF(('Balance Sheet'!D14/'Balance Sheet'!D33)>('Balance Sheet'!C14/'Balance Sheet'!C33),1,0) | E37: =IF(('Balance Sheet'!E14/'Balance Sheet'!E33)>('Balance Sheet'!D14/'Balance Sheet'!D33),1,0) | F37: =IF(('Balance Sheet'!F14/'Balance Sheet'!F33)>('Balance Sheet'!E14/'Balance Sheet'!E33),1,0) | G37: =IF(('Balance Sheet'!G14/'Balance Sheet'!G33)>('Balance Sheet'!F14/'Balance Sheet'!F33),1,0) | H37: =IF(('Balance Sheet'!H14/'Balance Sheet'!H33)>('Balance Sheet'!G14/'Balance Sheet'!G33),1,0) | I37: =IF(('Balance Sheet'!I14/'Balance Sheet'!I33)>('Balance Sheet'!H14/'Balance Sheet'!H33),1,0) | J37: =IF(('Balance Sheet'!J14/'Balance Sheet'!J33)>('Balance Sheet'!I14/'Balance Sheet'!I33),1,0) | K37: =IF(('Balance Sheet'!K14/'Balance Sheet'!K33)>('Balance Sheet'!J14/'Balance Sheet'!J33),1,0)
A38: 7. No dilution (diluted shares <= prior; n/a pre-FY2022) | B38: n/a | C38: =IF(AND(ISNUMBER('Income Statement'!C24),ISNUMBER('Income Statement'!B24)),IF('Income Statement'!C24<='Income Statement'!B24,1,0),"n/a") | D38: =IF(AND(ISNUMBER('Income Statement'!D24),ISNUMBER('Income Statement'!C24)),IF('Income Statement'!D24<='Income Statement'!C24,1,0),"n/a") | E38: =IF(AND(ISNUMBER('Income Statement'!E24),ISNUMBER('Income Statement'!D24)),IF('Income Statement'!E24<='Income Statement'!D24,1,0),"n/a") | F38: =IF(AND(ISNUMBER('Income Statement'!F24),ISNUMBER('Income Statement'!E24)),IF('Income Statement'!F24<='Income Statement'!E24,1,0),"n/a") | G38: =IF(AND(ISNUMBER('Income Statement'!G24),ISNUMBER('Income Statement'!F24)),IF('Income Statement'!G24<='Income Statement'!F24,1,0),"n/a") | H38: =IF(AND(ISNUMBER('Income Statement'!H24),ISNUMBER('Income Statement'!G24)),IF('Income Statement'!H24<='Income Statement'!G24,1,0),"n/a") | I38: =IF(AND(ISNUMBER('Income Statement'!I24),ISNUMBER('Income Statement'!H24)),IF('Income Statement'!I24<='Income Statement'!H24,1,0),"n/a") | J38: =IF(AND(ISNUMBER('Income Statement'!J24),ISNUMBER('Income Statement'!I24)),IF('Income Statement'!J24<='Income Statement'!I24,1,0),"n/a") | K38: =IF(AND(ISNUMBER('Income Statement'!K24),ISNUMBER('Income Statement'!J24)),IF('Income Statement'!K24<='Income Statement'!J24,1,0),"n/a") | L38: Diluted weighted shares are as-filed only from FY2022 (split-adjusted); earlier columns n/a - SUM skips text
A39: 8. dGross margin % > 0 | B39: n/a | C39: =IF(('Income Statement'!C9/'Income Statement'!C7)>('Income Statement'!B9/'Income Statement'!B7),1,0) | D39: =IF(('Income Statement'!D9/'Income Statement'!D7)>('Income Statement'!C9/'Income Statement'!C7),1,0) | E39: =IF(('Income Statement'!E9/'Income Statement'!E7)>('Income Statement'!D9/'Income Statement'!D7),1,0) | F39: =IF(('Income Statement'!F9/'Income Statement'!F7)>('Income Statement'!E9/'Income Statement'!E7),1,0) | G39: =IF(('Income Statement'!G9/'Income Statement'!G7)>('Income Statement'!F9/'Income Statement'!F7),1,0) | H39: =IF(('Income Statement'!H9/'Income Statement'!H7)>('Income Statement'!G9/'Income Statement'!G7),1,0) | I39: =IF(('Income Statement'!I9/'Income Statement'!I7)>('Income Statement'!H9/'Income Statement'!H7),1,0) | J39: =IF(('Income Statement'!J9/'Income Statement'!J7)>('Income Statement'!I9/'Income Statement'!I7),1,0) | K39: =IF(('Income Statement'!K9/'Income Statement'!K7)>('Income Statement'!J9/'Income Statement'!J7),1,0)
A40: 9. dAsset turnover > 0 | B40: n/a | C40: n/a | D40: =IF(('Income Statement'!D7/(('Balance Sheet'!D24+'Balance Sheet'!C24)/2))>('Income Statement'!C7/(('Balance Sheet'!C24+'Balance Sheet'!B24)/2)),1,0) | E40: =IF(('Income Statement'!E7/(('Balance Sheet'!E24+'Balance Sheet'!D24)/2))>('Income Statement'!D7/(('Balance Sheet'!D24+'Balance Sheet'!C24)/2)),1,0) | F40: =IF(('Income Statement'!F7/(('Balance Sheet'!F24+'Balance Sheet'!E24)/2))>('Income Statement'!E7/(('Balance Sheet'!E24+'Balance Sheet'!D24)/2)),1,0) | G40: =IF(('Income Statement'!G7/(('Balance Sheet'!G24+'Balance Sheet'!F24)/2))>('Income Statement'!F7/(('Balance Sheet'!F24+'Balance Sheet'!E24)/2)),1,0) | H40: =IF(('Income Statement'!H7/(('Balance Sheet'!H24+'Balance Sheet'!G24)/2))>('Income Statement'!G7/(('Balance Sheet'!G24+'Balance Sheet'!F24)/2)),1,0) | I40: =IF(('Income Statement'!I7/(('Balance Sheet'!I24+'Balance Sheet'!H24)/2))>('Income Statement'!H7/(('Balance Sheet'!H24+'Balance Sheet'!G24)/2)),1,0) | J40: =IF(('Income Statement'!J7/(('Balance Sheet'!J24+'Balance Sheet'!I24)/2))>('Income Statement'!I7/(('Balance Sheet'!I24+'Balance Sheet'!H24)/2)),1,0) | K40: =IF(('Income Statement'!K7/(('Balance Sheet'!K24+'Balance Sheet'!J24)/2))>('Income Statement'!J7/(('Balance Sheet'!J24+'Balance Sheet'!I24)/2)),1,0)
A41: F-SCORE (of signals available) | B41: n/a | C41: =SUM(C32:C40) | D41: =SUM(D32:D40) | E41: =SUM(E32:E40) | F41: =SUM(F32:F40) | G41: =SUM(G32:G40) | H41: =SUM(H32:H40) | I41: =SUM(I32:I40) | J41: =SUM(J32:J40) | K41: =SUM(K32:K40)
A42: Verdict (<=3 weak; >=8 strong) | B42: n/a | C42: =IF(C41<=3,"WEAK",IF(C41>=8,"strong","mid")) | D42: =IF(D41<=3,"WEAK",IF(D41>=8,"strong","mid")) | E42: =IF(E41<=3,"WEAK",IF(E41>=8,"strong","mid")) | F42: =IF(F41<=3,"WEAK",IF(F41>=8,"strong","mid")) | G42: =IF(G41<=3,"WEAK",IF(G41>=8,"strong","mid")) | H42: =IF(H41<=3,"WEAK",IF(H41>=8,"strong","mid")) | I42: =IF(I41<=3,"WEAK",IF(I41>=8,"strong","mid")) | J42: =IF(J41<=3,"WEAK",IF(J41>=8,"strong","mid")) | K42: =IF(K41<=3,"WEAK",IF(K41>=8,"strong","mid"))
A44: D. BENFORD'S LAW (full XBRL fact set per filing)
A45: Population: every USD-denominated us-gaap fact in the filing's XBRL instance (statements + notes), |value|>=1, deduped by (concept, period, value). MAD verdicts per Nigrini: <=0.006 close, <=0.012 acceptable, <=0.015 marginal, else nonconforming. chi-sq df=8, 5% crit 15.51. Benford applies to FILINGS, not years: the ten-year window is sourced from five 10-Ks (FY2017/19/21/23/25 - extraction_log.md); years sourced from a covering filing's comparatives share its statistics (left blank).
A46: (source-filing columns only) | B46: ='Income Statement'!B6 | C46: ='Income Statement'!C6 | D46: ='Income Statement'!D6 | E46: ='Income Statement'!E6 | F46: ='Income Statement'!F6 | G46: ='Income Statement'!G6 | H46: ='Income Statement'!H6 | I46: ='Income Statement'!I6 | ... K46: ='Income Statement'!K6
A47: Filing (10-K accession) | C47: 0001652044-18-000007 | E47: 0001652044-20-000008 | G47: 0001652044-22-000019 | I47: 0001652044-24-000022 | K47: 0001652044-26-000018
A48: N facts | C48: 471 | E48: 510 | G48: 506 | I48: 488 | K48: 575
A49: MAD (first digit) | C49: 0.00995 | E49: 0.014 | G49: 0.02212 | I49: 0.01378 | K49: 0.0073
A50: MAD verdict | C50: acceptable | E50: marginal | G50: NONCONFORM | I50: marginal | K50: acceptable
A51: chi-square (df=8) | C51: 4.9 | E51: 12.1 | G51: 26.3 | I51: 12.9 | K51: 3.7
A52: chi-sq > 15.51? | C52: no | E52: no | G52: yes | I52: no | K52: no
A55: QUARTERLY (Beneish/Piotroski on a same-quarter-prior-year basis, t vs t-4)
B56: Q1 2024 | C56: Q2 2024 | D56: Q3 2024 | E56: Q4 2024 | F56: Q1 2025 | G56: Q2 2025 | H56: Q3 2025 | I56: Q4 2025 | J56: Q1 2026
A57: Line Item | B57: ='Income Statement'!B32 | C57: ='Income Statement'!C32 | D57: ='Income Statement'!D32 | E57: ='Income Statement'!E32 | F57: ='Income Statement'!F32 | G57: ='Income Statement'!G32 | H57: ='Income Statement'!H32 | I57: ='Income Statement'!I32 | J57: ='Income Statement'!J32
A59: A. ACCRUALS & CASH CONVERSION (quarter)
A60: NOA (Condensed quarterly) | B60: ='Condensed Financials'!B103 | C60: ='Condensed Financials'!C103 | D60: ='Condensed Financials'!D103 | E60: ='Condensed Financials'!E103 | F60: ='Condensed Financials'!F103 | G60: ='Condensed Financials'!G103 | H60: ='Condensed Financials'!H103 | I60: ='Condensed Financials'!I103 | J60: ='Condensed Financials'!J103
A61: BS accruals = dNOA (QoQ) | B61: n/a | C61: =C60-B60 | D61: =D60-C60 | E61: =E60-D60 | F61: =F60-E60 | G61: =G60-F60 | H61: =H60-G60 | I61: =I60-H60 | J61: =J60-I60
A62: Avg NOA | B62: n/a | C62: =(C60+B60)/2 | D62: =(D60+C60)/2 | E62: =(E60+D60)/2 | F62: =(F60+E60)/2 | G62: =(G60+F60)/2 | H62: =(H60+G60)/2 | I62: =(I60+H60)/2 | J62: =(J60+I60)/2
A63: Scaled BS accruals | B63: n/a | C63: =C61/C62 | D63: =D61/D62 | E63: =E61/E62 | F63: =F61/F62 | G63: =G61/G62 | H63: =H61/H62 | I63: =I61/I62 | J63: =J61/J62
A64: Net income (quarter) | B64: ='Income Statement'!B46 | C64: ='Income Statement'!C46 | D64: ='Income Statement'!D46 | E64: ='Income Statement'!E46 | F64: ='Income Statement'!F46 | G64: ='Income Statement'!G46 | H64: ='Income Statement'!H46 | I64: ='Income Statement'!I46 | J64: ='Income Statement'!J46
A65: CFO (quarter) | B65: ='Cash Flow Statement'!B86 | C65: ='Cash Flow Statement'!C86 | D65: ='Cash Flow Statement'!D86 | E65: ='Cash Flow Statement'!E86 | F65: ='Cash Flow Statement'!F86 | G65: ='Cash Flow Statement'!G86 | H65: ='Cash Flow Statement'!H86 | I65: ='Cash Flow Statement'!I86 | J65: ='Cash Flow Statement'!J86
A66: Income accruals = NI - CFO | B66: =B64-B65 | C66: =C64-C65 | D66: =D64-D65 | E66: =E64-E65 | F66: =F64-F65 | G66: =G64-G65 | H66: =H64-H65 | I66: =I64-I65 | J66: =J64-J65
A67: Scaled income accruals | B67: n/a | C67: =C66/C62 | D67: =D66/D62 | E67: =E66/E62 | F67: =F66/F62 | G67: =G66/G62 | H67: =H66/H62 | I67: =I66/I62 | J67: =J66/J62 | L67: Q1 2026: the +$36.9B unrealized securities mark sits in NI but not CFO - income accruals spike mechanically
A68: Cash conversion (CFO/NI) | B68: =IFERROR(B65/B64,"n/m") | C68: =IFERROR(C65/C64,"n/m") | D68: =IFERROR(D65/D64,"n/m") | E68: =IFERROR(E65/E64,"n/m") | F68: =IFERROR(F65/F64,"n/m") | G68: =IFERROR(G65/G64,"n/m") | H68: =IFERROR(H65/H64,"n/m") | I68: =IFERROR(I65/I64,"n/m") | J68: =IFERROR(J65/J64,"n/m")
A70: B. BENEISH M-SCORE (t vs t-4)
A71: DSRI | B71: n/a | C71: n/a | D71: n/a | E71: n/a | F71: =IFERROR(('Balance Sheet'!F61/'Income Statement'!F34)/('Balance Sheet'!B61/'Income Statement'!B34),"n/m") | G71: =IFERROR(('Balance Sheet'!G61/'Income Statement'!G34)/('Balance Sheet'!C61/'Income Statement'!C34),"n/m") | H71: =IFERROR(('Balance Sheet'!H61/'Income Statement'!H34)/('Balance Sheet'!D61/'Income Statement'!D34),"n/m") | I71: =IFERROR(('Balance Sheet'!I61/'Income Statement'!I34)/('Balance Sheet'!E61/'Income Statement'!E34),"n/m") | J71: =IFERROR(('Balance Sheet'!J61/'Income Statement'!J34)/('Balance Sheet'!F61/'Income Statement'!F34),"n/m")
A72: GMI | B72: n/a | C72: n/a | D72: n/a | E72: n/a | F72: =IFERROR(('Income Statement'!B36/'Income Statement'!B34)/('Income Statement'!F36/'Income Statement'!F34),"n/m") | G72: =IFERROR(('Income Statement'!C36/'Income Statement'!C34)/('Income Statement'!G36/'Income Statement'!G34),"n/m") | H72: =IFERROR(('Income Statement'!D36/'Income Statement'!D34)/('Income Statement'!H36/'Income Statement'!H34),"n/m") | I72: =IFERROR(('Income Statement'!E36/'Income Statement'!E34)/('Income Statement'!I36/'Income Statement'!I34),"n/m") | J72: =IFERROR(('Income Statement'!F36/'Income Statement'!F34)/('Income Statement'!J36/'Income Statement'!J34),"n/m")
A73: AQI | B73: n/a | C73: n/a | D73: n/a | E73: n/a | F73: =IFERROR((1-('Balance Sheet'!F65+'Balance Sheet'!F70)/'Balance Sheet'!F75)/(1-('Balance Sheet'!B65+'Balance Sheet'!B70)/'Balance Sheet'!B75),"n/m") | G73: =IFERROR((1-('Balance Sheet'!G65+'Balance Sheet'!G70)/'Balance Sheet'!G75)/(1-('Balance Sheet'!C65+'Balance Sheet'!C70)/'Balance Sheet'!C75),"n/m") | H73: =IFERROR((1-('Balance Sheet'!H65+'Balance Sheet'!H70)/'Balance Sheet'!H75)/(1-('Balance Sheet'!D65+'Balance Sheet'!D70)/'Balance Sheet'!D75),"n/m") | I73: =IFERROR((1-('Balance Sheet'!I65+'Balance Sheet'!I70)/'Balance Sheet'!I75)/(1-('Balance Sheet'!E65+'Balance Sheet'!E70)/'Balance Sheet'!E75),"n/m") | J73: =IFERROR((1-('Balance Sheet'!J65+'Balance Sheet'!J70)/'Balance Sheet'!J75)/(1-('Balance Sheet'!F65+'Balance Sheet'!F70)/'Balance Sheet'!F75),"n/m")
A74: SGI | B74: n/a | C74: n/a | D74: n/a | E74: n/a | F74: ='Income Statement'!F34/'Income Statement'!B34 | G74: ='Income Statement'!G34/'Income Statement'!C34 | H74: ='Income Statement'!H34/'Income Statement'!D34 | I74: ='Income Statement'!I34/'Income Statement'!E34 | J74: ='Income Statement'!J34/'Income Statement'!F34
A75: DEPI | B75: n/a | C75: n/a | D75: n/a | E75: n/a | F75: =IFERROR(((N('Cash Flow Statement'!B70)+N('Cash Flow Statement'!B71)+N('Cash Flow Statement'!B72))/((N('Cash Flow Statement'!B70)+N('Cash Flow Statement'!B71)+N('Cash Flow Statement'!B72))+'Balance Sheet'!B70))/((N('Cash Flow Statement'!F70)+N('Cash Flow Statement'!F71)+N('Cash Flow Statement'!F72))/((N('Cash Flow Statement'!F70)+N('Cash Flow Statement'!F71)+N('Cash Flow Statement'!F72))+'Balance Sheet'!F70)),"n/m") | G75: =IFERROR(((N('Cash Flow Statement'!C70)+N('Cash Flow Statement'!C71)+N('Cash Flow Statement'!C72))/((N('Cash Flow Statement'!C70)+N('Cash Flow Statement'!C71)+N('Cash Flow Statement'!C72))+'Balance Sheet'!C70))/((N('Cash Flow Statement'!G70)+N('Cash Flow Statement'!G71)+N('Cash Flow Statement'!G72))/((N('Cash Flow Statement'!G70)+N('Cash Flow Statement'!G71)+N('Cash Flow Statement'!G72))+'Balance Sheet'!G70)),"n/m") | H75: =IFERROR(((N('Cash Flow Statement'!D70)+N('Cash Flow Statement'!D71)+N('Cash Flow Statement'!D72))/((N('Cash Flow Statement'!D70)+N('Cash Flow Statement'!D71)+N('Cash Flow Statement'!D72))+'Balance Sheet'!D70))/((N('Cash Flow Statement'!H70)+N('Cash Flow Statement'!H71)+N('Cash Flow Statement'!H72))/((N('Cash Flow Statement'!H70)+N('Cash Flow Statement'!H71)+N('Cash Flow Statement'!H72))+'Balance Sheet'!H70)),"n/m") | I75: =IFERROR(((N('Cash Flow Statement'!E70)+N('Cash Flow Statement'!E71)+N('Cash Flow Statement'!E72))/((N('Cash Flow Statement'!E70)+N('Cash Flow Statement'!E71)+N('Cash Flow Statement'!E72))+'Balance Sheet'!E70))/((N('Cash Flow Statement'!I70)+N('Cash Flow Statement'!I71)+N('Cash Flow Statement'!I72))/((N('Cash Flow Statement'!I70)+N('Cash Flow Statement'!I71)+N('Cash Flow Statement'!I72))+'Balance Sheet'!I70)),"n/m") | J75: =IFERROR(((N('Cash Flow Statement'!F70)+N('Cash Flow Statement'!F71)+N('Cash Flow Statement'!F72))/((N('Cash Flow Statement'!F70)+N('Cash Flow Statement'!F71)+N('Cash Flow Statement'!F72))+'Balance Sheet'!F70))/((N('Cash Flow Statement'!J70)+N('Cash Flow Statement'!J71)+N('Cash Flow Statement'!J72))/((N('Cash Flow Statement'!J70)+N('Cash Flow Statement'!J71)+N('Cash Flow Statement'!J72))+'Balance Sheet'!J70)),"n/m")
A76: SGAI | B76: n/a | C76: n/a | D76: n/a | E76: n/a | F76: =IFERROR(((ABS('Income Statement'!F38)+ABS('Income Statement'!F39))/'Income Statement'!F34)/((ABS('Income Statement'!B38)+ABS('Income Statement'!B39))/'Income Statement'!B34),"n/m") | G76: =IFERROR(((ABS('Income Statement'!G38)+ABS('Income Statement'!G39))/'Income Statement'!G34)/((ABS('Income Statement'!C38)+ABS('Income Statement'!C39))/'Income Statement'!C34),"n/m") | H76: =IFERROR(((ABS('Income Statement'!H38)+ABS('Income Statement'!H39))/'Income Statement'!H34)/((ABS('Income Statement'!D38)+ABS('Income Statement'!D39))/'Income Statement'!D34),"n/m") | I76: =IFERROR(((ABS('Income Statement'!I38)+ABS('Income Statement'!I39))/'Income Statement'!I34)/((ABS('Income Statement'!E38)+ABS('Income Statement'!E39))/'Income Statement'!E34),"n/m") | J76: =IFERROR(((ABS('Income Statement'!J38)+ABS('Income Statement'!J39))/'Income Statement'!J34)/((ABS('Income Statement'!F38)+ABS('Income Statement'!F39))/'Income Statement'!F34),"n/m")
A77: LVGI | B77: n/a | C77: n/a | D77: n/a | E77: n/a | F77: =IFERROR((('Balance Sheet'!F84+'Balance Sheet'!F87)/'Balance Sheet'!F75)/(('Balance Sheet'!B84+'Balance Sheet'!B87)/'Balance Sheet'!B75),"n/m") | G77: =IFERROR((('Balance Sheet'!G84+'Balance Sheet'!G87)/'Balance Sheet'!G75)/(('Balance Sheet'!C84+'Balance Sheet'!C87)/'Balance Sheet'!C75),"n/m") | H77: =IFERROR((('Balance Sheet'!H84+'Balance Sheet'!H87)/'Balance Sheet'!H75)/(('Balance Sheet'!D84+'Balance Sheet'!D87)/'Balance Sheet'!D75),"n/m") | I77: =IFERROR((('Balance Sheet'!I84+'Balance Sheet'!I87)/'Balance Sheet'!I75)/(('Balance Sheet'!E84+'Balance Sheet'!E87)/'Balance Sheet'!E75),"n/m") | J77: =IFERROR((('Balance Sheet'!J84+'Balance Sheet'!J87)/'Balance Sheet'!J75)/(('Balance Sheet'!F84+'Balance Sheet'!F87)/'Balance Sheet'!F75),"n/m")
A78: TATA (quarter) | B78: =(B64-B65)/'Balance Sheet'!B75 | C78: =(C64-C65)/'Balance Sheet'!C75 | D78: =(D64-D65)/'Balance Sheet'!D75 | E78: =(E64-E65)/'Balance Sheet'!E75 | F78: =(F64-F65)/'Balance Sheet'!F75 | G78: =(G64-G65)/'Balance Sheet'!G75 | H78: =(H64-H65)/'Balance Sheet'!H75 | I78: =(I64-I65)/'Balance Sheet'!I75 | J78: =(J64-J65)/'Balance Sheet'!J75
A79: M-SCORE (YoY-quarterly) | B79: n/a | C79: n/a | D79: n/a | E79: n/a | F79: =IFERROR(-4.84+0.92*F71+0.528*F72+0.404*F73+0.892*F74+0.115*F75-0.172*F76+4.679*F78-0.327*F77,"n/m") | G79: =IFERROR(-4.84+0.92*G71+0.528*G72+0.404*G73+0.892*G74+0.115*G75-0.172*G76+4.679*G78-0.327*G77,"n/m") | H79: =IFERROR(-4.84+0.92*H71+0.528*H72+0.404*H73+0.892*H74+0.115*H75-0.172*H76+4.679*H78-0.327*H77,"n/m") | I79: =IFERROR(-4.84+0.92*I71+0.528*I72+0.404*I73+0.892*I74+0.115*I75-0.172*I76+4.679*I78-0.327*I77,"n/m") | J79: =IFERROR(-4.84+0.92*J71+0.528*J72+0.404*J73+0.892*J74+0.115*J75-0.172*J76+4.679*J78-0.327*J77,"n/m")
A80: Verdict | B80: n/a | C80: n/a | D80: n/a | E80: n/a | F80: =IF(NOT(ISNUMBER(F79)),"n/m",IF(F79>-1.78,"FLAG",IF(F79>-2.22,"grey","ok"))) | G80: =IF(NOT(ISNUMBER(G79)),"n/m",IF(G79>-1.78,"FLAG",IF(G79>-2.22,"grey","ok"))) | H80: =IF(NOT(ISNUMBER(H79)),"n/m",IF(H79>-1.78,"FLAG",IF(H79>-2.22,"grey","ok"))) | I80: =IF(NOT(ISNUMBER(I79)),"n/m",IF(I79>-1.78,"FLAG",IF(I79>-2.22,"grey","ok"))) | J80: =IF(NOT(ISNUMBER(J79)),"n/m",IF(J79>-1.78,"FLAG",IF(J79>-2.22,"grey","ok"))) | L80: Quarterly Beneish is non-standard (model fit on annual data); YoY quarters control seasonality but the Q1 2026 TATA spike is the unrealized securities mark, not working-capital accrual
A82: C. PIOTROSKI F-SCORE (t vs t-4)
A83: 1. ROA > 0 | B83: n/a | C83: =IF(('Income Statement'!C46/(('Balance Sheet'!C75+'Balance Sheet'!B75)/2))>0,1,0) | D83: =IF(('Income Statement'!D46/(('Balance Sheet'!D75+'Balance Sheet'!C75)/2))>0,1,0) | E83: =IF(('Income Statement'!E46/(('Balance Sheet'!E75+'Balance Sheet'!D75)/2))>0,1,0) | F83: =IF(('Income Statement'!F46/(('Balance Sheet'!F75+'Balance Sheet'!E75)/2))>0,1,0) | G83: =IF(('Income Statement'!G46/(('Balance Sheet'!G75+'Balance Sheet'!F75)/2))>0,1,0) | H83: =IF(('Income Statement'!H46/(('Balance Sheet'!H75+'Balance Sheet'!G75)/2))>0,1,0) | I83: =IF(('Income Statement'!I46/(('Balance Sheet'!I75+'Balance Sheet'!H75)/2))>0,1,0) | J83: =IF(('Income Statement'!J46/(('Balance Sheet'!J75+'Balance Sheet'!I75)/2))>0,1,0)
A84: 2. CFO > 0 | B84: =IF('Cash Flow Statement'!B86>0,1,0) | C84: =IF('Cash Flow Statement'!C86>0,1,0) | D84: =IF('Cash Flow Statement'!D86>0,1,0) | E84: =IF('Cash Flow Statement'!E86>0,1,0) | F84: =IF('Cash Flow Statement'!F86>0,1,0) | G84: =IF('Cash Flow Statement'!G86>0,1,0) | H84: =IF('Cash Flow Statement'!H86>0,1,0) | I84: =IF('Cash Flow Statement'!I86>0,1,0) | J84: =IF('Cash Flow Statement'!J86>0,1,0)
A85: 3. dROA > 0 (YoY) | B85: n/a | C85: n/a | D85: n/a | E85: n/a | F85: n/a | G85: =IF(('Income Statement'!G46/(('Balance Sheet'!G75+'Balance Sheet'!F75)/2))>('Income Statement'!C46/(('Balance Sheet'!C75+'Balance Sheet'!B75)/2)),1,0) | H85: =IF(('Income Statement'!H46/(('Balance Sheet'!H75+'Balance Sheet'!G75)/2))>('Income Statement'!D46/(('Balance Sheet'!D75+'Balance Sheet'!C75)/2)),1,0) | I85: =IF(('Income Statement'!I46/(('Balance Sheet'!I75+'Balance Sheet'!H75)/2))>('Income Statement'!E46/(('Balance Sheet'!E75+'Balance Sheet'!D75)/2)),1,0) | J85: =IF(('Income Statement'!J46/(('Balance Sheet'!J75+'Balance Sheet'!I75)/2))>('Income Statement'!F46/(('Balance Sheet'!F75+'Balance Sheet'!E75)/2)),1,0)
A86: 4. CFO > NI | B86: =IF('Cash Flow Statement'!B86>'Income Statement'!B46,1,0) | C86: =IF('Cash Flow Statement'!C86>'Income Statement'!C46,1,0) | D86: =IF('Cash Flow Statement'!D86>'Income Statement'!D46,1,0) | E86: =IF('Cash Flow Statement'!E86>'Income Statement'!E46,1,0) | F86: =IF('Cash Flow Statement'!F86>'Income Statement'!F46,1,0) | G86: =IF('Cash Flow Statement'!G86>'Income Statement'!G46,1,0) | H86: =IF('Cash Flow Statement'!H86>'Income Statement'!H46,1,0) | I86: =IF('Cash Flow Statement'!I86>'Income Statement'!I46,1,0) | J86: =IF('Cash Flow Statement'!J86>'Income Statement'!J46,1,0)
A87: 5. dLeverage < 0 (YoY) | B87: n/a | C87: n/a | D87: n/a | E87: n/a | F87: =IF(('Balance Sheet'!F87/'Balance Sheet'!F75)<('Balance Sheet'!B87/'Balance Sheet'!B75),1,0) | G87: =IF(('Balance Sheet'!G87/'Balance Sheet'!G75)<('Balance Sheet'!C87/'Balance Sheet'!C75),1,0) | H87: =IF(('Balance Sheet'!H87/'Balance Sheet'!H75)<('Balance Sheet'!D87/'Balance Sheet'!D75),1,0) | I87: =IF(('Balance Sheet'!I87/'Balance Sheet'!I75)<('Balance Sheet'!E87/'Balance Sheet'!E75),1,0) | J87: =IF(('Balance Sheet'!J87/'Balance Sheet'!J75)<('Balance Sheet'!F87/'Balance Sheet'!F75),1,0)
A88: 6. dCurrent ratio > 0 (YoY) | B88: n/a | C88: n/a | D88: n/a | E88: n/a | F88: =IF(('Balance Sheet'!F65/'Balance Sheet'!F84)>('Balance Sheet'!B65/'Balance Sheet'!B84),1,0) | G88: =IF(('Balance Sheet'!G65/'Balance Sheet'!G84)>('Balance Sheet'!C65/'Balance Sheet'!C84),1,0) | H88: =IF(('Balance Sheet'!H65/'Balance Sheet'!H84)>('Balance Sheet'!D65/'Balance Sheet'!D84),1,0) | I88: =IF(('Balance Sheet'!I65/'Balance Sheet'!I84)>('Balance Sheet'!E65/'Balance Sheet'!E84),1,0) | J88: =IF(('Balance Sheet'!J65/'Balance Sheet'!J84)>('Balance Sheet'!F65/'Balance Sheet'!F84),1,0)
A89: 7. No dilution (YoY; n/a derived Q4s) | B89: n/a | C89: n/a | D89: n/a | E89: n/a | F89: =IF(AND(ISNUMBER('Income Statement'!F51),ISNUMBER('Income Statement'!B51)),IF('Income Statement'!F51<='Income Statement'!B51,1,0),"n/a") | G89: =IF(AND(ISNUMBER('Income Statement'!G51),ISNUMBER('Income Statement'!C51)),IF('Income Statement'!G51<='Income Statement'!C51,1,0),"n/a") | H89: =IF(AND(ISNUMBER('Income Statement'!H51),ISNUMBER('Income Statement'!D51)),IF('Income Statement'!H51<='Income Statement'!D51,1,0),"n/a") | I89: =IF(AND(ISNUMBER('Income Statement'!I51),ISNUMBER('Income Statement'!E51)),IF('Income Statement'!I51<='Income Statement'!E51,1,0),"n/a") | J89: =IF(AND(ISNUMBER('Income Statement'!J51),ISNUMBER('Income Statement'!F51)),IF('Income Statement'!J51<='Income Statement'!F51,1,0),"n/a")
A90: 8. dGM% > 0 (YoY) | B90: n/a | C90: n/a | D90: n/a | E90: n/a | F90: =IF(('Income Statement'!F36/'Income Statement'!F34)>('Income Statement'!B36/'Income Statement'!B34),1,0) | G90: =IF(('Income Statement'!G36/'Income Statement'!G34)>('Income Statement'!C36/'Income Statement'!C34),1,0) | H90: =IF(('Income Statement'!H36/'Income Statement'!H34)>('Income Statement'!D36/'Income Statement'!D34),1,0) | I90: =IF(('Income Statement'!I36/'Income Statement'!I34)>('Income Statement'!E36/'Income Statement'!E34),1,0) | J90: =IF(('Income Statement'!J36/'Income Statement'!J34)>('Income Statement'!F36/'Income Statement'!F34),1,0)
A91: 9. dATO > 0 (YoY) | B91: n/a | C91: n/a | D91: n/a | E91: n/a | F91: n/a | G91: =IF(('Income Statement'!G34/(('Balance Sheet'!G75+'Balance Sheet'!F75)/2))>('Income Statement'!C34/(('Balance Sheet'!C75+'Balance Sheet'!B75)/2)),1,0) | H91: =IF(('Income Statement'!H34/(('Balance Sheet'!H75+'Balance Sheet'!G75)/2))>('Income Statement'!D34/(('Balance Sheet'!D75+'Balance Sheet'!C75)/2)),1,0) | I91: =IF(('Income Statement'!I34/(('Balance Sheet'!I75+'Balance Sheet'!H75)/2))>('Income Statement'!E34/(('Balance Sheet'!E75+'Balance Sheet'!D75)/2)),1,0) | J91: =IF(('Income Statement'!J34/(('Balance Sheet'!J75+'Balance Sheet'!I75)/2))>('Income Statement'!F34/(('Balance Sheet'!F75+'Balance Sheet'!E75)/2)),1,0)
A92: F-SCORE (of signals available) | B92: =SUM(B83:B91) | C92: =SUM(C83:C91) | D92: =SUM(D83:D91) | E92: =SUM(E83:E91) | F92: =SUM(F83:F91) | G92: =SUM(G83:G91) | H92: =SUM(H83:H91) | I92: =SUM(I83:I91) | J92: =SUM(J83:J91)
A93: Verdict (<=3 weak; >=8 strong; 9 signals only from t-4+1) | B93: n/a | C93: n/a | D93: n/a | E93: n/a | F93: n/a | G93: =IF(G92<=3,"WEAK",IF(G92>=8,"strong","mid")) | H93: =IF(H92<=3,"WEAK",IF(H92>=8,"strong","mid")) | I93: =IF(I92<=3,"WEAK",IF(I92>=8,"strong","mid")) | J93: =IF(J92<=3,"WEAK",IF(J92>=8,"strong","mid"))
A95: D. BENFORD'S LAW (per 10-Q; derived Q4 columns have no filing)
A97: Filing (10-Q accession) | B97: 0001652044-24-000053 | C97: 0001652044-24-000079 | D97: 0001652044-24-000118 | F97: 0001652044-25-000043 | G97: 0001652044-25-000062 | H97: 0001652044-25-000091 | J97: 0001652044-26-000048
A98: N facts | B98: 301 | C98: 398 | D98: 403 | F98: 358 | G98: 468 | H98: 471 | J98: 368
A99: MAD (first digit) | B99: 0.0125 | C99: 0.01214 | D99: 0.00888 | F99: 0.01752 | G99: 0.01313 | H99: 0.01278 | J99: 0.01104
A100: MAD verdict | B100: marginal | C100: marginal | D100: acceptable | F100: NONCONFORM | G100: marginal | H100: marginal | J100: acceptable
A101: chi-square (df=8) | B101: 7.7 | C101: 9.5 | D101: 6.2 | F101: 11.1 | G101: 9.9 | H101: 7.2 | J101: 6.8
A102: chi-sq > 15.51? | B102: no | C102: no | D102: no | F102: no | G102: no | H102: no | J102: no

Sheet Guidance & Consensus
A1: Alphabet Inc. (GOOGL) — Guidance & Consensus
A2: Consensus: free-source snapshots captured DATED at each run, never backfilled - this ledger is the point-in-time archive. Forward statements: as-filed releases/MD&A only.
A4: 1. MANAGEMENT FORWARD STATEMENTS
A5: POLICY: NO FORMAL GUIDANCE — Alphabet publishes no outlook tables; the rows below are the dated, quantified forward statements that appear in filed documents (earnings releases / MD&A).
A7: Given | B7: Source | C7: For period | D7: Metric | E7: Low | F7: Mid | G7: High | H7: Unit | I7: Actual (as filed) | J7: Act vs Mid | L7: Statement / evidence
A8: 2024-01-31 | B8: 0001652044-24-000022 | C8: FY2024 | D8: capex commentary | H8: USD millions | L8: 'We expect to increase, relative to 2023, our investment in our technical infrastructure, including servers, network equipment, and data centers... in
A9: 2025-02-04 | B9: 0001652044-25-000010 | C9: FY2025 | D9: capex commentary | E9: 75000 | F9: 75000 | G9: 75000 | H9: USD millions | I9: =ABS('Cash Flow Statement'!K29) | J9: =I9-F9 | L9: Sundar Pichai: 'We are confident about the opportunities ahead, and to accelerate our progress, we expect to invest approximately $75 billion in capit
A10: 2025-02-05 | B10: 0001652044-25-000014 | C10: FY2025 | D10: capex commentary | H10: USD millions | L10: 'We expect to increase, relative to 2024, our investment in our technical infrastructure, including servers, network equipment, and data centers... in
A11: 2025-07-23 | B11: 0001652044-25-000056 | C11: FY2025 | D11: capex commentary | E11: 85000 | F11: 85000 | G11: 85000 | H11: USD millions | I11: =ABS('Cash Flow Statement'!K29) | J11: =I11-F11 | L11: Sundar Pichai: 'With this strong and growing demand for our Cloud products and services, we are increasing our investment in capital expenditures in 2
A12: 2025-10-29 | B12: 0001652044-25-000087 | C12: FY2025 | D12: capex commentary | E12: 91000 | F12: 92000 | G12: 93000 | H12: USD millions | I12: =ABS('Cash Flow Statement'!K29) | J12: =I12-F12 | L12: 'With the growth across our business and demand from Cloud customers, we now expect 2025 capital expenditures to be in a range of $91 billion to $93 b
A13: 2026-02-04 | B13: 0001652044-26-000012 | C13: FY2026 | D13: capex commentary | E13: 175000 | F13: 180000 | G13: 185000 | H13: USD millions | I13: pending | L13: Sundar Pichai: 'To meet customer demand and capitalize on the growing opportunities we have ahead of us, our 2026 CapEx investments are anticipated to
A14: 2026-02-05 | B14: 0001652044-26-000018 | C14: FY2026 | D14: capex commentary | H14: USD millions | L14: 'In 2026, we expect to significantly increase, relative to 2025, our investment in our technical infrastructure, including servers and network equipme
A15: 2026-04-30 | B15: 0001652044-26-000048 | C15: FY2026 | D15: capex commentary | H15: USD millions | L15: 'In 2026, we expect to significantly increase, relative to 2025, our investment in our technical infrastructure...' (Q1 2026 capex was $35.7 billion v
A16: 2024-04-25 | B16: 0001652044-24-000047 | C16: ongoing | D16: capital return commentary | H16: see evidence | L16: Initiation of cash dividend program: '$0.20 per share... The company intends to pay quarterly cash dividends in the future'; Board 'authorized the com
A17: 2025-04-24 | B17: 0001652044-25-000040 | C17: ongoing | D17: capital return commentary | H17: see evidence | L17: 'quarterly cash dividend of $0.21 representing a 5% increase from the previous quarterly dividend of $0.20'; Board 'authorized the company to repurcha
A18: 2026-04-29 | B18: 0001652044-26-000043 | C18: ongoing | D18: capital return commentary | H18: see evidence | L18: 'The company announced a 5% increase to the dividend, resulting in a quarterly cash dividend of $0.22.'
A21: 2. CONSENSUS SNAPSHOTS (point-in-time ledger - grows, never revised)
A22: Snapshot | B22: Period | C22: Rev avg ($M) | D22: Rev low | E22: Rev high | F22: #A | G22: EPS avg | H22: EPS low | I22: EPS high | J22: #A | K22: PT mean / price | L22: Source
A23: 2026-06-12 | B23: Q2 2026 | C23: 116678.36 | D23: 113623 | E23: 120126 | F23: 37 | G23: 2.87003 | H23: 2.6 | I23: 3.13 | J23: 42 | K23: 433 / 363 | L23: yfinance (Yahoo Finance aggregation)
B24: Q3 2026 | C24: 123399.91 | D24: 119062 | E24: 135927 | F24: 34 | G24: 3.00261 | H24: 2.67 | I24: 3.72 | J24: 38
B25: FY2026 | C25: 487719.9 | D25: 473886 | E25: 518969.93 | F25: 52 | G25: 14.22039 | H25: 12.79 | I25: 15.13 | J25: 53
B26: FY2027 | C26: 578906.99 | D26: 475293 | E26: 674239 | F26: 53 | G26: 14.4584 | H26: 11.7 | I26: 17.18 | J26: 55
A29: 3. TRANSLATION TO RIM PARAMETERS — OURS vs STREET (snapshot 2026-06-12)
A30: Bridge: street NI = street EPS x Model_Base diluted shares (L50); street NOPAT ~= street NI + model after-tax net interest (L33). OURS cells are live links - editing Model_Base updates this block. The FY2026 capex statement ($175-185B) has no direct model line; it informs the nolaRatioVector judgment.
A31: Metric | B31: OURS (Model_Base) | C31: STREET | D31: GUIDE-ish | E31: d STREET-OURS | F31: Note
A32: FY2026 revenue ($M) | B32: =Model_Base!L31 | C32: 487719.9 | E32: =C32-B32 | F32: street n=52
A33: FY2026 revenue growth Y1 | B33: =Model_Base!L11 | C33: =C32/'Income Statement'!K7-1 | E33: =C33-B33 | F33: street implied vs our growthVector[0]
A34: FY2027 revenue ($M) | B34: =Model_Base!M31 | C34: 578906.99 | E34: =C34-B34 | F34: street n=53
A35: FY2027 revenue growth Y2 | B35: =Model_Base!M11 | C35: =C34/C32-1 | E35: =C35-B35 | F35: street implied vs our growthVector[1]
A36: FY2026 diluted EPS | B36: =Model_Base!L34/Model_Base!L50 | C36: 14.22039 | E36: =C36-B36 | F36: street n=53
A37: FY2026 net income ($M) | B37: =Model_Base!L34 | C37: =C36*Model_Base!L50 | E37: =C37-B37 | F37: street NI = street EPS x model diluted shares
A38: FY2026 NOPAT margin | B38: =Model_Base!L12 | C38: =(C37+Model_Base!L33)/C32 | E38: =C38-B38 | F38: street NOPAT ~= NI + model after-tax net interest; compare also the IS-tab CORE NOPAT MARGIN row
A39: FY2026 capex ($M) | B39: n/a (annual model) | D39: 180000 | F39: release statement; informs nolaRatioVector, no direct model line
A40: Q2 2026 revenue ($M) | B40: n/a (annual model) | C40: 116678.36 | F40: street n=37
A41: Q2 2026 diluted EPS | B41: n/a (annual model) | C41: 2.87003 | F41: no company guide exists (policy)
A42: Reading: rows where dSTREET-OURS is large are WHERE WE DISAGREE WITH THE STREET, in our own model's units - take them to the memo.

Sheet Model_Bear
A1: MARKET DATA (Given) — BEAR CASE
A2: Beta | B2: 1.15
A3: Risk premium | B3: 0.05
A4: Risk free rate | B4: 0.042
A5: Cost of equity (Ke) | B5: =B4+B3*B2
A6: Tax Rate | B6: 0.17
A7: Pre-Tax Net Cost of Net Debt | B7: =B8/(1-B6)
A8: After-Tax Net Cost of Net Debt | B8: =AVERAGE('ALT DuPont'!H23:K23)
A9: Terminal growth (g) | B9: =U11
A10: Year | B10: =YEAR('Income Statement'!B6) | C10: =YEAR('Income Statement'!C6) | D10: =YEAR('Income Statement'!D6) | E10: =YEAR('Income Statement'!E6) | F10: =YEAR('Income Statement'!F6) | G10: =YEAR('Income Statement'!G6) | H10: =YEAR('Income Statement'!H6) | I10: =YEAR('Income Statement'!I6) | ... K10: =YEAR('Income Statement'!K6) | L10: =K10+1 | M10: =L10+1 | N10: =M10+1 | O10: =N10+1 | P10: =O10+1 | Q10: =P10+1 | R10: =Q10+1 | S10: =R10+1 | ... U10: =T10+1 | W10: Historical Average
A11: Revenue Growth Assumption | B11: n/a | C11: =C31/B31-1 | D11: =D31/C31-1 | E11: =E31/D31-1 | F11: =F31/E31-1 | G11: =G31/F31-1 | H11: =H31/G31-1 | I11: =I31/H31-1 | J11: =J31/I31-1 | K11: =K31/J31-1 | L11: 0.1 | M11: 0.08 | N11: 0.06 | O11: 0.05 | P11: 0.04 | Q11: 0.04 | R11: 0.03 | S11: 0.03 | T11: 0.03 | U11: 0.03 | W11: =AVERAGE(C11:K11)
A12: NOPAT Margin | B12: =B32/B31 | C12: =C32/C31 | D12: =D32/D31 | E12: =E32/E31 | F12: =F32/F31 | G12: =G32/G31 | H12: =H32/H31 | I12: =I32/I31 | ... K12: =K32/K31 | L12: 0.24 | M12: 0.235 | N12: 0.23 | O12: 0.225 | P12: 0.22 | Q12: 0.215 | R12: 0.21 | S12: 0.205 | T12: 0.2 | U12: 0.2 | W12: =AVERAGE(C12:K12)
A14: (Beg) NOWC / Sales | B14: n/a | C14: =C21/C31 | D14: =D21/D31 | E14: =E21/E31 | F14: =F21/F31 | G14: =G21/G31 | H14: =H21/H31 | I14: =I21/I31 | J14: =J21/J31 | K14: =K21/K31 | L14: 0.02 | M14: 0.025 | N14: 0.03 | O14: 0.035 | P14: 0.04 | Q14: 0.045 | R14: 0.05 | S14: 0.055 | T14: 0.06 | U14: 0.065 | W14: =AVERAGE(C14:K14)
A15: (Beg) Net Op LT Assets / Sales | B15: n/a | C15: =C22/C31 | D15: =D22/D31 | E15: =E22/E31 | F15: =F22/F31 | G15: =G22/G31 | H15: =H22/H31 | I15: =I22/I31 | J15: =J22/J31 | K15: =K22/K31 | L15: 0.5 | M15: 0.55 | N15: 0.6 | O15: 0.65 | P15: 0.7 | Q15: 0.75 | R15: 0.8 | S15: 0.85 | T15: 0.9 | U15: 0.95 | W15: =AVERAGE(C15:K15)
A17: Leverage (Beg Net Debt / Beg Assets) | B17: n/a | C17: =IFERROR(C26/C28,0) | D17: =IFERROR(D26/D28,0) | E17: =IFERROR(E26/E28,0) | F17: =IFERROR(F26/F28,0) | G17: =IFERROR(G26/G28,0) | H17: =IFERROR(H26/H28,0) | I17: =IFERROR(I26/I28,0) | J17: =IFERROR(J26/J28,0) | ... L17: =IFERROR(L26/L28,0) | M17: =L17 | N17: =M17 | O17: =N17 | P17: =O17 | Q17: =P17 | R17: =Q17 | S17: =R17 | T17: =S17 | U17: =T17
A19: BALANCE SHEET (Beginning)
A20: Operating Assets (Beginning)
A21: Net operating working capital | B21: ='Condensed Financials'!B27 | C21: ='Condensed Financials'!C27 | D21: ='Condensed Financials'!D27 | E21: ='Condensed Financials'!E27 | F21: ='Condensed Financials'!F27 | G21: ='Condensed Financials'!G27 | H21: ='Condensed Financials'!H27 | I21: ='Condensed Financials'!I27 | ... K21: ='Condensed Financials'!K27 | L21: ='Condensed Financials'!K27 | M21: =M14*M$31 | N21: =N14*N$31 | O21: =O14*O$31 | P21: =P14*P$31 | Q21: =Q14*Q$31 | R21: =R14*R$31 | S21: =S14*S$31 | T21: =T14*T$31 | U21: =U14*U$31
A22: Net operating LT assets | B22: ='Condensed Financials'!B31 | C22: ='Condensed Financials'!C31 | D22: ='Condensed Financials'!D31 | E22: ='Condensed Financials'!E31 | F22: ='Condensed Financials'!F31 | G22: ='Condensed Financials'!G31 | H22: ='Condensed Financials'!H31 | I22: ='Condensed Financials'!I31 | ... K22: ='Condensed Financials'!K31 | L22: ='Condensed Financials'!K31 | M22: =M15*M$31 | N22: =N15*N$31 | O22: =O15*O$31 | P22: =P15*P$31 | Q22: =Q15*Q$31 | R22: =R15*R$31 | S22: =S15*S$31 | T22: =T15*T$31 | U22: =U15*U$31
A23: Total operating net assets | B23: =B21+B22 | C23: =C21+C22 | D23: =D21+D22 | E23: =E21+E22 | F23: =F21+F22 | G23: =G21+G22 | H23: =H21+H22 | I23: =I21+I22 | ... U23: =U21+U22
A25: Capital (Beginning)
A26: Net debt | B26: ='Condensed Financials'!B37 | C26: ='Condensed Financials'!C37 | D26: ='Condensed Financials'!D37 | E26: ='Condensed Financials'!E37 | F26: ='Condensed Financials'!F37 | G26: ='Condensed Financials'!G37 | H26: ='Condensed Financials'!H37 | I26: ='Condensed Financials'!I37 | ... K26: ='Condensed Financials'!K37 | L26: ='Condensed Financials'!K37 | M26: =M17*M23 | N26: =N17*N23 | O26: =O17*O23 | P26: =P17*P23 | Q26: =Q17*Q23 | R26: =R17*R23 | S26: =S17*S23 | T26: =T17*T23 | U26: =U17*U23
A27: Common equity | B27: ='Condensed Financials'!B40 | C27: ='Condensed Financials'!C40 | D27: ='Condensed Financials'!D40 | E27: ='Condensed Financials'!E40 | F27: ='Condensed Financials'!F40 | G27: ='Condensed Financials'!G40 | H27: ='Condensed Financials'!H40 | I27: ='Condensed Financials'!I40 | ... K27: ='Condensed Financials'!K40 | L27: ='Condensed Financials'!K40 | M27: =M23-M26 | N27: =N23-N26 | O27: =O23-O26 | P27: =P23-P26 | Q27: =Q23-Q26 | R27: =R23-R26 | S27: =S23-S26 | T27: =T23-T26 | U27: =U23-U26
A28: Total Capital | B28: =B26+B27 | C28: =C26+C27 | D28: =D26+D27 | E28: =E26+E27 | F28: =F26+F27 | G28: =G26+G27 | H28: =H26+H27 | I28: =I26+I27 | ... U28: =U26+U27
A30: INCOME STATEMENT
A31: Sales | B31: ='Income Statement'!B7 | C31: ='Income Statement'!C7 | D31: ='Income Statement'!D7 | E31: ='Income Statement'!E7 | F31: ='Income Statement'!F7 | G31: ='Income Statement'!G7 | H31: ='Income Statement'!H7 | I31: ='Income Statement'!I7 | ... K31: ='Income Statement'!K7 | L31: =K31*(1+L11) | M31: =L31*(1+M11) | N31: =M31*(1+N11) | O31: =N31*(1+O11) | P31: =O31*(1+P11) | Q31: =P31*(1+Q11) | R31: =Q31*(1+R11) | S31: =R31*(1+S11) | ... U31: =T31*(1+U11)
A32: NOPAT | B32: ='Condensed Financials'!B17 | C32: ='Condensed Financials'!C17 | D32: ='Condensed Financials'!D17 | E32: ='Condensed Financials'!E17 | F32: ='Condensed Financials'!F17 | G32: ='Condensed Financials'!G17 | H32: ='Condensed Financials'!H17 | I32: ='Condensed Financials'!I17 | ... K32: ='Condensed Financials'!K17 | L32: =L31*L12 | M32: =M31*M12 | N32: =N31*N12 | O32: =O31*O12 | P32: =P31*P12 | Q32: =Q31*Q12 | R32: =R31*R12 | S32: =S31*S12 | ... U32: =U31*U12
A33: After tax interest expense (income) | B33: ='Condensed Financials'!B16 | C33: ='Condensed Financials'!C16 | D33: ='Condensed Financials'!D16 | E33: ='Condensed Financials'!E16 | F33: ='Condensed Financials'!F16 | G33: ='Condensed Financials'!G16 | H33: ='Condensed Financials'!H16 | I33: ='Condensed Financials'!I16 | ... K33: ='Condensed Financials'!K16 | L33: =L26*$B$8 | M33: =M26*$B$8 | N33: =N26*$B$8 | O33: =O26*$B$8 | P33: =P26*$B$8 | Q33: =Q26*$B$8 | R33: =R26*$B$8 | S33: =S26*$B$8 | ... U33: =U26*$B$8
A34: Net Income | B34: =B32-B33 | C34: =C32-C33 | D34: =D32-D33 | E34: =E32-E33 | F34: =F32-F33 | G34: =G32-G33 | H34: =H32-H33 | I34: =I32-I33 | ... U34: =U32-U33
A36: Return on (Beg) Equity | B36: n/a | C36: =IFERROR(C34/C27,0) | D36: =IFERROR(D34/D27,0) | E36: =IFERROR(E34/E27,0) | F36: =IFERROR(F34/F27,0) | G36: =IFERROR(G34/G27,0) | H36: =IFERROR(H34/H27,0) | I36: =IFERROR(I34/I27,0) | J36: =IFERROR(J34/J27,0) | ... U36: =IFERROR(U34/U27,0) | W36: =AVERAGE(C36:K36)
A37: Return on (Beg) NOA | B37: n/a | C37: =IFERROR(C32/C23,0) | D37: =IFERROR(D32/D23,0) | E37: =IFERROR(E32/E23,0) | F37: =IFERROR(F32/F23,0) | G37: =IFERROR(G32/G23,0) | H37: =IFERROR(H32/H23,0) | I37: =IFERROR(I32/I23,0) | J37: =IFERROR(J32/J23,0) | ... U37: =IFERROR(U32/U23,0) | W37: =AVERAGE(C37:K37)
A39: ABNORMAL EARNINGS & VALUATION
A40: Net Income | L40: =L34 | M40: =M34 | N40: =N34 | O40: =O34 | P40: =P34 | Q40: =Q34 | R40: =R34 | S40: =S34 | ... U40: =U34
A41: Capital charge (Beg Eq × Ke) | L41: =L27*$B$5 | M41: =M27*$B$5 | N41: =N27*$B$5 | O41: =O27*$B$5 | P41: =P27*$B$5 | Q41: =Q27*$B$5 | R41: =R27*$B$5 | S41: =S27*$B$5 | ... U41: =U27*$B$5
A42: Abnormal earnings | L42: =L40-L41 | M42: =M40-M41 | N42: =N40-N41 | O42: =O40-O41 | P42: =P40-P41 | Q42: =Q40-Q41 | R42: =R40-R41 | S42: =S40-S41 | ... U42: =U40-U41
A43: Free Cash Flow to Equity | L43: =L40+(K27-L27) | M43: =M40+(L27-M27) | N43: =N40+(M27-N27) | O43: =O40+(N27-O27) | P43: =P40+(O27-P27) | Q43: =Q40+(P27-Q27) | R43: =R40+(Q27-R27) | S43: =S40+(R27-S27) | ... U43: =U40+(T27-U27)
A44: PV Factor | L44: =1/(1+$B$5) | M44: =L44/(1+$B$5) | N44: =M44/(1+$B$5) | O44: =N44/(1+$B$5) | P44: =O44/(1+$B$5) | Q44: =P44/(1+$B$5) | R44: =Q44/(1+$B$5) | S44: =R44/(1+$B$5) | T44: =S44/(1+$B$5) | U44: =T44/(1+$B$5)
A45: PV of abnormal earnings | L45: =L42*L44 | M45: =M42*M44 | N45: =N42*N44 | O45: =O42*O44 | P45: =P42*P44 | Q45: =Q42*Q44 | R45: =R42*R44 | S45: =S42*S44 | ... U45: =U42*U44
A46: Sum of PV of abnormal earnings | L46: =SUM(L45:U45) | U46: =U42*(1+$B$9)/($B$5-$B$9)
A47: Terminal value (PV) | L47: =U46*U44
A48: Book Value of Equity (anchor) | L48: =L27
A49: Intrinsic Value of Common Equity | L49: =L48+L47+L46
A50: Number of shares (diluted, M) | L50: 12230
A51: Intrinsic value per share | L51: =L49/L50
A53: ENTERPRISE DCF (FCFF / WACC) — cross-check of the equity (RIM) value
A54: FCFF = NOPAT − ΔNet Operating Assets; EV = PV(FCFF) at WACC; Equity = EV − net debt (market value). Should ≈ the equity (RIM) value above. A material gap ⇒ recheck the market value of net debt or the WACC. Net cash here ⇒ the debt weight is negative; an inherent ~1–2% residual exists from terminal/leverage conventions.
A56: WACC INPUTS
A57: Cost of equity (Ke) | B57: =B5
A58: After-tax cost of debt (Kd) | B58: =B8
A59: Net debt — book ($M) | B59: =L26
A60: Net debt — market value ($M) — INPUT (book proxy; override when MV pulled) | B60: -50006
A61: Market cap ($M) = price × shares | B61: =363.6*L50
A62: Equity weight wE | B62: =B61/(B61+B60)
A63: Debt weight wD | B63: =B60/(B61+B60)
A64: WACC | B64: =B62*B57+B63*B58
A66: FCFF = NOPAT − ΔNet Op Assets ($M) | L66: =L32-(M23-L23) | M66: =M32-(N23-M23) | N66: =N32-(O23-N23) | O66: =O32-(P23-O23) | P66: =P32-(Q23-P23) | Q66: =Q32-(R23-Q23) | R66: =R32-(S23-R23) | S66: =S32-(T23-S23) | T66: =T32-(U23-T23) | U66: =U32-U23*B9
A67: PV factor @ WACC | L67: =1/(1+$B$64)^1 | M67: =1/(1+$B$64)^2 | N67: =1/(1+$B$64)^3 | O67: =1/(1+$B$64)^4 | P67: =1/(1+$B$64)^5 | Q67: =1/(1+$B$64)^6 | R67: =1/(1+$B$64)^7 | S67: =1/(1+$B$64)^8 | T67: =1/(1+$B$64)^9 | U67: =1/(1+$B$64)^10
A68: PV of FCFF ($M) | L68: =L66*L67 | M68: =M66*M67 | N68: =N66*N67 | O68: =O66*O67 | P68: =P66*P67 | Q68: =Q66*Q67 | R68: =R66*R67 | S68: =S66*S67 | ... U68: =U66*U67
A70: Σ PV of FCFF (explicit 10y) | L70: =SUM(L68:U68)
A71: Terminal value (PV) | L71: =U66*(1+B9)/($B$64-B9)*U67
A72: Enterprise value ($M) | L72: =L70+L71
A73: less: net debt (market value) | L73: =B60
A74: Equity value — DCF ($M) | L74: =L72-L73
A75: IVPS — enterprise DCF | L75: =L74/L50
A77: RECONCILIATION vs equity (RIM) value
A78: IVPS — equity method (RIM) | L78: =L51
A79: IVPS — enterprise DCF | L79: =L75
A80: Gap (DCF − RIM) | L80: =L75-L51 | M80: =(L75-L51)/L51
A81: ≈0 expected. Material gap ⇒ recheck net-debt market value (row above) or WACC. Inherent ~1–2% residual from terminal/leverage conventions.
A83: SCENARIO RATIONALE — BEAR
A84: ILLUSTRATIVE BEAR — generic deceleration-and-compression inputs for demonstration. Not analysis. Run /bav-pipeline to build scenarios from an actual strategy report.

Sheet Model_Base
A1: MARKET DATA (Given) — BASE CASE
A2: Beta | B2: 1
A3: Risk premium | B3: 0.05
A4: Risk free rate | B4: 0.042
A5: Cost of equity (Ke) | B5: =B4+B3*B2
A6: Tax Rate | B6: 0.17
A7: Pre-Tax Net Cost of Net Debt | B7: =B8/(1-B6)
A8: After-Tax Net Cost of Net Debt | B8: =AVERAGE('ALT DuPont'!H23:K23)
A9: Terminal growth (g) | B9: =U11
A10: Year | B10: =YEAR('Income Statement'!B6) | C10: =YEAR('Income Statement'!C6) | D10: =YEAR('Income Statement'!D6) | E10: =YEAR('Income Statement'!E6) | F10: =YEAR('Income Statement'!F6) | G10: =YEAR('Income Statement'!G6) | H10: =YEAR('Income Statement'!H6) | I10: =YEAR('Income Statement'!I6) | ... K10: =YEAR('Income Statement'!K6) | L10: =K10+1 | M10: =L10+1 | N10: =M10+1 | O10: =N10+1 | P10: =O10+1 | Q10: =P10+1 | R10: =Q10+1 | S10: =R10+1 | ... U10: =T10+1 | W10: Historical Average
A11: Revenue Growth Assumption | B11: n/a | C11: =C31/B31-1 | D11: =D31/C31-1 | E11: =E31/D31-1 | F11: =F31/E31-1 | G11: =G31/F31-1 | H11: =H31/G31-1 | I11: =I31/H31-1 | J11: =J31/I31-1 | K11: =K31/J31-1 | L11: 0.15 | M11: 0.12 | N11: 0.1 | O11: 0.08 | P11: 0.07 | Q11: 0.06 | R11: 0.05 | S11: 0.045 | T11: 0.04 | U11: 0.035 | W11: =AVERAGE(C11:K11)
A12: NOPAT Margin | B12: =B32/B31 | C12: =C32/C31 | D12: =D32/D31 | E12: =E32/E31 | F12: =F32/F31 | G12: =G32/G31 | H12: =H32/H31 | I12: =I32/I31 | ... K12: =K32/K31 | L12: 0.28 | M12: 0.275 | N12: 0.27 | O12: 0.265 | P12: 0.26 | Q12: 0.255 | R12: 0.25 | S12: 0.245 | T12: 0.24 | U12: 0.24 | W12: =AVERAGE(C12:K12)
A14: (Beg) NOWC / Sales | B14: n/a | C14: =C21/C31 | D14: =D21/D31 | E14: =E21/E31 | F14: =F21/F31 | G14: =G21/G31 | H14: =H21/H31 | I14: =I21/I31 | J14: =J21/J31 | K14: =K21/K31 | L14: 0.02 | M14: 0.025 | N14: 0.03 | O14: 0.035 | P14: 0.04 | Q14: 0.045 | R14: 0.05 | S14: 0.055 | T14: 0.06 | U14: 0.065 | W14: =AVERAGE(C14:K14)
A15: (Beg) Net Op LT Assets / Sales | B15: n/a | C15: =C22/C31 | D15: =D22/D31 | E15: =E22/E31 | F15: =F22/F31 | G15: =G22/G31 | H15: =H22/H31 | I15: =I22/I31 | J15: =J22/J31 | K15: =K22/K31 | L15: 0.5 | M15: 0.55 | N15: 0.6 | O15: 0.65 | P15: 0.7 | Q15: 0.75 | R15: 0.8 | S15: 0.85 | T15: 0.9 | U15: 0.95 | W15: =AVERAGE(C15:K15)
A17: Leverage (Beg Net Debt / Beg Assets) | B17: n/a | C17: =IFERROR(C26/C28,0) | D17: =IFERROR(D26/D28,0) | E17: =IFERROR(E26/E28,0) | F17: =IFERROR(F26/F28,0) | G17: =IFERROR(G26/G28,0) | H17: =IFERROR(H26/H28,0) | I17: =IFERROR(I26/I28,0) | J17: =IFERROR(J26/J28,0) | ... L17: =IFERROR(L26/L28,0) | M17: =L17 | N17: =M17 | O17: =N17 | P17: =O17 | Q17: =P17 | R17: =Q17 | S17: =R17 | T17: =S17 | U17: =T17
A19: BALANCE SHEET (Beginning)
A20: Operating Assets (Beginning)
A21: Net operating working capital | B21: ='Condensed Financials'!B27 | C21: ='Condensed Financials'!C27 | D21: ='Condensed Financials'!D27 | E21: ='Condensed Financials'!E27 | F21: ='Condensed Financials'!F27 | G21: ='Condensed Financials'!G27 | H21: ='Condensed Financials'!H27 | I21: ='Condensed Financials'!I27 | ... K21: ='Condensed Financials'!K27 | L21: ='Condensed Financials'!K27 | M21: =M14*M$31 | N21: =N14*N$31 | O21: =O14*O$31 | P21: =P14*P$31 | Q21: =Q14*Q$31 | R21: =R14*R$31 | S21: =S14*S$31 | T21: =T14*T$31 | U21: =U14*U$31
A22: Net operating LT assets | B22: ='Condensed Financials'!B31 | C22: ='Condensed Financials'!C31 | D22: ='Condensed Financials'!D31 | E22: ='Condensed Financials'!E31 | F22: ='Condensed Financials'!F31 | G22: ='Condensed Financials'!G31 | H22: ='Condensed Financials'!H31 | I22: ='Condensed Financials'!I31 | ... K22: ='Condensed Financials'!K31 | L22: ='Condensed Financials'!K31 | M22: =M15*M$31 | N22: =N15*N$31 | O22: =O15*O$31 | P22: =P15*P$31 | Q22: =Q15*Q$31 | R22: =R15*R$31 | S22: =S15*S$31 | T22: =T15*T$31 | U22: =U15*U$31
A23: Total operating net assets | B23: =B21+B22 | C23: =C21+C22 | D23: =D21+D22 | E23: =E21+E22 | F23: =F21+F22 | G23: =G21+G22 | H23: =H21+H22 | I23: =I21+I22 | ... U23: =U21+U22
A25: Capital (Beginning)
A26: Net debt | B26: ='Condensed Financials'!B37 | C26: ='Condensed Financials'!C37 | D26: ='Condensed Financials'!D37 | E26: ='Condensed Financials'!E37 | F26: ='Condensed Financials'!F37 | G26: ='Condensed Financials'!G37 | H26: ='Condensed Financials'!H37 | I26: ='Condensed Financials'!I37 | ... K26: ='Condensed Financials'!K37 | L26: ='Condensed Financials'!K37 | M26: =M17*M23 | N26: =N17*N23 | O26: =O17*O23 | P26: =P17*P23 | Q26: =Q17*Q23 | R26: =R17*R23 | S26: =S17*S23 | T26: =T17*T23 | U26: =U17*U23
A27: Common equity | B27: ='Condensed Financials'!B40 | C27: ='Condensed Financials'!C40 | D27: ='Condensed Financials'!D40 | E27: ='Condensed Financials'!E40 | F27: ='Condensed Financials'!F40 | G27: ='Condensed Financials'!G40 | H27: ='Condensed Financials'!H40 | I27: ='Condensed Financials'!I40 | ... K27: ='Condensed Financials'!K40 | L27: ='Condensed Financials'!K40 | M27: =M23-M26 | N27: =N23-N26 | O27: =O23-O26 | P27: =P23-P26 | Q27: =Q23-Q26 | R27: =R23-R26 | S27: =S23-S26 | T27: =T23-T26 | U27: =U23-U26
A28: Total Capital | B28: =B26+B27 | C28: =C26+C27 | D28: =D26+D27 | E28: =E26+E27 | F28: =F26+F27 | G28: =G26+G27 | H28: =H26+H27 | I28: =I26+I27 | ... U28: =U26+U27
A30: INCOME STATEMENT
A31: Sales | B31: ='Income Statement'!B7 | C31: ='Income Statement'!C7 | D31: ='Income Statement'!D7 | E31: ='Income Statement'!E7 | F31: ='Income Statement'!F7 | G31: ='Income Statement'!G7 | H31: ='Income Statement'!H7 | I31: ='Income Statement'!I7 | ... K31: ='Income Statement'!K7 | L31: =K31*(1+L11) | M31: =L31*(1+M11) | N31: =M31*(1+N11) | O31: =N31*(1+O11) | P31: =O31*(1+P11) | Q31: =P31*(1+Q11) | R31: =Q31*(1+R11) | S31: =R31*(1+S11) | ... U31: =T31*(1+U11)
A32: NOPAT | B32: ='Condensed Financials'!B17 | C32: ='Condensed Financials'!C17 | D32: ='Condensed Financials'!D17 | E32: ='Condensed Financials'!E17 | F32: ='Condensed Financials'!F17 | G32: ='Condensed Financials'!G17 | H32: ='Condensed Financials'!H17 | I32: ='Condensed Financials'!I17 | ... K32: ='Condensed Financials'!K17 | L32: =L31*L12 | M32: =M31*M12 | N32: =N31*N12 | O32: =O31*O12 | P32: =P31*P12 | Q32: =Q31*Q12 | R32: =R31*R12 | S32: =S31*S12 | ... U32: =U31*U12
A33: After tax interest expense (income) | B33: ='Condensed Financials'!B16 | C33: ='Condensed Financials'!C16 | D33: ='Condensed Financials'!D16 | E33: ='Condensed Financials'!E16 | F33: ='Condensed Financials'!F16 | G33: ='Condensed Financials'!G16 | H33: ='Condensed Financials'!H16 | I33: ='Condensed Financials'!I16 | ... K33: ='Condensed Financials'!K16 | L33: =L26*$B$8 | M33: =M26*$B$8 | N33: =N26*$B$8 | O33: =O26*$B$8 | P33: =P26*$B$8 | Q33: =Q26*$B$8 | R33: =R26*$B$8 | S33: =S26*$B$8 | ... U33: =U26*$B$8
A34: Net Income | B34: =B32-B33 | C34: =C32-C33 | D34: =D32-D33 | E34: =E32-E33 | F34: =F32-F33 | G34: =G32-G33 | H34: =H32-H33 | I34: =I32-I33 | ... U34: =U32-U33
A36: Return on (Beg) Equity | B36: n/a | C36: =IFERROR(C34/C27,0) | D36: =IFERROR(D34/D27,0) | E36: =IFERROR(E34/E27,0) | F36: =IFERROR(F34/F27,0) | G36: =IFERROR(G34/G27,0) | H36: =IFERROR(H34/H27,0) | I36: =IFERROR(I34/I27,0) | J36: =IFERROR(J34/J27,0) | ... U36: =IFERROR(U34/U27,0) | W36: =AVERAGE(C36:K36)
A37: Return on (Beg) NOA | B37: n/a | C37: =IFERROR(C32/C23,0) | D37: =IFERROR(D32/D23,0) | E37: =IFERROR(E32/E23,0) | F37: =IFERROR(F32/F23,0) | G37: =IFERROR(G32/G23,0) | H37: =IFERROR(H32/H23,0) | I37: =IFERROR(I32/I23,0) | J37: =IFERROR(J32/J23,0) | ... U37: =IFERROR(U32/U23,0) | W37: =AVERAGE(C37:K37)
A39: ABNORMAL EARNINGS & VALUATION
A40: Net Income | L40: =L34 | M40: =M34 | N40: =N34 | O40: =O34 | P40: =P34 | Q40: =Q34 | R40: =R34 | S40: =S34 | ... U40: =U34
A41: Capital charge (Beg Eq × Ke) | L41: =L27*$B$5 | M41: =M27*$B$5 | N41: =N27*$B$5 | O41: =O27*$B$5 | P41: =P27*$B$5 | Q41: =Q27*$B$5 | R41: =R27*$B$5 | S41: =S27*$B$5 | ... U41: =U27*$B$5
A42: Abnormal earnings | L42: =L40-L41 | M42: =M40-M41 | N42: =N40-N41 | O42: =O40-O41 | P42: =P40-P41 | Q42: =Q40-Q41 | R42: =R40-R41 | S42: =S40-S41 | ... U42: =U40-U41
A43: Free Cash Flow to Equity | L43: =L40+(K27-L27) | M43: =M40+(L27-M27) | N43: =N40+(M27-N27) | O43: =O40+(N27-O27) | P43: =P40+(O27-P27) | Q43: =Q40+(P27-Q27) | R43: =R40+(Q27-R27) | S43: =S40+(R27-S27) | ... U43: =U40+(T27-U27)
A44: PV Factor | L44: =1/(1+$B$5) | M44: =L44/(1+$B$5) | N44: =M44/(1+$B$5) | O44: =N44/(1+$B$5) | P44: =O44/(1+$B$5) | Q44: =P44/(1+$B$5) | R44: =Q44/(1+$B$5) | S44: =R44/(1+$B$5) | T44: =S44/(1+$B$5) | U44: =T44/(1+$B$5)
A45: PV of abnormal earnings | L45: =L42*L44 | M45: =M42*M44 | N45: =N42*N44 | O45: =O42*O44 | P45: =P42*P44 | Q45: =Q42*Q44 | R45: =R42*R44 | S45: =S42*S44 | ... U45: =U42*U44
A46: Sum of PV of abnormal earnings | L46: =SUM(L45:U45) | U46: =U42*(1+$B$9)/($B$5-$B$9)
A47: Terminal value (PV) | L47: =U46*U44
A48: Book Value of Equity (anchor) | L48: =L27
A49: Intrinsic Value of Common Equity | L49: =L48+L47+L46
A50: Number of shares (diluted, M) | L50: 12230
A51: Intrinsic value per share | L51: =L49/L50
A53: ENTERPRISE DCF (FCFF / WACC) — cross-check of the equity (RIM) value
A54: FCFF = NOPAT − ΔNet Operating Assets; EV = PV(FCFF) at WACC; Equity = EV − net debt (market value). Should ≈ the equity (RIM) value above. A material gap ⇒ recheck the market value of net debt or the WACC. Net cash here ⇒ the debt weight is negative; an inherent ~1–2% residual exists from terminal/leverage conventions.
A56: WACC INPUTS
A57: Cost of equity (Ke) | B57: =B5
A58: After-tax cost of debt (Kd) | B58: =B8
A59: Net debt — book ($M) | B59: =L26
A60: Net debt — market value ($M) — INPUT (book proxy; override when MV pulled) | B60: -50006
A61: Market cap ($M) = price × shares | B61: =363.6*L50
A62: Equity weight wE | B62: =B61/(B61+B60)
A63: Debt weight wD | B63: =B60/(B61+B60)
A64: WACC | B64: =B62*B57+B63*B58
A66: FCFF = NOPAT − ΔNet Op Assets ($M) | L66: =L32-(M23-L23) | M66: =M32-(N23-M23) | N66: =N32-(O23-N23) | O66: =O32-(P23-O23) | P66: =P32-(Q23-P23) | Q66: =Q32-(R23-Q23) | R66: =R32-(S23-R23) | S66: =S32-(T23-S23) | T66: =T32-(U23-T23) | U66: =U32-U23*B9
A67: PV factor @ WACC | L67: =1/(1+$B$64)^1 | M67: =1/(1+$B$64)^2 | N67: =1/(1+$B$64)^3 | O67: =1/(1+$B$64)^4 | P67: =1/(1+$B$64)^5 | Q67: =1/(1+$B$64)^6 | R67: =1/(1+$B$64)^7 | S67: =1/(1+$B$64)^8 | T67: =1/(1+$B$64)^9 | U67: =1/(1+$B$64)^10
A68: PV of FCFF ($M) | L68: =L66*L67 | M68: =M66*M67 | N68: =N66*N67 | O68: =O66*O67 | P68: =P66*P67 | Q68: =Q66*Q67 | R68: =R66*R67 | S68: =S66*S67 | ... U68: =U66*U67
A70: Σ PV of FCFF (explicit 10y) | L70: =SUM(L68:U68)
A71: Terminal value (PV) | L71: =U66*(1+B9)/($B$64-B9)*U67
A72: Enterprise value ($M) | L72: =L70+L71
A73: less: net debt (market value) | L73: =B60
A74: Equity value — DCF ($M) | L74: =L72-L73
A75: IVPS — enterprise DCF | L75: =L74/L50
A77: RECONCILIATION vs equity (RIM) value
A78: IVPS — equity method (RIM) | L78: =L51
A79: IVPS — enterprise DCF | L79: =L75
A80: Gap (DCF − RIM) | L80: =L75-L51 | M80: =(L75-L51)/L51
A81: ≈0 expected. Material gap ⇒ recheck net-debt market value (row above) or WACC. Inherent ~1–2% residual from terminal/leverage conventions.
A83: SCENARIO RATIONALE — BASE
A84: ILLUSTRATIVE BASE — generic moderate-fade inputs for demonstration. Not analysis.

Sheet Model_Bull
A1: MARKET DATA (Given) — BULL CASE
A2: Beta | B2: 0.95
A3: Risk premium | B3: 0.05
A4: Risk free rate | B4: 0.042
A5: Cost of equity (Ke) | B5: =B4+B3*B2
A6: Tax Rate | B6: 0.17
A7: Pre-Tax Net Cost of Net Debt | B7: =B8/(1-B6)
A8: After-Tax Net Cost of Net Debt | B8: =AVERAGE('ALT DuPont'!H23:K23)
A9: Terminal growth (g) | B9: =U11
A10: Year | B10: =YEAR('Income Statement'!B6) | C10: =YEAR('Income Statement'!C6) | D10: =YEAR('Income Statement'!D6) | E10: =YEAR('Income Statement'!E6) | F10: =YEAR('Income Statement'!F6) | G10: =YEAR('Income Statement'!G6) | H10: =YEAR('Income Statement'!H6) | I10: =YEAR('Income Statement'!I6) | ... K10: =YEAR('Income Statement'!K6) | L10: =K10+1 | M10: =L10+1 | N10: =M10+1 | O10: =N10+1 | P10: =O10+1 | Q10: =P10+1 | R10: =Q10+1 | S10: =R10+1 | ... U10: =T10+1 | W10: Historical Average
A11: Revenue Growth Assumption | B11: n/a | C11: =C31/B31-1 | D11: =D31/C31-1 | E11: =E31/D31-1 | F11: =F31/E31-1 | G11: =G31/F31-1 | H11: =H31/G31-1 | I11: =I31/H31-1 | J11: =J31/I31-1 | K11: =K31/J31-1 | L11: 0.2 | M11: 0.17 | N11: 0.14 | O11: 0.12 | P11: 0.1 | Q11: 0.08 | R11: 0.07 | S11: 0.06 | T11: 0.05 | U11: 0.04 | W11: =AVERAGE(C11:K11)
A12: NOPAT Margin | B12: =B32/B31 | C12: =C32/C31 | D12: =D32/D31 | E12: =E32/E31 | F12: =F32/F31 | G12: =G32/G31 | H12: =H32/H31 | I12: =I32/I31 | ... K12: =K32/K31 | L12: 0.32 | M12: 0.315 | N12: 0.31 | O12: 0.305 | P12: 0.3 | Q12: 0.295 | R12: 0.29 | S12: 0.285 | T12: 0.28 | U12: 0.28 | W12: =AVERAGE(C12:K12)
A14: (Beg) NOWC / Sales | B14: n/a | C14: =C21/C31 | D14: =D21/D31 | E14: =E21/E31 | F14: =F21/F31 | G14: =G21/G31 | H14: =H21/H31 | I14: =I21/I31 | J14: =J21/J31 | K14: =K21/K31 | L14: 0.02 | M14: 0.025 | N14: 0.03 | O14: 0.035 | P14: 0.04 | Q14: 0.045 | R14: 0.05 | S14: 0.055 | T14: 0.06 | U14: 0.065 | W14: =AVERAGE(C14:K14)
A15: (Beg) Net Op LT Assets / Sales | B15: n/a | C15: =C22/C31 | D15: =D22/D31 | E15: =E22/E31 | F15: =F22/F31 | G15: =G22/G31 | H15: =H22/H31 | I15: =I22/I31 | J15: =J22/J31 | K15: =K22/K31 | L15: 0.5 | M15: 0.55 | N15: 0.6 | O15: 0.65 | P15: 0.7 | Q15: 0.75 | R15: 0.8 | S15: 0.85 | T15: 0.9 | U15: 0.95 | W15: =AVERAGE(C15:K15)
A17: Leverage (Beg Net Debt / Beg Assets) | B17: n/a | C17: =IFERROR(C26/C28,0) | D17: =IFERROR(D26/D28,0) | E17: =IFERROR(E26/E28,0) | F17: =IFERROR(F26/F28,0) | G17: =IFERROR(G26/G28,0) | H17: =IFERROR(H26/H28,0) | I17: =IFERROR(I26/I28,0) | J17: =IFERROR(J26/J28,0) | ... L17: =IFERROR(L26/L28,0) | M17: =L17 | N17: =M17 | O17: =N17 | P17: =O17 | Q17: =P17 | R17: =Q17 | S17: =R17 | T17: =S17 | U17: =T17
A19: BALANCE SHEET (Beginning)
A20: Operating Assets (Beginning)
A21: Net operating working capital | B21: ='Condensed Financials'!B27 | C21: ='Condensed Financials'!C27 | D21: ='Condensed Financials'!D27 | E21: ='Condensed Financials'!E27 | F21: ='Condensed Financials'!F27 | G21: ='Condensed Financials'!G27 | H21: ='Condensed Financials'!H27 | I21: ='Condensed Financials'!I27 | ... K21: ='Condensed Financials'!K27 | L21: ='Condensed Financials'!K27 | M21: =M14*M$31 | N21: =N14*N$31 | O21: =O14*O$31 | P21: =P14*P$31 | Q21: =Q14*Q$31 | R21: =R14*R$31 | S21: =S14*S$31 | T21: =T14*T$31 | U21: =U14*U$31
A22: Net operating LT assets | B22: ='Condensed Financials'!B31 | C22: ='Condensed Financials'!C31 | D22: ='Condensed Financials'!D31 | E22: ='Condensed Financials'!E31 | F22: ='Condensed Financials'!F31 | G22: ='Condensed Financials'!G31 | H22: ='Condensed Financials'!H31 | I22: ='Condensed Financials'!I31 | ... K22: ='Condensed Financials'!K31 | L22: ='Condensed Financials'!K31 | M22: =M15*M$31 | N22: =N15*N$31 | O22: =O15*O$31 | P22: =P15*P$31 | Q22: =Q15*Q$31 | R22: =R15*R$31 | S22: =S15*S$31 | T22: =T15*T$31 | U22: =U15*U$31
A23: Total operating net assets | B23: =B21+B22 | C23: =C21+C22 | D23: =D21+D22 | E23: =E21+E22 | F23: =F21+F22 | G23: =G21+G22 | H23: =H21+H22 | I23: =I21+I22 | ... U23: =U21+U22
A25: Capital (Beginning)
A26: Net debt | B26: ='Condensed Financials'!B37 | C26: ='Condensed Financials'!C37 | D26: ='Condensed Financials'!D37 | E26: ='Condensed Financials'!E37 | F26: ='Condensed Financials'!F37 | G26: ='Condensed Financials'!G37 | H26: ='Condensed Financials'!H37 | I26: ='Condensed Financials'!I37 | ... K26: ='Condensed Financials'!K37 | L26: ='Condensed Financials'!K37 | M26: =M17*M23 | N26: =N17*N23 | O26: =O17*O23 | P26: =P17*P23 | Q26: =Q17*Q23 | R26: =R17*R23 | S26: =S17*S23 | T26: =T17*T23 | U26: =U17*U23
A27: Common equity | B27: ='Condensed Financials'!B40 | C27: ='Condensed Financials'!C40 | D27: ='Condensed Financials'!D40 | E27: ='Condensed Financials'!E40 | F27: ='Condensed Financials'!F40 | G27: ='Condensed Financials'!G40 | H27: ='Condensed Financials'!H40 | I27: ='Condensed Financials'!I40 | ... K27: ='Condensed Financials'!K40 | L27: ='Condensed Financials'!K40 | M27: =M23-M26 | N27: =N23-N26 | O27: =O23-O26 | P27: =P23-P26 | Q27: =Q23-Q26 | R27: =R23-R26 | S27: =S23-S26 | T27: =T23-T26 | U27: =U23-U26
A28: Total Capital | B28: =B26+B27 | C28: =C26+C27 | D28: =D26+D27 | E28: =E26+E27 | F28: =F26+F27 | G28: =G26+G27 | H28: =H26+H27 | I28: =I26+I27 | ... U28: =U26+U27
A30: INCOME STATEMENT
A31: Sales | B31: ='Income Statement'!B7 | C31: ='Income Statement'!C7 | D31: ='Income Statement'!D7 | E31: ='Income Statement'!E7 | F31: ='Income Statement'!F7 | G31: ='Income Statement'!G7 | H31: ='Income Statement'!H7 | I31: ='Income Statement'!I7 | ... K31: ='Income Statement'!K7 | L31: =K31*(1+L11) | M31: =L31*(1+M11) | N31: =M31*(1+N11) | O31: =N31*(1+O11) | P31: =O31*(1+P11) | Q31: =P31*(1+Q11) | R31: =Q31*(1+R11) | S31: =R31*(1+S11) | ... U31: =T31*(1+U11)
A32: NOPAT | B32: ='Condensed Financials'!B17 | C32: ='Condensed Financials'!C17 | D32: ='Condensed Financials'!D17 | E32: ='Condensed Financials'!E17 | F32: ='Condensed Financials'!F17 | G32: ='Condensed Financials'!G17 | H32: ='Condensed Financials'!H17 | I32: ='Condensed Financials'!I17 | ... K32: ='Condensed Financials'!K17 | L32: =L31*L12 | M32: =M31*M12 | N32: =N31*N12 | O32: =O31*O12 | P32: =P31*P12 | Q32: =Q31*Q12 | R32: =R31*R12 | S32: =S31*S12 | ... U32: =U31*U12
A33: After tax interest expense (income) | B33: ='Condensed Financials'!B16 | C33: ='Condensed Financials'!C16 | D33: ='Condensed Financials'!D16 | E33: ='Condensed Financials'!E16 | F33: ='Condensed Financials'!F16 | G33: ='Condensed Financials'!G16 | H33: ='Condensed Financials'!H16 | I33: ='Condensed Financials'!I16 | ... K33: ='Condensed Financials'!K16 | L33: =L26*$B$8 | M33: =M26*$B$8 | N33: =N26*$B$8 | O33: =O26*$B$8 | P33: =P26*$B$8 | Q33: =Q26*$B$8 | R33: =R26*$B$8 | S33: =S26*$B$8 | ... U33: =U26*$B$8
A34: Net Income | B34: =B32-B33 | C34: =C32-C33 | D34: =D32-D33 | E34: =E32-E33 | F34: =F32-F33 | G34: =G32-G33 | H34: =H32-H33 | I34: =I32-I33 | ... U34: =U32-U33
A36: Return on (Beg) Equity | B36: n/a | C36: =IFERROR(C34/C27,0) | D36: =IFERROR(D34/D27,0) | E36: =IFERROR(E34/E27,0) | F36: =IFERROR(F34/F27,0) | G36: =IFERROR(G34/G27,0) | H36: =IFERROR(H34/H27,0) | I36: =IFERROR(I34/I27,0) | J36: =IFERROR(J34/J27,0) | ... U36: =IFERROR(U34/U27,0) | W36: =AVERAGE(C36:K36)
A37: Return on (Beg) NOA | B37: n/a | C37: =IFERROR(C32/C23,0) | D37: =IFERROR(D32/D23,0) | E37: =IFERROR(E32/E23,0) | F37: =IFERROR(F32/F23,0) | G37: =IFERROR(G32/G23,0) | H37: =IFERROR(H32/H23,0) | I37: =IFERROR(I32/I23,0) | J37: =IFERROR(J32/J23,0) | ... U37: =IFERROR(U32/U23,0) | W37: =AVERAGE(C37:K37)
A39: ABNORMAL EARNINGS & VALUATION
A40: Net Income | L40: =L34 | M40: =M34 | N40: =N34 | O40: =O34 | P40: =P34 | Q40: =Q34 | R40: =R34 | S40: =S34 | ... U40: =U34
A41: Capital charge (Beg Eq × Ke) | L41: =L27*$B$5 | M41: =M27*$B$5 | N41: =N27*$B$5 | O41: =O27*$B$5 | P41: =P27*$B$5 | Q41: =Q27*$B$5 | R41: =R27*$B$5 | S41: =S27*$B$5 | ... U41: =U27*$B$5
A42: Abnormal earnings | L42: =L40-L41 | M42: =M40-M41 | N42: =N40-N41 | O42: =O40-O41 | P42: =P40-P41 | Q42: =Q40-Q41 | R42: =R40-R41 | S42: =S40-S41 | ... U42: =U40-U41
A43: Free Cash Flow to Equity | L43: =L40+(K27-L27) | M43: =M40+(L27-M27) | N43: =N40+(M27-N27) | O43: =O40+(N27-O27) | P43: =P40+(O27-P27) | Q43: =Q40+(P27-Q27) | R43: =R40+(Q27-R27) | S43: =S40+(R27-S27) | ... U43: =U40+(T27-U27)
A44: PV Factor | L44: =1/(1+$B$5) | M44: =L44/(1+$B$5) | N44: =M44/(1+$B$5) | O44: =N44/(1+$B$5) | P44: =O44/(1+$B$5) | Q44: =P44/(1+$B$5) | R44: =Q44/(1+$B$5) | S44: =R44/(1+$B$5) | T44: =S44/(1+$B$5) | U44: =T44/(1+$B$5)
A45: PV of abnormal earnings | L45: =L42*L44 | M45: =M42*M44 | N45: =N42*N44 | O45: =O42*O44 | P45: =P42*P44 | Q45: =Q42*Q44 | R45: =R42*R44 | S45: =S42*S44 | ... U45: =U42*U44
A46: Sum of PV of abnormal earnings | L46: =SUM(L45:U45) | U46: =U42*(1+$B$9)/($B$5-$B$9)
A47: Terminal value (PV) | L47: =U46*U44
A48: Book Value of Equity (anchor) | L48: =L27
A49: Intrinsic Value of Common Equity | L49: =L48+L47+L46
A50: Number of shares (diluted, M) | L50: 12230
A51: Intrinsic value per share | L51: =L49/L50
A53: ENTERPRISE DCF (FCFF / WACC) — cross-check of the equity (RIM) value
A54: FCFF = NOPAT − ΔNet Operating Assets; EV = PV(FCFF) at WACC; Equity = EV − net debt (market value). Should ≈ the equity (RIM) value above. A material gap ⇒ recheck the market value of net debt or the WACC. Net cash here ⇒ the debt weight is negative; an inherent ~1–2% residual exists from terminal/leverage conventions.
A56: WACC INPUTS
A57: Cost of equity (Ke) | B57: =B5
A58: After-tax cost of debt (Kd) | B58: =B8
A59: Net debt — book ($M) | B59: =L26
A60: Net debt — market value ($M) — INPUT (book proxy; override when MV pulled) | B60: -50006
A61: Market cap ($M) = price × shares | B61: =363.6*L50
A62: Equity weight wE | B62: =B61/(B61+B60)
A63: Debt weight wD | B63: =B60/(B61+B60)
A64: WACC | B64: =B62*B57+B63*B58
A66: FCFF = NOPAT − ΔNet Op Assets ($M) | L66: =L32-(M23-L23) | M66: =M32-(N23-M23) | N66: =N32-(O23-N23) | O66: =O32-(P23-O23) | P66: =P32-(Q23-P23) | Q66: =Q32-(R23-Q23) | R66: =R32-(S23-R23) | S66: =S32-(T23-S23) | T66: =T32-(U23-T23) | U66: =U32-U23*B9
A67: PV factor @ WACC | L67: =1/(1+$B$64)^1 | M67: =1/(1+$B$64)^2 | N67: =1/(1+$B$64)^3 | O67: =1/(1+$B$64)^4 | P67: =1/(1+$B$64)^5 | Q67: =1/(1+$B$64)^6 | R67: =1/(1+$B$64)^7 | S67: =1/(1+$B$64)^8 | T67: =1/(1+$B$64)^9 | U67: =1/(1+$B$64)^10
A68: PV of FCFF ($M) | L68: =L66*L67 | M68: =M66*M67 | N68: =N66*N67 | O68: =O66*O67 | P68: =P66*P67 | Q68: =Q66*Q67 | R68: =R66*R67 | S68: =S66*S67 | ... U68: =U66*U67
A70: Σ PV of FCFF (explicit 10y) | L70: =SUM(L68:U68)
A71: Terminal value (PV) | L71: =U66*(1+B9)/($B$64-B9)*U67
A72: Enterprise value ($M) | L72: =L70+L71
A73: less: net debt (market value) | L73: =B60
A74: Equity value — DCF ($M) | L74: =L72-L73
A75: IVPS — enterprise DCF | L75: =L74/L50
A77: RECONCILIATION vs equity (RIM) value
A78: IVPS — equity method (RIM) | L78: =L51
A79: IVPS — enterprise DCF | L79: =L75
A80: Gap (DCF − RIM) | L80: =L75-L51 | M80: =(L75-L51)/L51
A81: ≈0 expected. Material gap ⇒ recheck net-debt market value (row above) or WACC. Inherent ~1–2% residual from terminal/leverage conventions.
A83: SCENARIO RATIONALE — BULL
A84: ILLUSTRATIVE BULL — generic durable-growth inputs for demonstration. Not analysis.

Sheet Scenario_Summary
A1: Alphabet Inc. (GOOGL) — Scenario Summary
A2: Probability-Weighted Residual Income Valuation — ILLUSTRATIVE inputs (see model tabs); not analysis
A4: Metric | B4: Bear | C4: Base | D4: Bull | E4: Weighted
A5: Probability Weight | B5: 0.25 | C5: 0.5 | D5: 0.25
A7: VALUATION OUTPUTS
A8: Intrinsic Value per Share | B8: =Model_Bear!L51 | C8: =Model_Base!L51 | D8: =Model_Bull!L51 | E8: =SUMPRODUCT(B5:D5,B8:D8)
A9: Intrinsic Value of Equity ($M) | B9: =Model_Bear!L49 | C9: =Model_Base!L49 | D9: =Model_Bull!L49 | E9: =SUMPRODUCT(B5:D5,B9:D9)
A10: Book Value of Equity ($M) | B10: =Model_Bear!L48 | C10: =Model_Base!L48 | D10: =Model_Bull!L48 | E10: =SUMPRODUCT(B5:D5,B10:D10)
A11: Sum PV of Abnormal Earnings ($M) | B11: =Model_Bear!L46 | C11: =Model_Base!L46 | D11: =Model_Bull!L46 | E11: =SUMPRODUCT(B5:D5,B11:D11)
A12: Terminal Value PV ($M) | B12: =Model_Bear!L47 | C12: =Model_Base!L47 | D12: =Model_Bull!L47 | E12: =SUMPRODUCT(B5:D5,B12:D12)
A14: MARKET COMPARISON
A15: Current Market Price | B15: 363.6
A16: Implied Upside / (Downside) | B16: =B8/$B$15-1 | C16: =C8/$B$15-1 | D16: =D8/$B$15-1 | E16: =E8/$B$15-1
A18: TERMINAL RETURNS — vs HURDLES & HISTORY
A19: Terminal RNOA (Yr 10) | B19: =Model_Bear!U37 | C19: =Model_Base!U37 | D19: =Model_Bull!U37
A20: WACC (firm hurdle) | B20: =Model_Bear!B64 | C20: =Model_Base!B64 | D20: =Model_Bull!B64
A21: Historical RNOA (FY2025) | B21: ='ALT DuPont'!$K$20 | C21: ='ALT DuPont'!$K$20 | D21: ='ALT DuPont'!$K$20
A22: Terminal RNOA − WACC | B22: =B19-B20 | C22: =C19-C20 | D22: =D19-D20
A23: Terminal RNOA − historical | B23: =B19-B21 | C23: =C19-C21 | D23: =D19-D21
A25: Terminal ROE (Yr 10) | B25: =Model_Bear!U36 | C25: =Model_Base!U36 | D25: =Model_Bull!U36
A26: Cost of equity (Ke) | B26: =Model_Bear!B5 | C26: =Model_Base!B5 | D26: =Model_Bull!B5
A27: Historical ROE (FY2025) | B27: ='ALT DuPont'!$K$30 | C27: ='ALT DuPont'!$K$30 | D27: ='ALT DuPont'!$K$30
A28: Terminal ROE − cost of equity | B28: =B25-B26 | C28: =C25-C26 | D28: =D25-D26
A29: Terminal ROE − historical | B29: =B25-B27 | C29: =C25-C27 | D29: =D25-D27
A31: KEY ASSUMPTIONS
A32: Year 1 Revenue Growth | B32: =Model_Bear!L11 | C32: =Model_Base!L11 | D32: =Model_Bull!L11
A33: Terminal Revenue Growth | B33: =Model_Bear!U11 | C33: =Model_Base!U11 | D33: =Model_Bull!U11
A34: Year 1 NOPAT Margin | B34: =Model_Bear!L12 | C34: =Model_Base!L12 | D34: =Model_Bull!L12
A35: Terminal NOPAT Margin | B35: =Model_Bear!U12 | C35: =Model_Base!U12 | D35: =Model_Bull!U12
A36: Beta | B36: =Model_Bear!B2 | C36: =Model_Base!B2 | D36: =Model_Bull!B2
A38: IMPLIED MULTIPLES
A39: One-year-ahead EPS (FY+1, $) | B39: =Model_Bear!L34/Model_Bear!L50 | C39: =Model_Base!L34/Model_Base!L50 | D39: =Model_Bull!L34/Model_Bull!L50
A40: Implied forward P/E (IVPS ÷ FY+1 EPS) | B40: =Model_Bear!L51*Model_Bear!L50/Model_Bear!L34 | C40: =Model_Base!L51*Model_Base!L50/Model_Base!L34 | D40: =Model_Bull!L51*Model_Bull!L50/Model_Bull!L34
A41: Yr-11 earnings (terminal +1, $M) | B41: =Model_Bear!U34*(1+Model_Bear!B9) | C41: =Model_Base!U34*(1+Model_Base!B9) | D41: =Model_Bull!U34*(1+Model_Bull!B9)
A42: Terminal value (as of Yr-10, $M) | B42: =Model_Bear!U46 | C42: =Model_Base!U46 | D42: =Model_Bull!U46
A43: Implied terminal multiple (TV as-of-Yr10 ÷ Yr-11 earnings) | B43: =Model_Bear!U46/(Model_Bear!U34*(1+Model_Bear!B9)) | C43: =Model_Base!U46/(Model_Base!U34*(1+Model_Base!B9)) | D43: =Model_Bull!U46/(Model_Bull!U34*(1+Model_Bull!B9))
A45: ENTERPRISE DCF CROSS-CHECK
A46: IVPS — enterprise DCF | B46: =Model_Bear!L75 | C46: =Model_Base!L75 | D46: =Model_Bull!L75
A47: IVPS — equity method (RIM) | B47: =Model_Bear!L51 | C47: =Model_Base!L51 | D47: =Model_Bull!L51
A48: Gap (DCF − RIM) | B48: =B46-B47 | C48: =C46-C47 | D48: =D46-D47
A49: P/E uses our intrinsic value over next-year earnings. Terminal multiple = the terminal value AS OF Yr-10 (continuing value at the end of the explicit forecast) over Yr-11 earnings (= Yr-10 NI × (1+g)). RNOA is benchmarked to WACC (firm hurdle); ROE to cost of equity — both vs the FY2025 actual to gauge mean reversion.
A51: SENSITIVITY — IVPS vs Cost of Equity (rows) × Terminal Growth (cols), Base case
A52: Ke ↓ / param → | B52: =Model_Base!$B$9-0.01 | C52: =Model_Base!$B$9-0.005 | D52: =Model_Base!$B$9+0.0 | E52: =Model_Base!$B$9+0.005 | F52: =Model_Base!$B$9+0.01
A53: =Model_Base!$B$5-0.02 | B53: =((Model_Base!$L$48+SUMPRODUCT((Model_Base!$L$40:$U$40-$A$53*Model_Base!$L$27:$U$27)/(1+$A$53)^{1,2,3,4,5,6,7,8,9,10})+(Model_Base!$U$40-$A$53*Model_Base!$U$27)*(1+B$52)/($A$53-B$52)/(1+$A$53)^10)/Model_Base!$L$50) | C53: =((Model_Base!$L$48+SUMPRODUCT((Model_Base!$L$40:$U$40-$A$53*Model_Base!$L$27:$U$27)/(1+$A$53)^{1,2,3,4,5,6,7,8,9,10})+(Model_Base!$U$40-$A$53*Model_Base!$U$27)*(1+C$52)/($A$53-C$52)/(1+$A$53)^10)/Model_Base!$L$50) | D53: =((Model_Base!$L$48+SUMPRODUCT((Model_Base!$L$40:$U$40-$A$53*Model_Base!$L$27:$U$27)/(1+$A$53)^{1,2,3,4,5,6,7,8,9,10})+(Model_Base!$U$40-$A$53*Model_Base!$U$27)*(1+D$52)/($A$53-D$52)/(1+$A$53)^10)/Model_Base!$L$50) | E53: =((Model_Base!$L$48+SUMPRODUCT((Model_Base!$L$40:$U$40-$A$53*Model_Base!$L$27:$U$27)/(1+$A$53)^{1,2,3,4,5,6,7,8,9,10})+(Model_Base!$U$40-$A$53*Model_Base!$U$27)*(1+E$52)/($A$53-E$52)/(1+$A$53)^10)/Model_Base!$L$50) | F53: =((Model_Base!$L$48+SUMPRODUCT((Model_Base!$L$40:$U$40-$A$53*Model_Base!$L$27:$U$27)/(1+$A$53)^{1,2,3,4,5,6,7,8,9,10})+(Model_Base!$U$40-$A$53*Model_Base!$U$27)*(1+F$52)/($A$53-F$52)/(1+$A$53)^10)/Model_Base!$L$50)
A54: =Model_Base!$B$5-0.01 | B54: =((Model_Base!$L$48+SUMPRODUCT((Model_Base!$L$40:$U$40-$A$54*Model_Base!$L$27:$U$27)/(1+$A$54)^{1,2,3,4,5,6,7,8,9,10})+(Model_Base!$U$40-$A$54*Model_Base!$U$27)*(1+B$52)/($A$54-B$52)/(1+$A$54)^10)/Model_Base!$L$50) | C54: =((Model_Base!$L$48+SUMPRODUCT((Model_Base!$L$40:$U$40-$A$54*Model_Base!$L$27:$U$27)/(1+$A$54)^{1,2,3,4,5,6,7,8,9,10})+(Model_Base!$U$40-$A$54*Model_Base!$U$27)*(1+C$52)/($A$54-C$52)/(1+$A$54)^10)/Model_Base!$L$50) | D54: =((Model_Base!$L$48+SUMPRODUCT((Model_Base!$L$40:$U$40-$A$54*Model_Base!$L$27:$U$27)/(1+$A$54)^{1,2,3,4,5,6,7,8,9,10})+(Model_Base!$U$40-$A$54*Model_Base!$U$27)*(1+D$52)/($A$54-D$52)/(1+$A$54)^10)/Model_Base!$L$50) | E54: =((Model_Base!$L$48+SUMPRODUCT((Model_Base!$L$40:$U$40-$A$54*Model_Base!$L$27:$U$27)/(1+$A$54)^{1,2,3,4,5,6,7,8,9,10})+(Model_Base!$U$40-$A$54*Model_Base!$U$27)*(1+E$52)/($A$54-E$52)/(1+$A$54)^10)/Model_Base!$L$50) | F54: =((Model_Base!$L$48+SUMPRODUCT((Model_Base!$L$40:$U$40-$A$54*Model_Base!$L$27:$U$27)/(1+$A$54)^{1,2,3,4,5,6,7,8,9,10})+(Model_Base!$U$40-$A$54*Model_Base!$U$27)*(1+F$52)/($A$54-F$52)/(1+$A$54)^10)/Model_Base!$L$50)
A55: =Model_Base!$B$5+0.0 | B55: =((Model_Base!$L$48+SUMPRODUCT((Model_Base!$L$40:$U$40-$A$55*Model_Base!$L$27:$U$27)/(1+$A$55)^{1,2,3,4,5,6,7,8,9,10})+(Model_Base!$U$40-$A$55*Model_Base!$U$27)*(1+B$52)/($A$55-B$52)/(1+$A$55)^10)/Model_Base!$L$50) | C55: =((Model_Base!$L$48+SUMPRODUCT((Model_Base!$L$40:$U$40-$A$55*Model_Base!$L$27:$U$27)/(1+$A$55)^{1,2,3,4,5,6,7,8,9,10})+(Model_Base!$U$40-$A$55*Model_Base!$U$27)*(1+C$52)/($A$55-C$52)/(1+$A$55)^10)/Model_Base!$L$50) | D55: =((Model_Base!$L$48+SUMPRODUCT((Model_Base!$L$40:$U$40-$A$55*Model_Base!$L$27:$U$27)/(1+$A$55)^{1,2,3,4,5,6,7,8,9,10})+(Model_Base!$U$40-$A$55*Model_Base!$U$27)*(1+D$52)/($A$55-D$52)/(1+$A$55)^10)/Model_Base!$L$50) | E55: =((Model_Base!$L$48+SUMPRODUCT((Model_Base!$L$40:$U$40-$A$55*Model_Base!$L$27:$U$27)/(1+$A$55)^{1,2,3,4,5,6,7,8,9,10})+(Model_Base!$U$40-$A$55*Model_Base!$U$27)*(1+E$52)/($A$55-E$52)/(1+$A$55)^10)/Model_Base!$L$50) | F55: =((Model_Base!$L$48+SUMPRODUCT((Model_Base!$L$40:$U$40-$A$55*Model_Base!$L$27:$U$27)/(1+$A$55)^{1,2,3,4,5,6,7,8,9,10})+(Model_Base!$U$40-$A$55*Model_Base!$U$27)*(1+F$52)/($A$55-F$52)/(1+$A$55)^10)/Model_Base!$L$50)
A56: =Model_Base!$B$5+0.01 | B56: =((Model_Base!$L$48+SUMPRODUCT((Model_Base!$L$40:$U$40-$A$56*Model_Base!$L$27:$U$27)/(1+$A$56)^{1,2,3,4,5,6,7,8,9,10})+(Model_Base!$U$40-$A$56*Model_Base!$U$27)*(1+B$52)/($A$56-B$52)/(1+$A$56)^10)/Model_Base!$L$50) | C56: =((Model_Base!$L$48+SUMPRODUCT((Model_Base!$L$40:$U$40-$A$56*Model_Base!$L$27:$U$27)/(1+$A$56)^{1,2,3,4,5,6,7,8,9,10})+(Model_Base!$U$40-$A$56*Model_Base!$U$27)*(1+C$52)/($A$56-C$52)/(1+$A$56)^10)/Model_Base!$L$50) | D56: =((Model_Base!$L$48+SUMPRODUCT((Model_Base!$L$40:$U$40-$A$56*Model_Base!$L$27:$U$27)/(1+$A$56)^{1,2,3,4,5,6,7,8,9,10})+(Model_Base!$U$40-$A$56*Model_Base!$U$27)*(1+D$52)/($A$56-D$52)/(1+$A$56)^10)/Model_Base!$L$50) | E56: =((Model_Base!$L$48+SUMPRODUCT((Model_Base!$L$40:$U$40-$A$56*Model_Base!$L$27:$U$27)/(1+$A$56)^{1,2,3,4,5,6,7,8,9,10})+(Model_Base!$U$40-$A$56*Model_Base!$U$27)*(1+E$52)/($A$56-E$52)/(1+$A$56)^10)/Model_Base!$L$50) | F56: =((Model_Base!$L$48+SUMPRODUCT((Model_Base!$L$40:$U$40-$A$56*Model_Base!$L$27:$U$27)/(1+$A$56)^{1,2,3,4,5,6,7,8,9,10})+(Model_Base!$U$40-$A$56*Model_Base!$U$27)*(1+F$52)/($A$56-F$52)/(1+$A$56)^10)/Model_Base!$L$50)
A57: =Model_Base!$B$5+0.02 | B57: =((Model_Base!$L$48+SUMPRODUCT((Model_Base!$L$40:$U$40-$A$57*Model_Base!$L$27:$U$27)/(1+$A$57)^{1,2,3,4,5,6,7,8,9,10})+(Model_Base!$U$40-$A$57*Model_Base!$U$27)*(1+B$52)/($A$57-B$52)/(1+$A$57)^10)/Model_Base!$L$50) | C57: =((Model_Base!$L$48+SUMPRODUCT((Model_Base!$L$40:$U$40-$A$57*Model_Base!$L$27:$U$27)/(1+$A$57)^{1,2,3,4,5,6,7,8,9,10})+(Model_Base!$U$40-$A$57*Model_Base!$U$27)*(1+C$52)/($A$57-C$52)/(1+$A$57)^10)/Model_Base!$L$50) | D57: =((Model_Base!$L$48+SUMPRODUCT((Model_Base!$L$40:$U$40-$A$57*Model_Base!$L$27:$U$27)/(1+$A$57)^{1,2,3,4,5,6,7,8,9,10})+(Model_Base!$U$40-$A$57*Model_Base!$U$27)*(1+D$52)/($A$57-D$52)/(1+$A$57)^10)/Model_Base!$L$50) | E57: =((Model_Base!$L$48+SUMPRODUCT((Model_Base!$L$40:$U$40-$A$57*Model_Base!$L$27:$U$27)/(1+$A$57)^{1,2,3,4,5,6,7,8,9,10})+(Model_Base!$U$40-$A$57*Model_Base!$U$27)*(1+E$52)/($A$57-E$52)/(1+$A$57)^10)/Model_Base!$L$50) | F57: =((Model_Base!$L$48+SUMPRODUCT((Model_Base!$L$40:$U$40-$A$57*Model_Base!$L$27:$U$27)/(1+$A$57)^{1,2,3,4,5,6,7,8,9,10})+(Model_Base!$U$40-$A$57*Model_Base!$U$27)*(1+F$52)/($A$57-F$52)/(1+$A$57)^10)/Model_Base!$L$50)
A59: SENSITIVITY — IVPS vs Cost of Equity (rows) × Terminal NOPAT Margin (cols), Base case
A60: Ke ↓ / param → | B60: =Model_Base!$U$12-0.03 | C60: =Model_Base!$U$12-0.015 | D60: =Model_Base!$U$12+0.0 | E60: =Model_Base!$U$12+0.015 | F60: =Model_Base!$U$12+0.03
A61: =Model_Base!$B$5-0.02 | B61: =((Model_Base!$L$48+SUMPRODUCT((Model_Base!$L$40:$T$40-$A$61*Model_Base!$L$27:$T$27)/(1+$A$61)^{1,2,3,4,5,6,7,8,9})+(Model_Base!$U$31*B$60-Model_Base!$U$33-$A$61*Model_Base!$U$27)/(1+$A$61)^10+(Model_Base!$U$31*B$60-Model_Base!$U$33-$A$61*Model_Base!$U$27)*(1+Model_Base!$B$9)/($A$61-Model_Base!$B$9)/(1+$A$61)^10)/Model_Base!$L$50) | C61: =((Model_Base!$L$48+SUMPRODUCT((Model_Base!$L$40:$T$40-$A$61*Model_Base!$L$27:$T$27)/(1+$A$61)^{1,2,3,4,5,6,7,8,9})+(Model_Base!$U$31*C$60-Model_Base!$U$33-$A$61*Model_Base!$U$27)/(1+$A$61)^10+(Model_Base!$U$31*C$60-Model_Base!$U$33-$A$61*Model_Base!$U$27)*(1+Model_Base!$B$9)/($A$61-Model_Base!$B$9)/(1+$A$61)^10)/Model_Base!$L$50) | D61: =((Model_Base!$L$48+SUMPRODUCT((Model_Base!$L$40:$T$40-$A$61*Model_Base!$L$27:$T$27)/(1+$A$61)^{1,2,3,4,5,6,7,8,9})+(Model_Base!$U$31*D$60-Model_Base!$U$33-$A$61*Model_Base!$U$27)/(1+$A$61)^10+(Model_Base!$U$31*D$60-Model_Base!$U$33-$A$61*Model_Base!$U$27)*(1+Model_Base!$B$9)/($A$61-Model_Base!$B$9)/(1+$A$61)^10)/Model_Base!$L$50) | E61: =((Model_Base!$L$48+SUMPRODUCT((Model_Base!$L$40:$T$40-$A$61*Model_Base!$L$27:$T$27)/(1+$A$61)^{1,2,3,4,5,6,7,8,9})+(Model_Base!$U$31*E$60-Model_Base!$U$33-$A$61*Model_Base!$U$27)/(1+$A$61)^10+(Model_Base!$U$31*E$60-Model_Base!$U$33-$A$61*Model_Base!$U$27)*(1+Model_Base!$B$9)/($A$61-Model_Base!$B$9)/(1+$A$61)^10)/Model_Base!$L$50) | F61: =((Model_Base!$L$48+SUMPRODUCT((Model_Base!$L$40:$T$40-$A$61*Model_Base!$L$27:$T$27)/(1+$A$61)^{1,2,3,4,5,6,7,8,9})+(Model_Base!$U$31*F$60-Model_Base!$U$33-$A$61*Model_Base!$U$27)/(1+$A$61)^10+(Model_Base!$U$31*F$60-Model_Base!$U$33-$A$61*Model_Base!$U$27)*(1+Model_Base!$B$9)/($A$61-Model_Base!$B$9)/(1+$A$61)^10)/Model_Base!$L$50)
A62: =Model_Base!$B$5-0.01 | B62: =((Model_Base!$L$48+SUMPRODUCT((Model_Base!$L$40:$T$40-$A$62*Model_Base!$L$27:$T$27)/(1+$A$62)^{1,2,3,4,5,6,7,8,9})+(Model_Base!$U$31*B$60-Model_Base!$U$33-$A$62*Model_Base!$U$27)/(1+$A$62)^10+(Model_Base!$U$31*B$60-Model_Base!$U$33-$A$62*Model_Base!$U$27)*(1+Model_Base!$B$9)/($A$62-Model_Base!$B$9)/(1+$A$62)^10)/Model_Base!$L$50) | C62: =((Model_Base!$L$48+SUMPRODUCT((Model_Base!$L$40:$T$40-$A$62*Model_Base!$L$27:$T$27)/(1+$A$62)^{1,2,3,4,5,6,7,8,9})+(Model_Base!$U$31*C$60-Model_Base!$U$33-$A$62*Model_Base!$U$27)/(1+$A$62)^10+(Model_Base!$U$31*C$60-Model_Base!$U$33-$A$62*Model_Base!$U$27)*(1+Model_Base!$B$9)/($A$62-Model_Base!$B$9)/(1+$A$62)^10)/Model_Base!$L$50) | D62: =((Model_Base!$L$48+SUMPRODUCT((Model_Base!$L$40:$T$40-$A$62*Model_Base!$L$27:$T$27)/(1+$A$62)^{1,2,3,4,5,6,7,8,9})+(Model_Base!$U$31*D$60-Model_Base!$U$33-$A$62*Model_Base!$U$27)/(1+$A$62)^10+(Model_Base!$U$31*D$60-Model_Base!$U$33-$A$62*Model_Base!$U$27)*(1+Model_Base!$B$9)/($A$62-Model_Base!$B$9)/(1+$A$62)^10)/Model_Base!$L$50) | E62: =((Model_Base!$L$48+SUMPRODUCT((Model_Base!$L$40:$T$40-$A$62*Model_Base!$L$27:$T$27)/(1+$A$62)^{1,2,3,4,5,6,7,8,9})+(Model_Base!$U$31*E$60-Model_Base!$U$33-$A$62*Model_Base!$U$27)/(1+$A$62)^10+(Model_Base!$U$31*E$60-Model_Base!$U$33-$A$62*Model_Base!$U$27)*(1+Model_Base!$B$9)/($A$62-Model_Base!$B$9)/(1+$A$62)^10)/Model_Base!$L$50) | F62: =((Model_Base!$L$48+SUMPRODUCT((Model_Base!$L$40:$T$40-$A$62*Model_Base!$L$27:$T$27)/(1+$A$62)^{1,2,3,4,5,6,7,8,9})+(Model_Base!$U$31*F$60-Model_Base!$U$33-$A$62*Model_Base!$U$27)/(1+$A$62)^10+(Model_Base!$U$31*F$60-Model_Base!$U$33-$A$62*Model_Base!$U$27)*(1+Model_Base!$B$9)/($A$62-Model_Base!$B$9)/(1+$A$62)^10)/Model_Base!$L$50)
A63: =Model_Base!$B$5+0.0 | B63: =((Model_Base!$L$48+SUMPRODUCT((Model_Base!$L$40:$T$40-$A$63*Model_Base!$L$27:$T$27)/(1+$A$63)^{1,2,3,4,5,6,7,8,9})+(Model_Base!$U$31*B$60-Model_Base!$U$33-$A$63*Model_Base!$U$27)/(1+$A$63)^10+(Model_Base!$U$31*B$60-Model_Base!$U$33-$A$63*Model_Base!$U$27)*(1+Model_Base!$B$9)/($A$63-Model_Base!$B$9)/(1+$A$63)^10)/Model_Base!$L$50) | C63: =((Model_Base!$L$48+SUMPRODUCT((Model_Base!$L$40:$T$40-$A$63*Model_Base!$L$27:$T$27)/(1+$A$63)^{1,2,3,4,5,6,7,8,9})+(Model_Base!$U$31*C$60-Model_Base!$U$33-$A$63*Model_Base!$U$27)/(1+$A$63)^10+(Model_Base!$U$31*C$60-Model_Base!$U$33-$A$63*Model_Base!$U$27)*(1+Model_Base!$B$9)/($A$63-Model_Base!$B$9)/(1+$A$63)^10)/Model_Base!$L$50) | D63: =((Model_Base!$L$48+SUMPRODUCT((Model_Base!$L$40:$T$40-$A$63*Model_Base!$L$27:$T$27)/(1+$A$63)^{1,2,3,4,5,6,7,8,9})+(Model_Base!$U$31*D$60-Model_Base!$U$33-$A$63*Model_Base!$U$27)/(1+$A$63)^10+(Model_Base!$U$31*D$60-Model_Base!$U$33-$A$63*Model_Base!$U$27)*(1+Model_Base!$B$9)/($A$63-Model_Base!$B$9)/(1+$A$63)^10)/Model_Base!$L$50) | E63: =((Model_Base!$L$48+SUMPRODUCT((Model_Base!$L$40:$T$40-$A$63*Model_Base!$L$27:$T$27)/(1+$A$63)^{1,2,3,4,5,6,7,8,9})+(Model_Base!$U$31*E$60-Model_Base!$U$33-$A$63*Model_Base!$U$27)/(1+$A$63)^10+(Model_Base!$U$31*E$60-Model_Base!$U$33-$A$63*Model_Base!$U$27)*(1+Model_Base!$B$9)/($A$63-Model_Base!$B$9)/(1+$A$63)^10)/Model_Base!$L$50) | F63: =((Model_Base!$L$48+SUMPRODUCT((Model_Base!$L$40:$T$40-$A$63*Model_Base!$L$27:$T$27)/(1+$A$63)^{1,2,3,4,5,6,7,8,9})+(Model_Base!$U$31*F$60-Model_Base!$U$33-$A$63*Model_Base!$U$27)/(1+$A$63)^10+(Model_Base!$U$31*F$60-Model_Base!$U$33-$A$63*Model_Base!$U$27)*(1+Model_Base!$B$9)/($A$63-Model_Base!$B$9)/(1+$A$63)^10)/Model_Base!$L$50)
A64: =Model_Base!$B$5+0.01 | B64: =((Model_Base!$L$48+SUMPRODUCT((Model_Base!$L$40:$T$40-$A$64*Model_Base!$L$27:$T$27)/(1+$A$64)^{1,2,3,4,5,6,7,8,9})+(Model_Base!$U$31*B$60-Model_Base!$U$33-$A$64*Model_Base!$U$27)/(1+$A$64)^10+(Model_Base!$U$31*B$60-Model_Base!$U$33-$A$64*Model_Base!$U$27)*(1+Model_Base!$B$9)/($A$64-Model_Base!$B$9)/(1+$A$64)^10)/Model_Base!$L$50) | C64: =((Model_Base!$L$48+SUMPRODUCT((Model_Base!$L$40:$T$40-$A$64*Model_Base!$L$27:$T$27)/(1+$A$64)^{1,2,3,4,5,6,7,8,9})+(Model_Base!$U$31*C$60-Model_Base!$U$33-$A$64*Model_Base!$U$27)/(1+$A$64)^10+(Model_Base!$U$31*C$60-Model_Base!$U$33-$A$64*Model_Base!$U$27)*(1+Model_Base!$B$9)/($A$64-Model_Base!$B$9)/(1+$A$64)^10)/Model_Base!$L$50) | D64: =((Model_Base!$L$48+SUMPRODUCT((Model_Base!$L$40:$T$40-$A$64*Model_Base!$L$27:$T$27)/(1+$A$64)^{1,2,3,4,5,6,7,8,9})+(Model_Base!$U$31*D$60-Model_Base!$U$33-$A$64*Model_Base!$U$27)/(1+$A$64)^10+(Model_Base!$U$31*D$60-Model_Base!$U$33-$A$64*Model_Base!$U$27)*(1+Model_Base!$B$9)/($A$64-Model_Base!$B$9)/(1+$A$64)^10)/Model_Base!$L$50) | E64: =((Model_Base!$L$48+SUMPRODUCT((Model_Base!$L$40:$T$40-$A$64*Model_Base!$L$27:$T$27)/(1+$A$64)^{1,2,3,4,5,6,7,8,9})+(Model_Base!$U$31*E$60-Model_Base!$U$33-$A$64*Model_Base!$U$27)/(1+$A$64)^10+(Model_Base!$U$31*E$60-Model_Base!$U$33-$A$64*Model_Base!$U$27)*(1+Model_Base!$B$9)/($A$64-Model_Base!$B$9)/(1+$A$64)^10)/Model_Base!$L$50) | F64: =((Model_Base!$L$48+SUMPRODUCT((Model_Base!$L$40:$T$40-$A$64*Model_Base!$L$27:$T$27)/(1+$A$64)^{1,2,3,4,5,6,7,8,9})+(Model_Base!$U$31*F$60-Model_Base!$U$33-$A$64*Model_Base!$U$27)/(1+$A$64)^10+(Model_Base!$U$31*F$60-Model_Base!$U$33-$A$64*Model_Base!$U$27)*(1+Model_Base!$B$9)/($A$64-Model_Base!$B$9)/(1+$A$64)^10)/Model_Base!$L$50)
A65: =Model_Base!$B$5+0.02 | B65: =((Model_Base!$L$48+SUMPRODUCT((Model_Base!$L$40:$T$40-$A$65*Model_Base!$L$27:$T$27)/(1+$A$65)^{1,2,3,4,5,6,7,8,9})+(Model_Base!$U$31*B$60-Model_Base!$U$33-$A$65*Model_Base!$U$27)/(1+$A$65)^10+(Model_Base!$U$31*B$60-Model_Base!$U$33-$A$65*Model_Base!$U$27)*(1+Model_Base!$B$9)/($A$65-Model_Base!$B$9)/(1+$A$65)^10)/Model_Base!$L$50) | C65: =((Model_Base!$L$48+SUMPRODUCT((Model_Base!$L$40:$T$40-$A$65*Model_Base!$L$27:$T$27)/(1+$A$65)^{1,2,3,4,5,6,7,8,9})+(Model_Base!$U$31*C$60-Model_Base!$U$33-$A$65*Model_Base!$U$27)/(1+$A$65)^10+(Model_Base!$U$31*C$60-Model_Base!$U$33-$A$65*Model_Base!$U$27)*(1+Model_Base!$B$9)/($A$65-Model_Base!$B$9)/(1+$A$65)^10)/Model_Base!$L$50) | D65: =((Model_Base!$L$48+SUMPRODUCT((Model_Base!$L$40:$T$40-$A$65*Model_Base!$L$27:$T$27)/(1+$A$65)^{1,2,3,4,5,6,7,8,9})+(Model_Base!$U$31*D$60-Model_Base!$U$33-$A$65*Model_Base!$U$27)/(1+$A$65)^10+(Model_Base!$U$31*D$60-Model_Base!$U$33-$A$65*Model_Base!$U$27)*(1+Model_Base!$B$9)/($A$65-Model_Base!$B$9)/(1+$A$65)^10)/Model_Base!$L$50) | E65: =((Model_Base!$L$48+SUMPRODUCT((Model_Base!$L$40:$T$40-$A$65*Model_Base!$L$27:$T$27)/(1+$A$65)^{1,2,3,4,5,6,7,8,9})+(Model_Base!$U$31*E$60-Model_Base!$U$33-$A$65*Model_Base!$U$27)/(1+$A$65)^10+(Model_Base!$U$31*E$60-Model_Base!$U$33-$A$65*Model_Base!$U$27)*(1+Model_Base!$B$9)/($A$65-Model_Base!$B$9)/(1+$A$65)^10)/Model_Base!$L$50) | F65: =((Model_Base!$L$48+SUMPRODUCT((Model_Base!$L$40:$T$40-$A$65*Model_Base!$L$27:$T$27)/(1+$A$65)^{1,2,3,4,5,6,7,8,9})+(Model_Base!$U$31*F$60-Model_Base!$U$33-$A$65*Model_Base!$U$27)/(1+$A$65)^10+(Model_Base!$U$31*F$60-Model_Base!$U$33-$A$65*Model_Base!$U$27)*(1+Model_Base!$B$9)/($A$65-Model_Base!$B$9)/(1+$A$65)^10)/Model_Base!$L$50)
A67: Live grids: each cell recomputes the Base-case IVPS at that Ke/parameter pair (green = current Base, equals Scenario_Summary IVPS). Valuation is most sensitive to Ke, then terminal margin/asset-intensity; terminal growth is muted (RIM terminal is abnormal earnings, not free cash flow).

Sheet Implied Cost of Capital
A1: Alphabet (GOOGL) — Implied Cost of Capital (ICC)
A2: Live ICC: the discount rate at which each scenario's IVPS equals the price in B5. Reactive — recomputes when the price or any model input changes. Model inputs ILLUSTRATIVE; not analysis.
A4: MARKET
A5: Current price (edit here — Scenario_Summary links to this cell) | B5: 363.6
A6: As of | B6: 2026-06-11
A7: Diluted shares (M) | B7: =Model_Base!L50
A8: Market cap ($M) | B8: =B5*B7
A10: MODEL VS PRICE
A11: Scenario | B11: IVPS | C11: vs. price
A12: Bear | B12: =Model_Bear!L51 | C12: =B12/$B$5-1
A13: Base | B13: =Model_Base!L51 | C13: =B13/$B$5-1
A14: Bull | B14: =Model_Bull!L51 | C14: =B14/$B$5-1
A15: Probability-weighted | B15: =SUMPRODUCT(Scenario_Summary!B5:D5,B12:B14) | C15: =B15/$B$5-1
A39: IMPLIED RETURNS (ICC) — live (reactive to the price cell)
A40: ICC = the discount rate at which each scenario’s IVPS equals the price in B5. Recomputes when you change the price or any model assumption (interpolated from the grid below; no macros). Excess = ICC − Ke: positive ⇒ the price implies a return above our hurdle (cheap), negative ⇒ below it.
A42: Scenario | B42: IVPS | C42: Ke (hurdle) | D42: ICC | E42: ICC − Ke | F42: Read
A43: Bear | B43: =Model_Bear!$L$51 | C43: =Model_Bear!$B$5 | D43: =IFERROR(INDEX($H$54:$H$158,MATCH($B$5,$I$54:$I$158,1))+($B$5-INDEX($I$54:$I$158,MATCH($B$5,$I$54:$I$158,1)))/(INDEX($I$54:$I$158,MATCH($B$5,$I$54:$I$158,1)+1)-INDEX($I$54:$I$158,MATCH($B$5,$I$54:$I$158,1)))*(INDEX($H$54:$H$158,MATCH($B$5,$I$54:$I$158,1)+1)-INDEX($H$54:$H$158,MATCH($B$5,$I$54:$I$158,1))),NA()) | E43: =IF(ISNA(D43),"",D43-C43) | F43: =IF(ISNA(D43),IF($B$5>MAX($I$54:$I$158),"price above scenario — overvalued, no positive-excess solution","price below grid (ICC>30%)"),IF(E43>0,"undervalued — price implies return above hurdle","overvalued — price implies return below hurdle"))
A44: Base | B44: =Model_Base!$L$51 | C44: =Model_Base!$B$5 | D44: =IFERROR(INDEX($J$54:$J$158,MATCH($B$5,$K$54:$K$158,1))+($B$5-INDEX($K$54:$K$158,MATCH($B$5,$K$54:$K$158,1)))/(INDEX($K$54:$K$158,MATCH($B$5,$K$54:$K$158,1)+1)-INDEX($K$54:$K$158,MATCH($B$5,$K$54:$K$158,1)))*(INDEX($J$54:$J$158,MATCH($B$5,$K$54:$K$158,1)+1)-INDEX($J$54:$J$158,MATCH($B$5,$K$54:$K$158,1))),NA()) | E44: =IF(ISNA(D44),"",D44-C44) | F44: =IF(ISNA(D44),IF($B$5>MAX($K$54:$K$158),"price above scenario — overvalued, no positive-excess solution","price below grid (ICC>30%)"),IF(E44>0,"undervalued — price implies return above hurdle","overvalued — price implies return below hurdle"))
A45: Bull | B45: =Model_Bull!$L$51 | C45: =Model_Bull!$B$5 | D45: =IFERROR(INDEX($L$54:$L$158,MATCH($B$5,$M$54:$M$158,1))+($B$5-INDEX($M$54:$M$158,MATCH($B$5,$M$54:$M$158,1)))/(INDEX($M$54:$M$158,MATCH($B$5,$M$54:$M$158,1)+1)-INDEX($M$54:$M$158,MATCH($B$5,$M$54:$M$158,1)))*(INDEX($L$54:$L$158,MATCH($B$5,$M$54:$M$158,1)+1)-INDEX($L$54:$L$158,MATCH($B$5,$M$54:$M$158,1))),NA()) | E45: =IF(ISNA(D45),"",D45-C45) | F45: =IF(ISNA(D45),IF($B$5>MAX($M$54:$M$158),"price above scenario — overvalued, no positive-excess solution","price below grid (ICC>30%)"),IF(E45>0,"undervalued — price implies return above hurdle","overvalued — price implies return below hurdle"))
A46: Probability-weighted | B46: =SUMPRODUCT(Scenario_Summary!$B$5:$D$5,B43:B45) | C46: =SUMPRODUCT(Scenario_Summary!$B$5:$D$5,C43:C45) | D46: =SUMPRODUCT(Scenario_Summary!$B$5:$D$5,D43:D45) | E46: =D46-C46 | F46: =IF(E46>0.01,"LEAN BUY",IF(E46<-0.01,"AVOID","FAIR"))
A48: Ranking excess (weighted ICC − Ke) — the universe sort key: | D48: =E46
A49: Price inside the scenario hull? | D49: =IF($B$5<=MAX(B43:B45),"yes","NO — above every scenario IVPS (avoid)")
A51: IVPS-by-discount-rate grid — helper for the interpolation above (do not edit)
H53: r (Bear) | I53: IVPS (Bear) | J53: r (Base) | K53: IVPS (Base) | L53: r (Bull) | M53: IVPS (Bull)
H54: 0.3 | I54: =(Model_Bear!$L$48+SUMPRODUCT((Model_Bear!$L$40:$U$40-$H54*Model_Bear!$L$27:$U$27)/(1+$H54)^{1,2,3,4,5,6,7,8,9,10})+(Model_Bear!$U$40-$H54*Model_Bear!$U$27)*(1+0.035)/($H54-0.035)/(1+$H54)^10)/Model_Bear!$L$50 | J54: 0.3 | K54: =(Model_Base!$L$48+SUMPRODUCT((Model_Base!$L$40:$U$40-$J54*Model_Base!$L$27:$U$27)/(1+$J54)^{1,2,3,4,5,6,7,8,9,10})+(Model_Base!$U$40-$J54*Model_Base!$U$27)*(1+0.04)/($J54-0.04)/(1+$J54)^10)/Model_Base!$L$50 | L54: 0.3 | M54: =(Model_Bull!$L$48+SUMPRODUCT((Model_Bull!$L$40:$U$40-$L54*Model_Bull!$L$27:$U$27)/(1+$L54)^{1,2,3,4,5,6,7,8,9,10})+(Model_Bull!$U$40-$L54*Model_Bull!$U$27)*(1+0.06)/($L54-0.06)/(1+$L54)^10)/Model_Bull!$L$50
H55: 0.29749 | I55: =(Model_Bear!$L$48+SUMPRODUCT((Model_Bear!$L$40:$U$40-$H55*Model_Bear!$L$27:$U$27)/(1+$H55)^{1,2,3,4,5,6,7,8,9,10})+(Model_Bear!$U$40-$H55*Model_Bear!$U$27)*(1+0.035)/($H55-0.035)/(1+$H55)^10)/Model_Bear!$L$50 | J55: 0.297538 | K55: =(Model_Base!$L$48+SUMPRODUCT((Model_Base!$L$40:$U$40-$J55*Model_Base!$L$27:$U$27)/(1+$J55)^{1,2,3,4,5,6,7,8,9,10})+(Model_Base!$U$40-$J55*Model_Base!$U$27)*(1+0.04)/($J55-0.04)/(1+$J55)^10)/Model_Base!$L$50 | L55: 0.297731 | M55: =(Model_Bull!$L$48+SUMPRODUCT((Model_Bull!$L$40:$U$40-$L55*Model_Bull!$L$27:$U$27)/(1+$L55)^{1,2,3,4,5,6,7,8,9,10})+(Model_Bull!$U$40-$L55*Model_Bull!$U$27)*(1+0.06)/($L55-0.06)/(1+$L55)^10)/Model_Bull!$L$50
H56: 0.294981 | I56: =(Model_Bear!$L$48+SUMPRODUCT((Model_Bear!$L$40:$U$40-$H56*Model_Bear!$L$27:$U$27)/(1+$H56)^{1,2,3,4,5,6,7,8,9,10})+(Model_Bear!$U$40-$H56*Model_Bear!$U$27)*(1+0.035)/($H56-0.035)/(1+$H56)^10)/Model_Bear!$L$50 | J56: 0.295077 | K56: =(Model_Base!$L$48+SUMPRODUCT((Model_Base!$L$40:$U$40-$J56*Model_Base!$L$27:$U$27)/(1+$J56)^{1,2,3,4,5,6,7,8,9,10})+(Model_Base!$U$40-$J56*Model_Base!$U$27)*(1+0.04)/($J56-0.04)/(1+$J56)^10)/Model_Base!$L$50 | L56: 0.295462 | M56: =(Model_Bull!$L$48+SUMPRODUCT((Model_Bull!$L$40:$U$40-$L56*Model_Bull!$L$27:$U$27)/(1+$L56)^{1,2,3,4,5,6,7,8,9,10})+(Model_Bull!$U$40-$L56*Model_Bull!$U$27)*(1+0.06)/($L56-0.06)/(1+$L56)^10)/Model_Bull!$L$50
